<?xml version="1.0" encoding="gb2312" ?><?xml-stylesheet type="text/xsl" href="C:\Program Files\National Instruments\TestStand 2012\Components\Models\TestStandModels\ATML\StyleSheets\tr5_horizontal.xsl"?>

<trc:TestResultsCollection xmlns:trc="urn:IEEE-1636.1:2011:01:TestResultsCollection" xmlns:tr="urn:IEEE-1636.1:2011:01:TestResults" xmlns:c="urn:IEEE-1671:2010:Common" xmlns:xsi="http://www.w3.org/2001/XMLSchema-instance" xmlns:ts="www.ni.com/TestStand/ATMLTestResults/2.0">
<trc:TestResults uuid="a39b1bcf-5528-41e9-bdf5-38fdbfeed06d" xmlns:trc="urn:IEEE-1636.1:2011:01:TestResultsCollection" xmlns:tr="urn:IEEE-1636.1:2011:01:TestResults" xmlns:c="urn:IEEE-1671:2010:Common" xmlns:xsi="http://www.w3.org/2001/XMLSchema-instance" xmlns:ts="www.ni.com/TestStand/ATMLTestResults/2.0">
	<tr:Personnel>
		<tr:SystemOperator ID = "administrator" name = "administrator"/>
	</tr:Personnel>
	<tr:ResultSet ID="2344" name = "C:\Bio Rad TestStand_10041194\Main\Bio Rad Teststand.seq#MainSequence" startDateTime = "2021-12-11T06:10:31.044" endDateTime = "2021-12-11T06:13:58.946">
		<tr:Extension>
			<ts:TSStepProperties>
				<ts:StepType>SequenceCall</ts:StepType>
				<ts:StepGroup>Main</ts:StepGroup>
				<ts:BlockLevel value='1'/>
				<ts:Index value='9'/>
				<ts:TotalTime value='207.902'/>
				<ts:ModuleTime value='207.902'/>
			</ts:TSStepProperties>
		</tr:Extension>
		<tr:Outcome value="Aborted" qualifier="Terminated" />
		<tr:SessionAction ID = "2345" name = "Load Bio Rad DLL" startDateTime = "2021-12-11T06:10:31.081"  endDateTime = "2021-12-11T06:10:31.082"  testReferenceID="ID#:vjT50USnYkW0sYJ60awv0D">
			<tr:Extension>
				<ts:TSStepProperties>
					<ts:StepType>Action</ts:StepType>
					<ts:StepGroup>Setup</ts:StepGroup>
					<ts:BlockLevel value='0'/>
					<ts:Index value='0'/>
					<ts:TotalTime value='0.0010202'/>
					<ts:ModuleTime value='0.0010202'/>
				</ts:TSStepProperties>
			</tr:Extension>
			<tr:ActionOutcome value = "Done" />
		</tr:SessionAction>
		<tr:Test ID = "2346" name = "Put UUT" startDateTime = "2021-12-11T06:10:31.098"  endDateTime = "2021-12-11T06:10:32.632"  testReferenceID="ID#:pCsUDaEDBUWb+mCAymOY1A">
			<tr:Extension>
				<ts:TSStepProperties>
					<ts:StepType>PassFailTest</ts:StepType>
					<ts:StepGroup>Main</ts:StepGroup>
					<ts:BlockLevel value='0'/>
					<ts:Index value='0'/>
					<ts:TotalTime value='1.53412'/>
					<ts:ModuleTime value='1.53412'/>
				</ts:TSStepProperties>
			</tr:Extension>
			<tr:Outcome value = "Passed" />
		</tr:Test>
		<tr:SessionAction ID = "2347" name = "DC Power On" startDateTime = "2021-12-11T06:10:32.636"  endDateTime = "2021-12-11T06:10:32.953"  testReferenceID="ID#:f7l0w4KeGUuAgAdvy4llyA">
			<tr:Extension>
				<ts:TSStepProperties>
					<ts:StepType>Action</ts:StepType>
					<ts:StepGroup>Main</ts:StepGroup>
					<ts:BlockLevel value='0'/>
					<ts:Index value='1'/>
					<ts:TotalTime value='0.31705'/>
					<ts:ModuleTime value='0.31705'/>
				</ts:TSStepProperties>
			</tr:Extension>
			<tr:ActionOutcome value = "Done" />
		</tr:SessionAction>
		<tr:SessionAction ID = "2348" name = "AC Power On" startDateTime = "2021-12-11T06:10:32.958"  endDateTime = "2021-12-11T06:10:33.129"  testReferenceID="ID#:GzbbZRerW0KsOfSjLH45uD">
			<tr:Extension>
				<ts:TSStepProperties>
					<ts:StepType>Action</ts:StepType>
					<ts:StepGroup>Main</ts:StepGroup>
					<ts:BlockLevel value='0'/>
					<ts:Index value='2'/>
					<ts:TotalTime value='0.171263'/>
					<ts:ModuleTime value='0.171263'/>
				</ts:TSStepProperties>
			</tr:Extension>
			<tr:ActionOutcome value = "Done" />
		</tr:SessionAction>
		<tr:Test ID = "2349" name = "Find Attached Devices" startDateTime = "2021-12-11T06:10:33.140"  endDateTime = "2021-12-11T06:10:51.512"  testReferenceID="ID#:3/5kcZbtdEezckeONT1yKB">
			<tr:Extension>
				<ts:TSStepProperties>
					<ts:StepType>StringValueTest</ts:StepType>
					<ts:StepGroup>Main</ts:StepGroup>
					<ts:BlockLevel value='0'/>
					<ts:Index value='4'/>
					<ts:TotalTime value='18.3722'/>
					<ts:ModuleTime value='18.3722'/>
				</ts:TSStepProperties>
			</tr:Extension>
			<tr:Outcome value = "Passed" />
			<tr:TestResult ID = "tr741D1211T5246Z883" name = "String">
				<tr:TestData>
					<c:Datum xsi:type="ts:TS_string" flags = "0x2400">
						<c:Value>Success</c:Value>
					</c:Datum>
				</tr:TestData>
				<tr:TestLimits>
					<tr:Limits>
						<c:Expected comparator = "EQ">
							<c:Datum xsi:type="ts:TS_string" flags = "0x0000">
								<c:Value>Success</c:Value>
							</c:Datum>
						</c:Expected>
					</tr:Limits>
				</tr:TestLimits>
			</tr:TestResult>
		</tr:Test>
		<tr:Test ID = "2350" name = "12.8V No Load Test" startDateTime = "2021-12-11T06:10:51.523"  endDateTime = "2021-12-11T06:10:52.823"  testReferenceID="ID#:s2EHM1jn9kGPV9WF3jYYlD">
			<tr:Extension>
				<ts:TSStepProperties>
					<ts:StepType>NumericLimitTest</ts:StepType>
					<ts:StepGroup>Main</ts:StepGroup>
					<ts:BlockLevel value='0'/>
					<ts:Index value='6'/>
					<ts:TotalTime value='1.29955'/>
					<ts:ModuleTime value='1.29955'/>
				</ts:TSStepProperties>
			</tr:Extension>
			<tr:Outcome value = "Passed" />
			<tr:TestResult ID = "tr742D1211T5246Z883" name = "Numeric">
				<tr:TestData>
					<c:Datum value = "12.7786111" xsi:type="ts:TS_double" nonStandardUnit="volt" flags = "0x2400"/>
				</tr:TestData>
				<tr:TestLimits>
					<tr:Limits>
						<c:LimitPair operator = "AND">
							<c:Limit comparator = "GE">
								<c:Datum nonStandardUnit = "volt" value = "12.16" xsi:type="ts:TS_double" flags = "0x0000"/>
							</c:Limit>
							<c:Limit comparator = "LE">
								<c:Datum nonStandardUnit = "volt" value = "13.44" xsi:type="ts:TS_double" flags = "0x0000"/>
							</c:Limit>
						</c:LimitPair>
					</tr:Limits>
				</tr:TestLimits>
			</tr:TestResult>
		</tr:Test>
		<tr:Test ID = "2351" name = "12.8V Load 30W" startDateTime = "2021-12-11T06:10:52.829"  endDateTime = "2021-12-11T06:10:53.978"  testReferenceID="ID#:/PEXBGfFnUy0sBWfu6GovA">
			<tr:Extension>
				<ts:TSStepProperties>
					<ts:StepType>NumericLimitTest</ts:StepType>
					<ts:StepGroup>Main</ts:StepGroup>
					<ts:BlockLevel value='0'/>
					<ts:Index value='7'/>
					<ts:TotalTime value='1.14896'/>
					<ts:ModuleTime value='1.14896'/>
				</ts:TSStepProperties>
			</tr:Extension>
			<tr:Outcome value = "Passed" />
			<tr:TestResult ID = "tr743D1211T5246Z883" name = "Numeric">
				<tr:TestData>
					<c:Datum value = "12.4772806" xsi:type="ts:TS_double" nonStandardUnit="volt" flags = "0x2400"/>
				</tr:TestData>
				<tr:TestLimits>
					<tr:Limits>
						<c:LimitPair operator = "AND">
							<c:Limit comparator = "GE">
								<c:Datum nonStandardUnit = "volt" value = "12.16" xsi:type="ts:TS_double" flags = "0x0000"/>
							</c:Limit>
							<c:Limit comparator = "LE">
								<c:Datum nonStandardUnit = "volt" value = "13.44" xsi:type="ts:TS_double" flags = "0x0000"/>
							</c:Limit>
						</c:LimitPair>
					</tr:Limits>
				</tr:TestLimits>
			</tr:TestResult>
		</tr:Test>
		<tr:Test ID = "2352" name = "5V No Load Test" startDateTime = "2021-12-11T06:10:53.990"  endDateTime = "2021-12-11T06:10:54.725"  testReferenceID="ID#:uT9QBRM1n0S0ZJX7F9++eA">
			<tr:Extension>
				<ts:TSStepProperties>
					<ts:StepType>NumericLimitTest</ts:StepType>
					<ts:StepGroup>Main</ts:StepGroup>
					<ts:BlockLevel value='0'/>
					<ts:Index value='9'/>
					<ts:TotalTime value='0.735318'/>
					<ts:ModuleTime value='0.735318'/>
				</ts:TSStepProperties>
			</tr:Extension>
			<tr:Outcome value = "Passed" />
			<tr:TestResult ID = "tr744D1211T5246Z883" name = "Numeric">
				<tr:TestData>
					<c:Datum value = "5.05904818" xsi:type="ts:TS_double" nonStandardUnit="volt" flags = "0x2400"/>
				</tr:TestData>
				<tr:TestLimits>
					<tr:Limits>
						<c:LimitPair operator = "AND">
							<c:Limit comparator = "GE">
								<c:Datum nonStandardUnit = "volt" value = "4.75" xsi:type="ts:TS_double" flags = "0x0000"/>
							</c:Limit>
							<c:Limit comparator = "LE">
								<c:Datum nonStandardUnit = "volt" value = "5.25" xsi:type="ts:TS_double" flags = "0x0000"/>
							</c:Limit>
						</c:LimitPair>
					</tr:Limits>
				</tr:TestLimits>
			</tr:TestResult>
		</tr:Test>
		<tr:Test ID = "2353" name = "5V 600mA Load" startDateTime = "2021-12-11T06:10:54.731"  endDateTime = "2021-12-11T06:10:55.978"  testReferenceID="ID#:hK5y13WF/UOw/cQ9FI1UED">
			<tr:Extension>
				<ts:TSStepProperties>
					<ts:StepType>NumericLimitTest</ts:StepType>
					<ts:StepGroup>Main</ts:StepGroup>
					<ts:BlockLevel value='0'/>
					<ts:Index value='10'/>
					<ts:TotalTime value='1.24731'/>
					<ts:ModuleTime value='1.24731'/>
				</ts:TSStepProperties>
			</tr:Extension>
			<tr:Outcome value = "Passed" />
			<tr:TestResult ID = "tr745D1211T5246Z883" name = "Numeric">
				<tr:TestData>
					<c:Datum value = "5.04979751" xsi:type="ts:TS_double" nonStandardUnit="volt" flags = "0x2400"/>
				</tr:TestData>
				<tr:TestLimits>
					<tr:Limits>
						<c:LimitPair operator = "AND">
							<c:Limit comparator = "GE">
								<c:Datum nonStandardUnit = "volt" value = "4.75" xsi:type="ts:TS_double" flags = "0x0000"/>
							</c:Limit>
							<c:Limit comparator = "LE">
								<c:Datum nonStandardUnit = "volt" value = "5.25" xsi:type="ts:TS_double" flags = "0x0000"/>
							</c:Limit>
						</c:LimitPair>
					</tr:Limits>
				</tr:TestLimits>
			</tr:TestResult>
		</tr:Test>
		<tr:Test ID = "2354" name = "3.3V Voltage Check" startDateTime = "2021-12-11T06:10:55.990"  endDateTime = "2021-12-11T06:10:56.726"  testReferenceID="ID#:dBBvwB2wHES0ifCY7PD/0B">
			<tr:Extension>
				<ts:TSStepProperties>
					<ts:StepType>NumericLimitTest</ts:StepType>
					<ts:StepGroup>Main</ts:StepGroup>
					<ts:BlockLevel value='0'/>
					<ts:Index value='12'/>
					<ts:TotalTime value='0.736056'/>
					<ts:ModuleTime value='0.736056'/>
				</ts:TSStepProperties>
			</tr:Extension>
			<tr:Outcome value = "Passed" />
			<tr:TestResult ID = "tr746D1211T5246Z883" name = "Numeric">
				<tr:TestData>
					<c:Datum value = "3.31787507" xsi:type="ts:TS_double" nonStandardUnit="volt" flags = "0x2400"/>
				</tr:TestData>
				<tr:TestLimits>
					<tr:Limits>
						<c:LimitPair operator = "AND">
							<c:Limit comparator = "GE">
								<c:Datum nonStandardUnit = "volt" value = "2.85" xsi:type="ts:TS_double" flags = "0x0000"/>
							</c:Limit>
							<c:Limit comparator = "LE">
								<c:Datum nonStandardUnit = "volt" value = "3.45" xsi:type="ts:TS_double" flags = "0x0000"/>
							</c:Limit>
						</c:LimitPair>
					</tr:Limits>
				</tr:TestLimits>
			</tr:TestResult>
		</tr:Test>
		<tr:Test ID = "2355" name = "Battery Voltage Check" startDateTime = "2021-12-11T06:10:56.737"  endDateTime = "2021-12-11T06:10:57.480"  testReferenceID="ID#:9ZyDVNqHmE+lSY/ulKlYSC">
			<tr:Extension>
				<ts:TSStepProperties>
					<ts:StepType>NumericLimitTest</ts:StepType>
					<ts:StepGroup>Main</ts:StepGroup>
					<ts:BlockLevel value='0'/>
					<ts:Index value='14'/>
					<ts:TotalTime value='0.742463'/>
					<ts:ModuleTime value='0.742463'/>
				</ts:TSStepProperties>
			</tr:Extension>
			<tr:Outcome value = "Passed" />
			<tr:TestResult ID = "tr747D1211T5246Z883" name = "Numeric">
				<tr:TestData>
					<c:Datum value = "3.22708978" xsi:type="ts:TS_double" nonStandardUnit="volt" flags = "0x2400"/>
				</tr:TestData>
				<tr:TestLimits>
					<tr:Limits>
						<c:LimitPair operator = "AND">
							<c:Limit comparator = "GE">
								<c:Datum nonStandardUnit = "volt" value = "2.85" xsi:type="ts:TS_double" flags = "0x0000"/>
							</c:Limit>
							<c:Limit comparator = "LE">
								<c:Datum nonStandardUnit = "volt" value = "3.45" xsi:type="ts:TS_double" flags = "0x0000"/>
							</c:Limit>
						</c:LimitPair>
					</tr:Limits>
				</tr:TestLimits>
			</tr:TestResult>
		</tr:Test>
		<tr:SessionAction ID = "2356" name = "Wait 10" startDateTime = "2021-12-11T06:10:57.485"  endDateTime = "2021-12-11T06:11:07.486"  testReferenceID="ID#:731Py5h0n0O4z4TxEZWZlC">
			<tr:Extension>
				<ts:TSStepProperties>
					<ts:StepType>NI_Wait</ts:StepType>
					<ts:StepGroup>Main</ts:StepGroup>
					<ts:BlockLevel value='0'/>
					<ts:Index value='15'/>
					<ts:TotalTime value='10.0005'/>
				</ts:TSStepProperties>
			</tr:Extension>
			<tr:ActionOutcome value = "Done" />
		</tr:SessionAction>
		<tr:Test ID = "2357" name = "Remote Command Set" startDateTime = "2021-12-11T06:11:07.490"  endDateTime = "2021-12-11T06:12:08.365"  testReferenceID="ID#:rwMhfIhvkEGEPElh2WthJB">
			<tr:Extension>
				<ts:TSStepProperties>
					<ts:StepType>PassFailTest</ts:StepType>
					<ts:StepGroup>Main</ts:StepGroup>
					<ts:BlockLevel value='0'/>
					<ts:Index value='16'/>
					<ts:TotalTime value='60.8746'/>
					<ts:ModuleTime value='60.8746'/>
				</ts:TSStepProperties>
			</tr:Extension>
			<tr:Outcome value = "Passed" />
		</tr:Test>
		<tr:Test ID = "2358" name = "Initialize SRAM and HC12" startDateTime = "2021-12-11T06:12:08.366"  endDateTime = "2021-12-11T06:12:17.850"  testReferenceID="ID#:2mvB+Nka+EKbhUY+CDsGaC">
			<tr:Extension>
				<ts:TSStepProperties>
					<ts:StepType>PassFailTest</ts:StepType>
					<ts:StepGroup>Main</ts:StepGroup>
					<ts:BlockLevel value='0'/>
					<ts:Index value='17'/>
					<ts:TotalTime value='9.48415'/>
					<ts:ModuleTime value='9.48415'/>
				</ts:TSStepProperties>
			</tr:Extension>
			<tr:Outcome value = "Passed" />
		</tr:Test>
		<tr:Test ID = "2359" name = "I2C Read Write Test" startDateTime = "2021-12-11T06:12:17.861"  endDateTime = "2021-12-11T06:12:20.869"  testReferenceID="ID#:fJAamqcq2k20eyHGphq6yD">
			<tr:Extension>
				<ts:TSStepProperties>
					<ts:StepType>PassFailTest</ts:StepType>
					<ts:StepGroup>Main</ts:StepGroup>
					<ts:BlockLevel value='0'/>
					<ts:Index value='19'/>
					<ts:TotalTime value='3.00788'/>
					<ts:ModuleTime value='3.00788'/>
				</ts:TSStepProperties>
			</tr:Extension>
			<tr:Outcome value = "Passed" />
			<tr:TestResult ID = "tr748D1211T5246Z883" name = "Alpha VCC">
				<tr:TestData>
					<c:Datum value = "5.0591868375" xsi:type="ts:TS_double" flags = "0x2000"/>
				</tr:TestData>
			</tr:TestResult>
		</tr:Test>
		<tr:Test ID = "2360" name = "Get VCC Sensor Value" startDateTime = "2021-12-11T06:12:20.875"  endDateTime = "2021-12-11T06:12:20.894"  testReferenceID="ID#:lLtihA257EqchQIoLTc4cD">
			<tr:Extension>
				<ts:TSStepProperties>
					<ts:StepType>NumericLimitTest</ts:StepType>
					<ts:StepGroup>Main</ts:StepGroup>
					<ts:BlockLevel value='0'/>
					<ts:Index value='20'/>
					<ts:TotalTime value='0.0191117'/>
					<ts:ModuleTime value='0.0191117'/>
				</ts:TSStepProperties>
			</tr:Extension>
			<tr:Outcome value = "Passed" />
			<tr:TestResult ID = "tr749D1211T5246Z883" name = "Numeric">
				<tr:TestData>
					<c:Datum value = "4.99712" xsi:type="ts:TS_double" nonStandardUnit="volt" flags = "0x2400"/>
				</tr:TestData>
				<tr:TestLimits>
					<tr:Limits>
						<c:LimitPair operator = "AND">
							<c:Limit comparator = "GE">
								<c:Datum nonStandardUnit = "volt" value = "4.75" xsi:type="ts:TS_double" flags = "0x0000"/>
							</c:Limit>
							<c:Limit comparator = "LE">
								<c:Datum nonStandardUnit = "volt" value = "5.25" xsi:type="ts:TS_double" flags = "0x0000"/>
							</c:Limit>
						</c:LimitPair>
					</tr:Limits>
				</tr:TestLimits>
			</tr:TestResult>
		</tr:Test>
		<tr:Test ID = "2361" name = "Get 15V Sensor Value" startDateTime = "2021-12-11T06:12:20.899"  endDateTime = "2021-12-11T06:12:20.912"  testReferenceID="ID#:OXQvCycUQEO2wsMJkgzwsB">
			<tr:Extension>
				<ts:TSStepProperties>
					<ts:StepType>NumericLimitTest</ts:StepType>
					<ts:StepGroup>Main</ts:StepGroup>
					<ts:BlockLevel value='0'/>
					<ts:Index value='21'/>
					<ts:TotalTime value='0.0130905'/>
					<ts:ModuleTime value='0.0130905'/>
				</ts:TSStepProperties>
			</tr:Extension>
			<tr:Outcome value = "Passed" />
			<tr:TestResult ID = "tr750D1211T5246Z883" name = "Numeric">
				<tr:TestData>
					<c:Datum value = "13.13928" xsi:type="ts:TS_double" nonStandardUnit="volt" flags = "0x2400"/>
				</tr:TestData>
				<tr:TestLimits>
					<tr:Limits>
						<c:LimitPair operator = "AND">
							<c:Limit comparator = "GE">
								<c:Datum nonStandardUnit = "volt" value = "12.16" xsi:type="ts:TS_double" flags = "0x0000"/>
							</c:Limit>
							<c:Limit comparator = "LE">
								<c:Datum nonStandardUnit = "volt" value = "13.44" xsi:type="ts:TS_double" flags = "0x0000"/>
							</c:Limit>
						</c:LimitPair>
					</tr:Limits>
				</tr:TestLimits>
			</tr:TestResult>
		</tr:Test>
		<tr:Test ID = "2362" name = "Get Power Sensor Value" startDateTime = "2021-12-11T06:12:20.918"  endDateTime = "2021-12-11T06:12:20.930"  testReferenceID="ID#:tq6ATEHbkk+HI/3GbKMbtB">
			<tr:Extension>
				<ts:TSStepProperties>
					<ts:StepType>NumericLimitTest</ts:StepType>
					<ts:StepGroup>Main</ts:StepGroup>
					<ts:BlockLevel value='0'/>
					<ts:Index value='22'/>
					<ts:TotalTime value='0.0128934'/>
					<ts:ModuleTime value='0.0128934'/>
				</ts:TSStepProperties>
			</tr:Extension>
			<tr:Outcome value = "Passed" />
			<tr:TestResult ID = "tr751D1211T5246Z883" name = "Numeric">
				<tr:TestData>
					<c:Datum value = "39.6204" xsi:type="ts:TS_double" nonStandardUnit="volt" flags = "0x2400"/>
				</tr:TestData>
				<tr:TestLimits>
					<tr:Limits>
						<c:LimitPair operator = "AND">
							<c:Limit comparator = "GE">
								<c:Datum nonStandardUnit = "volt" value = "38" xsi:type="ts:TS_double" flags = "0x0000"/>
							</c:Limit>
							<c:Limit comparator = "LE">
								<c:Datum nonStandardUnit = "volt" value = "42" xsi:type="ts:TS_double" flags = "0x0000"/>
							</c:Limit>
						</c:LimitPair>
					</tr:Limits>
				</tr:TestLimits>
			</tr:TestResult>
		</tr:Test>
		<tr:Test ID = "2363" name = "Lid Left Sensor Test" startDateTime = "2021-12-11T06:12:20.936"  endDateTime = "2021-12-11T06:12:20.951"  testReferenceID="ID#:mtZOusQhZ0aR9DOvVCf06B">
			<tr:Extension>
				<ts:TSStepProperties>
					<ts:StepType>NumericLimitTest</ts:StepType>
					<ts:StepGroup>Main</ts:StepGroup>
					<ts:BlockLevel value='0'/>
					<ts:StepCausedSequenceFailure value='true'/>
					<ts:Index value='23'/>
					<ts:TotalTime value='0.0155137'/>
					<ts:ModuleTime value='0.0155137'/>
				</ts:TSStepProperties>
			</tr:Extension>
			<tr:Outcome value = "Failed" />
			<tr:TestResult ID = "tr752D1211T5246Z883" name = "Numeric">
				<tr:TestData>
					<c:Datum value = "25.3" xsi:type="ts:TS_double" flags = "0x2400"/>
				</tr:TestData>
				<tr:TestLimits>
					<tr:Limits>
						<c:LimitPair operator = "AND">
							<c:Limit comparator = "GE">
								<c:Datum value = "50.179" xsi:type="ts:TS_double" flags = "0x0000"/>
							</c:Limit>
							<c:Limit comparator = "LE">
								<c:Datum value = "55.456" xsi:type="ts:TS_double" flags = "0x0000"/>
							</c:Limit>
						</c:LimitPair>
					</tr:Limits>
				</tr:TestLimits>
			</tr:TestResult>
		</tr:Test>
		<tr:Test ID = "2364" name = "Lid Right Sensor Test" startDateTime = "2021-12-11T06:12:20.955"  endDateTime = "2021-12-11T06:12:20.968"  testReferenceID="ID#:DJXkLSdTrEC0jp7Z2uRpTB">
			<tr:Extension>
				<ts:TSStepProperties>
					<ts:StepType>NumericLimitTest</ts:StepType>
					<ts:StepGroup>Main</ts:StepGroup>
					<ts:BlockLevel value='0'/>
					<ts:Index value='24'/>
					<ts:TotalTime value='0.0133693'/>
					<ts:ModuleTime value='0.0133693'/>
				</ts:TSStepProperties>
			</tr:Extension>
			<tr:Outcome value = "Failed" />
			<tr:TestResult ID = "tr753D1211T5246Z883" name = "Numeric">
				<tr:TestData>
					<c:Datum value = "25.3" xsi:type="ts:TS_double" flags = "0x2400"/>
				</tr:TestData>
				<tr:TestLimits>
					<tr:Limits>
						<c:LimitPair operator = "AND">
							<c:Limit comparator = "GE">
								<c:Datum value = "50.179" xsi:type="ts:TS_double" flags = "0x0000"/>
							</c:Limit>
							<c:Limit comparator = "LE">
								<c:Datum value = "55.456" xsi:type="ts:TS_double" flags = "0x0000"/>
							</c:Limit>
						</c:LimitPair>
					</tr:Limits>
				</tr:TestLimits>
			</tr:TestResult>
		</tr:Test>
		<tr:Test ID = "2365" name = "HS Left Sensor Test" startDateTime = "2021-12-11T06:12:20.972"  endDateTime = "2021-12-11T06:12:20.984"  testReferenceID="ID#:iFTOUj6L7EuXDBSu+DhS4D">
			<tr:Extension>
				<ts:TSStepProperties>
					<ts:StepType>NumericLimitTest</ts:StepType>
					<ts:StepGroup>Main</ts:StepGroup>
					<ts:BlockLevel value='0'/>
					<ts:Index value='25'/>
					<ts:TotalTime value='0.0121794'/>
					<ts:ModuleTime value='0.0121794'/>
				</ts:TSStepProperties>
			</tr:Extension>
			<tr:Outcome value = "Failed" />
			<tr:TestResult ID = "tr754D1211T5246Z883" name = "Numeric">
				<tr:TestData>
					<c:Datum value = "25.3" xsi:type="ts:TS_double" flags = "0x2400"/>
				</tr:TestData>
				<tr:TestLimits>
					<tr:Limits>
						<c:LimitPair operator = "AND">
							<c:Limit comparator = "GE">
								<c:Datum value = "50.179" xsi:type="ts:TS_double" flags = "0x0000"/>
							</c:Limit>
							<c:Limit comparator = "LE">
								<c:Datum value = "55.456" xsi:type="ts:TS_double" flags = "0x0000"/>
							</c:Limit>
						</c:LimitPair>
					</tr:Limits>
				</tr:TestLimits>
			</tr:TestResult>
		</tr:Test>
		<tr:Test ID = "2366" name = "HS Right Sensor Test" startDateTime = "2021-12-11T06:12:20.988"  endDateTime = "2021-12-11T06:12:21.001"  testReferenceID="ID#:WyP2dWG4mUyCXhu6wF0rwB">
			<tr:Extension>
				<ts:TSStepProperties>
					<ts:StepType>NumericLimitTest</ts:StepType>
					<ts:StepGroup>Main</ts:StepGroup>
					<ts:BlockLevel value='0'/>
					<ts:Index value='26'/>
					<ts:TotalTime value='0.0127542'/>
					<ts:ModuleTime value='0.0127542'/>
				</ts:TSStepProperties>
			</tr:Extension>
			<tr:Outcome value = "Failed" />
			<tr:TestResult ID = "tr755D1211T5246Z883" name = "Numeric">
				<tr:TestData>
					<c:Datum value = "25.3" xsi:type="ts:TS_double" flags = "0x2400"/>
				</tr:TestData>
				<tr:TestLimits>
					<tr:Limits>
						<c:LimitPair operator = "AND">
							<c:Limit comparator = "GE">
								<c:Datum value = "50.179" xsi:type="ts:TS_double" flags = "0x0000"/>
							</c:Limit>
							<c:Limit comparator = "LE">
								<c:Datum value = "55.456" xsi:type="ts:TS_double" flags = "0x0000"/>
							</c:Limit>
						</c:LimitPair>
					</tr:Limits>
				</tr:TestLimits>
			</tr:TestResult>
		</tr:Test>
		<tr:Test ID = "2367" name = "Get Amp2 Sensor Value" startDateTime = "2021-12-11T06:12:21.004"  endDateTime = "2021-12-11T06:12:21.016"  testReferenceID="ID#:+cEzB3eXu0GAFph0u4nGdD">
			<tr:Extension>
				<ts:TSStepProperties>
					<ts:StepType>NumericLimitTest</ts:StepType>
					<ts:StepGroup>Main</ts:StepGroup>
					<ts:BlockLevel value='0'/>
					<ts:Index value='27'/>
					<ts:TotalTime value='0.0115475'/>
					<ts:ModuleTime value='0.0115475'/>
				</ts:TSStepProperties>
			</tr:Extension>
			<tr:Outcome value = "Passed" />
			<tr:TestResult ID = "tr756D1211T5246Z883" name = "Numeric">
				<tr:TestData>
					<c:Datum value = "23.8" xsi:type="ts:TS_double" nonStandardUnit="degrees Celsius" flags = "0x2400"/>
				</tr:TestData>
				<tr:TestLimits>
					<tr:Limits>
						<c:LimitPair operator = "AND">
							<c:Limit comparator = "GE">
								<c:Datum nonStandardUnit = "degrees Celsius" value = "0" xsi:type="ts:TS_double" flags = "0x0000"/>
							</c:Limit>
							<c:Limit comparator = "LE">
								<c:Datum nonStandardUnit = "degrees Celsius" value = "50" xsi:type="ts:TS_double" flags = "0x0000"/>
							</c:Limit>
						</c:LimitPair>
					</tr:Limits>
				</tr:TestLimits>
			</tr:TestResult>
		</tr:Test>
		<tr:Test ID = "2368" name = "Get Amp Sensor Value" startDateTime = "2021-12-11T06:12:21.019"  endDateTime = "2021-12-11T06:12:21.032"  testReferenceID="ID#:ZeBOXyeCEkK/Q4rhF/s1TC">
			<tr:Extension>
				<ts:TSStepProperties>
					<ts:StepType>NumericLimitTest</ts:StepType>
					<ts:StepGroup>Main</ts:StepGroup>
					<ts:BlockLevel value='0'/>
					<ts:Index value='28'/>
					<ts:TotalTime value='0.0124921'/>
					<ts:ModuleTime value='0.0124921'/>
				</ts:TSStepProperties>
			</tr:Extension>
			<tr:Outcome value = "Passed" />
			<tr:TestResult ID = "tr757D1211T5246Z883" name = "Numeric">
				<tr:TestData>
					<c:Datum value = "23.1" xsi:type="ts:TS_double" nonStandardUnit="degrees Celsius" flags = "0x2400"/>
				</tr:TestData>
				<tr:TestLimits>
					<tr:Limits>
						<c:LimitPair operator = "AND">
							<c:Limit comparator = "GE">
								<c:Datum nonStandardUnit = "degrees Celsius" value = "0" xsi:type="ts:TS_double" flags = "0x0000"/>
							</c:Limit>
							<c:Limit comparator = "LE">
								<c:Datum nonStandardUnit = "degrees Celsius" value = "50" xsi:type="ts:TS_double" flags = "0x0000"/>
							</c:Limit>
						</c:LimitPair>
					</tr:Limits>
				</tr:TestLimits>
			</tr:TestResult>
		</tr:Test>
		<tr:Test ID = "2369" name = "Get Power Supply Sensor Value" startDateTime = "2021-12-11T06:12:21.036"  endDateTime = "2021-12-11T06:12:21.049"  testReferenceID="ID#:XJyw3lUbfk+DGfORDTDmaA">
			<tr:Extension>
				<ts:TSStepProperties>
					<ts:StepType>NumericLimitTest</ts:StepType>
					<ts:StepGroup>Main</ts:StepGroup>
					<ts:BlockLevel value='0'/>
					<ts:Index value='29'/>
					<ts:TotalTime value='0.0129728'/>
					<ts:ModuleTime value='0.0129728'/>
				</ts:TSStepProperties>
			</tr:Extension>
			<tr:Outcome value = "Passed" />
			<tr:TestResult ID = "tr758D1211T5246Z883" name = "Numeric">
				<tr:TestData>
					<c:Datum value = "25.3" xsi:type="ts:TS_double" nonStandardUnit="degrees Celsius" flags = "0x2400"/>
				</tr:TestData>
				<tr:TestLimits>
					<tr:Limits>
						<c:LimitPair operator = "AND">
							<c:Limit comparator = "GE">
								<c:Datum nonStandardUnit = "degrees Celsius" value = "-50" xsi:type="ts:TS_double" flags = "0x0000"/>
							</c:Limit>
							<c:Limit comparator = "LE">
								<c:Datum nonStandardUnit = "degrees Celsius" value = "50" xsi:type="ts:TS_double" flags = "0x0000"/>
							</c:Limit>
						</c:LimitPair>
					</tr:Limits>
				</tr:TestLimits>
			</tr:TestResult>
		</tr:Test>
		<tr:Test ID = "2370" name = "SRAM Page 0 Check" startDateTime = "2021-12-11T06:12:21.056"  endDateTime = "2021-12-11T06:13:16.655"  testReferenceID="ID#:3kcqtTylf0K2d4hJ13c0gD">
			<tr:Extension>
				<ts:TSStepProperties>
					<ts:StepType>PassFailTest</ts:StepType>
					<ts:StepGroup>Main</ts:StepGroup>
					<ts:BlockLevel value='0'/>
					<ts:Index value='31'/>
					<ts:TotalTime value='55.5993'/>
					<ts:ModuleTime value='55.5993'/>
				</ts:TSStepProperties>
			</tr:Extension>
			<tr:Outcome value = "Passed" />
		</tr:Test>
		<tr:Test ID = "2371" name = "SRAM Page 1 Check" startDateTime = "2021-12-11T06:13:16.665"  endDateTime = "2021-12-11T06:13:17.244"  testReferenceID="ID#:che6FvrUSUa/xqqXpET9gD">
			<tr:Extension>
				<ts:TSStepProperties>
					<ts:StepType>PassFailTest</ts:StepType>
					<ts:StepGroup>Main</ts:StepGroup>
					<ts:BlockLevel value='0'/>
					<ts:Index value='32'/>
					<ts:TotalTime value='0.579171'/>
					<ts:ModuleTime value='0.579171'/>
				</ts:TSStepProperties>
			</tr:Extension>
			<tr:Outcome value = "Passed" />
		</tr:Test>
		<tr:Test ID = "2372" name = "SRAM Page 2 Check" startDateTime = "2021-12-11T06:13:17.249"  endDateTime = "2021-12-11T06:13:17.751"  testReferenceID="ID#:cNXE9UJMRU6lposNdl02BA">
			<tr:Extension>
				<ts:TSStepProperties>
					<ts:StepType>PassFailTest</ts:StepType>
					<ts:StepGroup>Main</ts:StepGroup>
					<ts:BlockLevel value='0'/>
					<ts:Index value='33'/>
					<ts:TotalTime value='0.501925'/>
					<ts:ModuleTime value='0.501925'/>
				</ts:TSStepProperties>
			</tr:Extension>
			<tr:Outcome value = "Passed" />
		</tr:Test>
		<tr:Test ID = "2373" name = "SRAM Page 3 Check" startDateTime = "2021-12-11T06:13:17.756"  endDateTime = "2021-12-11T06:13:18.259"  testReferenceID="ID#:YqGUbJEF9EWgJpk574R7qA">
			<tr:Extension>
				<ts:TSStepProperties>
					<ts:StepType>PassFailTest</ts:StepType>
					<ts:StepGroup>Main</ts:StepGroup>
					<ts:BlockLevel value='0'/>
					<ts:Index value='34'/>
					<ts:TotalTime value='0.502212'/>
					<ts:ModuleTime value='0.502212'/>
				</ts:TSStepProperties>
			</tr:Extension>
			<tr:Outcome value = "Passed" />
		</tr:Test>
		<tr:Test ID = "2374" name = "Power Cycle Unit" startDateTime = "2021-12-11T06:13:18.260"  endDateTime = "2021-12-11T06:13:43.543"  testReferenceID="ID#:FIYuItwZckyYuf6JOYOSVD">
			<tr:Extension>
				<ts:TSStepProperties>
					<ts:StepType>PassFailTest</ts:StepType>
					<ts:StepGroup>Main</ts:StepGroup>
					<ts:BlockLevel value='0'/>
					<ts:Index value='35'/>
					<ts:TotalTime value='25.2825'/>
					<ts:ModuleTime value='25.2825'/>
				</ts:TSStepProperties>
			</tr:Extension>
			<tr:Outcome value = "Aborted" qualifier= "Terminated" />
		</tr:Test>
		<tr:SessionAction ID = "2375" name = "Power Off" startDateTime = "2021-12-11T06:13:43.543"  endDateTime = "2021-12-11T06:13:43.605"  testReferenceID="ID#:+HcHQC/MrEW6zKqBfNUvNB">
			<tr:Extension>
				<ts:TSStepProperties>
					<ts:StepType>Action</ts:StepType>
					<ts:StepGroup>Cleanup</ts:StepGroup>
					<ts:BlockLevel value='0'/>
					<ts:Index value='0'/>
					<ts:TotalTime value='0.0628953'/>
					<ts:ModuleTime value='0.0628953'/>
				</ts:TSStepProperties>
			</tr:Extension>
			<tr:ActionOutcome value = "Done" />
		</tr:SessionAction>
		<tr:SessionAction ID = "2376" name = "DC Power Off" startDateTime = "2021-12-11T06:13:43.606"  endDateTime = "2021-12-11T06:13:43.920"  testReferenceID="ID#:uHxAHNpOc02A2ZVKR0dFLB">
			<tr:Extension>
				<ts:TSStepProperties>
					<ts:StepType>Action</ts:StepType>
					<ts:StepGroup>Cleanup</ts:StepGroup>
					<ts:BlockLevel value='0'/>
					<ts:Index value='1'/>
					<ts:TotalTime value='0.314419'/>
					<ts:ModuleTime value='0.314419'/>
				</ts:TSStepProperties>
			</tr:Extension>
			<tr:ActionOutcome value = "Done" />
		</tr:SessionAction>
		<tr:SessionAction ID = "2377" name = "Wait 10" startDateTime = "2021-12-11T06:13:43.920"  endDateTime = "2021-12-11T06:13:58.920"  testReferenceID="ID#:vYX24mrHDEm0g32FqlewxC">
			<tr:Extension>
				<ts:TSStepProperties>
					<ts:StepType>NI_Wait</ts:StepType>
					<ts:StepGroup>Cleanup</ts:StepGroup>
					<ts:BlockLevel value='0'/>
					<ts:Index value='2'/>
					<ts:TotalTime value='15.0003'/>
				</ts:TSStepProperties>
			</tr:Extension>
			<tr:ActionOutcome value = "Done" />
		</tr:SessionAction>
	</tr:ResultSet>
	<tr:TestProgram>
		<c:SerialNumber>
			CFTP7
		</c:SerialNumber>
		<tr:Configuration>
			<c:Collection xsi:type="ts:TS_Collection" flags = "0x0000">
				<c:Item name = "IncludeTSExtensionElements">
					<c:Datum value = "true" xsi:type="ts:TS_boolean" flags = "0x0000"/>
				</c:Item>
				<c:Item name = "IncludeAttributes">
					<c:Datum value = "false" xsi:type="ts:TS_boolean" flags = "0x0000"/>
				</c:Item>
				<c:Item name = "IncludeLimits">
					<c:Datum value = "true" xsi:type="ts:TS_boolean" flags = "0x0000"/>
				</c:Item>
				<c:Item name = "IncludeMeasurements">
					<c:Datum value = "true" xsi:type="ts:TS_boolean" flags = "0x0000"/>
				</c:Item>
				<c:Item name = "IncludeArrayMeasurement">
					<c:Datum value = "2" xsi:type="ts:TS_double" flags = "0x0000"/>
				</c:Item>
				<c:Item name = "ArrayMeasurementFilter">
					<c:Datum value = "3" xsi:type="ts:TS_double" flags = "0x0000"/>
				</c:Item>
				<c:Item name = "ArrayMeasurementMax">
					<c:Datum value = "100" xsi:type="ts:TS_double" flags = "0x0000"/>
				</c:Item>
				<c:Item name = "IncludeTimes">
					<c:Datum value = "true" xsi:type="ts:TS_boolean" flags = "0x0000"/>
				</c:Item>
				<c:Item name = "Format">
					<c:Datum xsi:type="ts:TS_string" flags = "0x0000">
						<c:Value>xml</c:Value>
					</c:Datum>
				</c:Item>
				<c:Item name = "NumericFormat">
					<c:Datum xsi:type="ts:TS_string" flags = "0x0000">
						<c:Value>%$.13g</c:Value>
					</c:Datum>
				</c:Item>
				<c:Item name = "ResultFilterExpression">
					<c:Datum xsi:type="ts:TS_string" flags = "0x0000">
						<c:Value>True</c:Value>
					</c:Datum>
				</c:Item>
				<c:Item name = "GeneratePath">
					<c:Datum value = "true" xsi:type="ts:TS_boolean" flags = "0x0000"/>
				</c:Item>
				<c:Item name = "UseTemporaryFile">
					<c:Datum value = "false" xsi:type="ts:TS_boolean" flags = "0x0000"/>
				</c:Item>
				<c:Item name = "UseSequenceFileNameAsPrefix">
					<c:Datum value = "true" xsi:type="ts:TS_boolean" flags = "0x0000"/>
				</c:Item>
				<c:Item name = "AddTimeAndDateToFileName">
					<c:Datum value = "true" xsi:type="ts:TS_boolean" flags = "0x0000"/>
				</c:Item>
				<c:Item name = "NewFileNameForEachUUT">
					<c:Datum value = "true" xsi:type="ts:TS_boolean" flags = "0x0000"/>
				</c:Item>
				<c:Item name = "ForceFileNameToBeUnique">
					<c:Datum value = "true" xsi:type="ts:TS_boolean" flags = "0x0000"/>
				</c:Item>
				<c:Item name = "AppendToFileIfItExists">
					<c:Datum value = "false" xsi:type="ts:TS_boolean" flags = "0x0000"/>
				</c:Item>
				<c:Item name = "DirectoryType">
					<c:Datum xsi:type="ts:TS_string" flags = "0x0000">
						<c:Value>SpecifyByExpression</c:Value>
					</c:Datum>
				</c:Item>
				<c:Item name = "Directory">
					<c:Datum xsi:type="ts:TS_string" flags = "0x0000">
						<c:Value></c:Value>
					</c:Datum>
				</c:Item>
				<c:Item name = "BaseName">
					<c:Datum xsi:type="ts:TS_string" flags = "0x0000">
						<c:Value>Report</c:Value>
					</c:Datum>
				</c:Item>
				<c:Item name = "UseFormatForExtension">
					<c:Datum value = "true" xsi:type="ts:TS_boolean" flags = "0x0000"/>
				</c:Item>
				<c:Item name = "Extension">
					<c:Datum xsi:type="ts:TS_string" flags = "0x0000">
						<c:Value></c:Value>
					</c:Datum>
				</c:Item>
				<c:Item name = "ReportFilePath">
					<c:Datum xsi:type="ts:TS_string" flags = "0x0000">
						<c:Value></c:Value>
					</c:Datum>
				</c:Item>
				<c:Item name = "DisableReportGeneration">
					<c:Datum value = "false" xsi:type="ts:TS_boolean" flags = "0x0000"/>
				</c:Item>
				<c:Item name = "IncludeStepResults">
					<c:Datum value = "true" xsi:type="ts:TS_boolean" flags = "0x0000"/>
				</c:Item>
				<c:Item name = "BodyGenerator">
					<c:Datum xsi:type="ts:TS_string" flags = "0x0000">
						<c:Value>DLL</c:Value>
					</c:Datum>
				</c:Item>
				<c:Item name = "Colors">
					<c:Collection xsi:type="ts:TS_Collection" flags = "0x0000">
						<c:Item name = "LabelBg">
							<c:Datum xsi:type="ts:TS_string" flags = "0x0000">
								<c:Value>#FFFFFF</c:Value>
							</c:Datum>
						</c:Item>
						<c:Item name = "ValueBg">
							<c:Datum xsi:type="ts:TS_string" flags = "0x0000">
								<c:Value>#32FFFF</c:Value>
							</c:Datum>
						</c:Item>
						<c:Item name = "UUTSeparator">
							<c:Datum xsi:type="ts:TS_string" flags = "0x0000">
								<c:Value>#0000E0</c:Value>
							</c:Datum>
						</c:Item>
						<c:Item name = "HeaderSeparator">
							<c:Datum xsi:type="ts:TS_string" flags = "0x0000">
								<c:Value>#8000CC</c:Value>
							</c:Datum>
						</c:Item>
						<c:Item name = "TableBorder">
							<c:Datum xsi:type="ts:TS_string" flags = "0x0000">
								<c:Value>#000000</c:Value>
							</c:Datum>
						</c:Item>
						<c:Item name = "MainBg">
							<c:Datum xsi:type="ts:TS_string" flags = "0x0000">
								<c:Value>#00C4C4</c:Value>
							</c:Datum>
						</c:Item>
						<c:Item name = "SetupBg">
							<c:Datum xsi:type="ts:TS_string" flags = "0x0000">
								<c:Value>#FF8000</c:Value>
							</c:Datum>
						</c:Item>
						<c:Item name = "CleanupBg">
							<c:Datum xsi:type="ts:TS_string" flags = "0x0000">
								<c:Value>#ADD8E6</c:Value>
							</c:Datum>
						</c:Item>
						<c:Item name = "ReportTextBg">
							<c:Datum xsi:type="ts:TS_string" flags = "0x0000">
								<c:Value>#FF32CC</c:Value>
							</c:Datum>
						</c:Item>
						<c:Item name = "Terminated">
							<c:Datum xsi:type="ts:TS_string" flags = "0x0000">
								<c:Value>#000080</c:Value>
							</c:Datum>
						</c:Item>
						<c:Item name = "Failed">
							<c:Datum xsi:type="ts:TS_string" flags = "0x0000">
								<c:Value>#FF0000</c:Value>
							</c:Datum>
						</c:Item>
						<c:Item name = "Error">
							<c:Datum xsi:type="ts:TS_string" flags = "0x0000">
								<c:Value>#FF0000</c:Value>
							</c:Datum>
						</c:Item>
						<c:Item name = "Passed">
							<c:Datum xsi:type="ts:TS_string" flags = "0x0000">
								<c:Value>#008000</c:Value>
							</c:Datum>
						</c:Item>
						<c:Item name = "Skipped">
							<c:Datum xsi:type="ts:TS_string" flags = "0x0000">
								<c:Value>#B98028</c:Value>
							</c:Datum>
						</c:Item>
						<c:Item name = "Done">
							<c:Datum xsi:type="ts:TS_string" flags = "0x0000">
								<c:Value>#008000</c:Value>
							</c:Datum>
						</c:Item>
						<c:Item name = "Running">
							<c:Datum xsi:type="ts:TS_string" flags = "0x0000">
								<c:Value>#FFCC33</c:Value>
							</c:Datum>
						</c:Item>
						<c:Item name = "TerminatedBg">
							<c:Datum xsi:type="ts:TS_string" flags = "0x0000">
								<c:Value>#0000FF</c:Value>
							</c:Datum>
						</c:Item>
						<c:Item name = "FailedBg">
							<c:Datum xsi:type="ts:TS_string" flags = "0x0000">
								<c:Value>#FF0000</c:Value>
							</c:Datum>
						</c:Item>
						<c:Item name = "ErrorBg">
							<c:Datum xsi:type="ts:TS_string" flags = "0x0000">
								<c:Value>#FF0000</c:Value>
							</c:Datum>
						</c:Item>
						<c:Item name = "PassedBg">
							<c:Datum xsi:type="ts:TS_string" flags = "0x0000">
								<c:Value>#00FF00</c:Value>
							</c:Datum>
						</c:Item>
						<c:Item name = "SkippedBg">
							<c:Datum xsi:type="ts:TS_string" flags = "0x0000">
								<c:Value>#FFFF00</c:Value>
							</c:Datum>
						</c:Item>
						<c:Item name = "DoneBg">
							<c:Datum xsi:type="ts:TS_string" flags = "0x0000">
								<c:Value>#00FFCC</c:Value>
							</c:Datum>
						</c:Item>
						<c:Item name = "RunningBg">
							<c:Datum xsi:type="ts:TS_string" flags = "0x0000">
								<c:Value>#FFCC33</c:Value>
							</c:Datum>
						</c:Item>
						<c:Item name = "FailureStackLabelBg">
							<c:Datum xsi:type="ts:TS_string" flags = "0x0000">
								<c:Value>#FF2020</c:Value>
							</c:Datum>
						</c:Item>
						<c:Item name = "FailureStackValueBg">
							<c:Datum xsi:type="ts:TS_string" flags = "0x0000">
								<c:Value>#D0D0D0</c:Value>
							</c:Datum>
						</c:Item>
						<c:Item name = "BatchHeadingBg">
							<c:Datum xsi:type="ts:TS_string" flags = "0x0000">
								<c:Value>#00C4C4</c:Value>
							</c:Datum>
						</c:Item>
					</c:Collection>
				</c:Item>
				<c:Item name = "DateAndTimeFormat">
					<c:Datum xsi:type="ts:TS_string" flags = "0x0000">
						<c:Value>TimeFirst</c:Value>
					</c:Datum>
				</c:Item>
				<c:Item name = "NewFileNameForEachBatch">
					<c:Datum value = "false" xsi:type="ts:TS_boolean" flags = "0x0000"/>
				</c:Item>
				<c:Item name = "NewBatchFileNameForEachBatch">
					<c:Datum value = "false" xsi:type="ts:TS_boolean" flags = "0x0000"/>
				</c:Item>
				<c:Item name = "NewFileNameForEachTestSocket">
					<c:Datum value = "false" xsi:type="ts:TS_boolean" flags = "0x0000"/>
				</c:Item>
				<c:Item name = "StoreUUTReportWithBatchReport">
					<c:Datum value = "true" xsi:type="ts:TS_boolean" flags = "0x0000"/>
				</c:Item>
				<c:Item name = "BatchBaseName">
					<c:Datum xsi:type="ts:TS_string" flags = "0x0000">
						<c:Value>BatchReport</c:Value>
					</c:Datum>
				</c:Item>
				<c:Item name = "LabelSize">
					<c:Datum value = "26" xsi:type="ts:TS_double" flags = "0x0000"/>
				</c:Item>
				<c:Item name = "RelStylesheetPath">
					<c:Datum xsi:type="ts:TS_string" flags = "0x0000">
						<c:Value>tr5_horizontal.xsl</c:Value>
					</c:Datum>
				</c:Item>
				<c:Item name = "StylesheetPath">
					<c:Datum xsi:type="ts:TS_string" flags = "0x0000">
						<c:Value>C:\Program Files\National Instruments\TestStand 2012\Components\Models\TestStandModels\ATML\StyleSheets\tr5_horizontal.xsl</c:Value>
					</c:Datum>
				</c:Item>
				<c:Item name = "StylesheetMRU">
					<c:IndexedArray dimensions="[5]" lowerBounds="[0]" upperBounds="[4]" xsi:type="ts:TS_stringArray" flags = "0x0000">
						<ts:Element position ="[0]">
							<c:Value>horizontal.xsl</c:Value>
						</ts:Element>
						<ts:Element position ="[1]">
							<c:Value>report.xsl</c:Value>
						</ts:Element>
						<ts:Element position ="[2]">
							<c:Value>expand.xsl</c:Value>
						</ts:Element>
						<ts:Element position ="[3]">
							<c:Value></c:Value>
						</ts:Element>
						<ts:Element position ="[4]">
							<c:Value></c:Value>
						</ts:Element>
					</c:IndexedArray>
				</c:Item>
				<c:Item name = "ATMLStylesheetMRU">
					<c:IndexedArray dimensions="[3]" lowerBounds="[0]" upperBounds="[2]" xsi:type="ts:TS_stringArray" flags = "0x0000">
						<ts:Element position ="[0]">
							<c:Value>TR_horizontal.xsl</c:Value>
						</ts:Element>
						<ts:Element position ="[1]">
							<c:Value>trml.xsl</c:Value>
						</ts:Element>
						<ts:Element position ="[2]">
							<c:Value></c:Value>
						</ts:Element>
					</c:IndexedArray>
				</c:Item>
				<c:Item name = "StoreStylesheetAbsolutePath">
					<c:Datum value = "true" xsi:type="ts:TS_boolean" flags = "0x0000"/>
				</c:Item>
				<c:Item name = "ProcessOnTheFly">
					<c:Datum value = "false" xsi:type="ts:TS_boolean" flags = "0x0000"/>
				</c:Item>
				<c:Item name = "PurgeOnTheFlyResults">
					<c:Datum value = "false" xsi:type="ts:TS_boolean" flags = "0x0000"/>
				</c:Item>
				<c:Item name = "IncludeStepResultComments">
					<c:Datum value = "true" xsi:type="ts:TS_boolean" flags = "0x0000"/>
				</c:Item>
				<c:Item name = "UseLocalizedDecimalPoint">
					<c:Datum value = "false" xsi:type="ts:TS_boolean" flags = "0x0000"/>
				</c:Item>
				<c:Item name = "ReportStyle">
					<c:Datum xsi:type="ts:TS_string" flags = "0x0000">
						<c:Value>ATML5</c:Value>
					</c:Datum>
				</c:Item>
				<c:Item name = "ReportFileSequentialModelExpression">
					<c:Datum xsi:type="ts:TS_string" flags = "0x0000">
						<c:Value><![CDATA["<ClientFileDir>\\TestReport_<ClientFileName>\\<ClientFileName>_Report[<UUT>][<FileTime>][<FileDate>][<UUTStatus>]<Unique>.<FileExtension>"]]></c:Value>
					</c:Datum>
				</c:Item>
				<c:Item name = "ReportFileParallelModelExpression">
					<c:Datum xsi:type="ts:TS_string" flags = "0x0000">
						<c:Value><![CDATA["<ClientFileDir>\\<ClientFileName>_Report[<FileTime>][<FileDate>]<Unique>.<FileExtension>"]]></c:Value>
					</c:Datum>
				</c:Item>
				<c:Item name = "ReportFileBatchModelExpression">
					<c:Datum xsi:type="ts:TS_string" flags = "0x0000">
						<c:Value><![CDATA["<ClientFileDir>\\<ClientFileName>_BatchReport[<FileTime>][<FileDate>]<Unique>.<FileExtension>"]]></c:Value>
					</c:Datum>
				</c:Item>
				<c:Item name = "BatchFileBatchModelExpression">
					<c:Datum xsi:type="ts:TS_string" flags = "0x0000">
						<c:Value><![CDATA["<ClientFileDir>\\<ClientFileName>_BatchReport[<FileTime>][<FileDate>]<Unique>.<FileExtension>"]]></c:Value>
					</c:Datum>
				</c:Item>
				<c:Item name = "NewFileNameForEachUUTStatus">
					<c:Datum value = "true" xsi:type="ts:TS_boolean" flags = "0x0000"/>
				</c:Item>
				<c:Item name = "ReportPathMacroListString">
					<c:Datum xsi:type="ts:TS_string" flags = "0x0000">
						<c:Value><![CDATA[<CLIENTFILEDIR><CLIENTFILENAME><CLIENTFILENAME><UUT><FILETIME><FILEDATE><UUTSTATUS><UNIQUE><FILEEXTENSION>]]></c:Value>
					</c:Datum>
				</c:Item>
				<c:Item name = "BatchReportPathMacroListString">
					<c:Datum xsi:type="ts:TS_string" flags = "0x0000">
						<c:Value></c:Value>
					</c:Datum>
				</c:Item>
				<c:Item name = "CheckIfMacroListIsUnchanged">
					<c:Datum value = "true" xsi:type="ts:TS_boolean" flags = "0x0000"/>
				</c:Item>
				<c:Item name = "ATML5StylesheetMRU">
					<c:IndexedArray dimensions="[3]" lowerBounds="[0]" upperBounds="[2]" xsi:type="ts:TS_stringArray" flags = "0x0000">
						<ts:Element position ="[0]">
							<c:Value>tr5_horizontal.xsl</c:Value>
						</ts:Element>
						<ts:Element position ="[1]">
							<c:Value>tr5_report.xsl</c:Value>
						</ts:Element>
						<ts:Element position ="[2]">
							<c:Value>tr5_expand.xsl</c:Value>
						</ts:Element>
					</c:IndexedArray>
				</c:Item>
				<c:Item name = "Atml_Rpt_Options">
					<c:Collection xsi:type="ts:TS_Collection" flags = "0x0000">
						<c:Item name = "AddReportText">
							<c:Datum value = "true" xsi:type="ts:TS_boolean" flags = "0x0000"/>
						</c:Item>
						<c:Item name = "ExtensionDLLAbsolutePath">
							<c:Datum xsi:type="ts:TS_string" flags = "0x0000">
								<c:Value></c:Value>
							</c:Datum>
						</c:Item>
						<c:Item name = "TestResultsSchemaPath">
							<c:Datum xsi:type="ts:TS_string" flags = "0x0000">
								<c:Value></c:Value>
							</c:Datum>
						</c:Item>
					</c:Collection>
				</c:Item>
			</c:Collection>
		</tr:Configuration>
	</tr:TestProgram>
	<tr:TestStation>
		<c:SerialNumber>CFTP7</c:SerialNumber>
	</tr:TestStation>
	<tr:UUT>
		<c:SerialNumber>10041194-RA21452321</c:SerialNumber>
	</tr:UUT>
	<tr:Extension>
		<ts:TSResultSetProperties>
			<ts:NumOfResults value = '33'/>
		</ts:TSResultSetProperties>
	</tr:Extension>
</trc:TestResults>
</trc:TestResultsCollection>
