<?xml version="1.0" encoding="gb2312" ?><?xml-stylesheet type="text/xsl" href="C:\Program Files\National Instruments\TestStand 2012\Components\Models\TestStandModels\ATML\StyleSheets\tr5_horizontal.xsl"?>

<trc:TestResultsCollection xmlns:trc="urn:IEEE-1636.1:2011:01:TestResultsCollection" xmlns:tr="urn:IEEE-1636.1:2011:01:TestResults" xmlns:c="urn:IEEE-1671:2010:Common" xmlns:xsi="http://www.w3.org/2001/XMLSchema-instance" xmlns:ts="www.ni.com/TestStand/ATMLTestResults/2.0">
<trc:TestResults uuid="ccb34167-f00a-44a8-81f5-3b13da650947" xmlns:trc="urn:IEEE-1636.1:2011:01:TestResultsCollection" xmlns:tr="urn:IEEE-1636.1:2011:01:TestResults" xmlns:c="urn:IEEE-1671:2010:Common" xmlns:xsi="http://www.w3.org/2001/XMLSchema-instance" xmlns:ts="www.ni.com/TestStand/ATMLTestResults/2.0">
	<tr:Personnel>
		<tr:SystemOperator ID = "administrator" name = "administrator"/>
	</tr:Personnel>
	<tr:ResultSet ID="1069" name = "C:\Bio Rad TestStand_10041194\Main\Bio Rad Teststand.seq#MainSequence" startDateTime = "2022-04-13T18:37:21.396" endDateTime = "2022-04-13T18:41:56.962">
		<tr:Extension>
			<ts:TSStepProperties>
				<ts:StepType>SequenceCall</ts:StepType>
				<ts:StepGroup>Main</ts:StepGroup>
				<ts:BlockLevel value='1'/>
				<ts:Index value='9'/>
				<ts:TotalTime value='275.567'/>
				<ts:ModuleTime value='275.567'/>
			</ts:TSStepProperties>
		</tr:Extension>
		<tr:Outcome value="Aborted" qualifier="Terminated" />
		<tr:SessionAction ID = "1070" name = "Load Bio Rad DLL" startDateTime = "2022-04-13T18:37:21.433"  endDateTime = "2022-04-13T18:37:21.434"  testReferenceID="ID#:vjT50USnYkW0sYJ60awv0D">
			<tr:Extension>
				<ts:TSStepProperties>
					<ts:StepType>Action</ts:StepType>
					<ts:StepGroup>Setup</ts:StepGroup>
					<ts:BlockLevel value='0'/>
					<ts:Index value='0'/>
					<ts:TotalTime value='0.001207'/>
					<ts:ModuleTime value='0.001207'/>
				</ts:TSStepProperties>
			</tr:Extension>
			<tr:ActionOutcome value = "Done" />
		</tr:SessionAction>
		<tr:Test ID = "1071" name = "Put UUT" startDateTime = "2022-04-13T18:37:21.450"  endDateTime = "2022-04-13T18:37:23.534"  testReferenceID="ID#:pCsUDaEDBUWb+mCAymOY1A">
			<tr:Extension>
				<ts:TSStepProperties>
					<ts:StepType>PassFailTest</ts:StepType>
					<ts:StepGroup>Main</ts:StepGroup>
					<ts:BlockLevel value='0'/>
					<ts:Index value='0'/>
					<ts:TotalTime value='2.08462'/>
					<ts:ModuleTime value='2.08462'/>
				</ts:TSStepProperties>
			</tr:Extension>
			<tr:Outcome value = "Passed" />
		</tr:Test>
		<tr:SessionAction ID = "1072" name = "DC Power On" startDateTime = "2022-04-13T18:37:23.542"  endDateTime = "2022-04-13T18:37:23.881"  testReferenceID="ID#:f7l0w4KeGUuAgAdvy4llyA">
			<tr:Extension>
				<ts:TSStepProperties>
					<ts:StepType>Action</ts:StepType>
					<ts:StepGroup>Main</ts:StepGroup>
					<ts:BlockLevel value='0'/>
					<ts:Index value='1'/>
					<ts:TotalTime value='0.338839'/>
					<ts:ModuleTime value='0.338839'/>
				</ts:TSStepProperties>
			</tr:Extension>
			<tr:ActionOutcome value = "Done" />
		</tr:SessionAction>
		<tr:SessionAction ID = "1073" name = "AC Power On" startDateTime = "2022-04-13T18:37:23.886"  endDateTime = "2022-04-13T18:37:24.052"  testReferenceID="ID#:GzbbZRerW0KsOfSjLH45uD">
			<tr:Extension>
				<ts:TSStepProperties>
					<ts:StepType>Action</ts:StepType>
					<ts:StepGroup>Main</ts:StepGroup>
					<ts:BlockLevel value='0'/>
					<ts:Index value='2'/>
					<ts:TotalTime value='0.165936'/>
					<ts:ModuleTime value='0.165936'/>
				</ts:TSStepProperties>
			</tr:Extension>
			<tr:ActionOutcome value = "Done" />
		</tr:SessionAction>
		<tr:Test ID = "1074" name = "Find Attached Devices" startDateTime = "2022-04-13T18:37:24.054"  endDateTime = "2022-04-13T18:37:59.145"  testReferenceID="ID#:3/5kcZbtdEezckeONT1yKB">
			<tr:Extension>
				<ts:TSStepProperties>
					<ts:StepType>StringValueTest</ts:StepType>
					<ts:StepGroup>Main</ts:StepGroup>
					<ts:BlockLevel value='0'/>
					<ts:Index value='4'/>
					<ts:TotalTime value='35.091'/>
					<ts:ModuleTime value='35.091'/>
				</ts:TSStepProperties>
			</tr:Extension>
			<tr:Outcome value = "Passed" />
			<tr:TestResult ID = "tr791D0413T2357Z777" name = "String">
				<tr:TestData>
					<c:Datum xsi:type="ts:TS_string" flags = "0x2400">
						<c:Value>Success</c:Value>
					</c:Datum>
				</tr:TestData>
				<tr:TestLimits>
					<tr:Limits>
						<c:Expected comparator = "EQ">
							<c:Datum xsi:type="ts:TS_string" flags = "0x0000">
								<c:Value>Success</c:Value>
							</c:Datum>
						</c:Expected>
					</tr:Limits>
				</tr:TestLimits>
			</tr:TestResult>
		</tr:Test>
		<tr:Test ID = "1075" name = "12.8V No Load Test" startDateTime = "2022-04-13T18:37:59.175"  endDateTime = "2022-04-13T18:38:00.463"  testReferenceID="ID#:s2EHM1jn9kGPV9WF3jYYlD">
			<tr:Extension>
				<ts:TSStepProperties>
					<ts:StepType>NumericLimitTest</ts:StepType>
					<ts:StepGroup>Main</ts:StepGroup>
					<ts:BlockLevel value='0'/>
					<ts:Index value='6'/>
					<ts:TotalTime value='1.28841'/>
					<ts:ModuleTime value='1.28841'/>
				</ts:TSStepProperties>
			</tr:Extension>
			<tr:Outcome value = "Passed" />
			<tr:TestResult ID = "tr792D0413T2357Z777" name = "Numeric">
				<tr:TestData>
					<c:Datum value = "12.7395932" xsi:type="ts:TS_double" nonStandardUnit="volt" flags = "0x2400"/>
				</tr:TestData>
				<tr:TestLimits>
					<tr:Limits>
						<c:LimitPair operator = "AND">
							<c:Limit comparator = "GE">
								<c:Datum nonStandardUnit = "volt" value = "12.16" xsi:type="ts:TS_double" flags = "0x0000"/>
							</c:Limit>
							<c:Limit comparator = "LE">
								<c:Datum nonStandardUnit = "volt" value = "13.44" xsi:type="ts:TS_double" flags = "0x0000"/>
							</c:Limit>
						</c:LimitPair>
					</tr:Limits>
				</tr:TestLimits>
			</tr:TestResult>
		</tr:Test>
		<tr:Test ID = "1076" name = "12.8V Load 30W" startDateTime = "2022-04-13T18:38:00.465"  endDateTime = "2022-04-13T18:38:01.896"  testReferenceID="ID#:/PEXBGfFnUy0sBWfu6GovA">
			<tr:Extension>
				<ts:TSStepProperties>
					<ts:StepType>NumericLimitTest</ts:StepType>
					<ts:StepGroup>Main</ts:StepGroup>
					<ts:BlockLevel value='0'/>
					<ts:Index value='7'/>
					<ts:TotalTime value='1.43094'/>
					<ts:ModuleTime value='1.43094'/>
				</ts:TSStepProperties>
			</tr:Extension>
			<tr:Outcome value = "Passed" />
			<tr:TestResult ID = "tr793D0413T2357Z777" name = "Numeric">
				<tr:TestData>
					<c:Datum value = "12.3352843" xsi:type="ts:TS_double" nonStandardUnit="volt" flags = "0x2400"/>
				</tr:TestData>
				<tr:TestLimits>
					<tr:Limits>
						<c:LimitPair operator = "AND">
							<c:Limit comparator = "GE">
								<c:Datum nonStandardUnit = "volt" value = "12.16" xsi:type="ts:TS_double" flags = "0x0000"/>
							</c:Limit>
							<c:Limit comparator = "LE">
								<c:Datum nonStandardUnit = "volt" value = "13.44" xsi:type="ts:TS_double" flags = "0x0000"/>
							</c:Limit>
						</c:LimitPair>
					</tr:Limits>
				</tr:TestLimits>
			</tr:TestResult>
		</tr:Test>
		<tr:Test ID = "1077" name = "5V No Load Test" startDateTime = "2022-04-13T18:38:01.909"  endDateTime = "2022-04-13T18:38:02.642"  testReferenceID="ID#:uT9QBRM1n0S0ZJX7F9++eA">
			<tr:Extension>
				<ts:TSStepProperties>
					<ts:StepType>NumericLimitTest</ts:StepType>
					<ts:StepGroup>Main</ts:StepGroup>
					<ts:BlockLevel value='0'/>
					<ts:Index value='9'/>
					<ts:TotalTime value='0.733099'/>
					<ts:ModuleTime value='0.733099'/>
				</ts:TSStepProperties>
			</tr:Extension>
			<tr:Outcome value = "Passed" />
			<tr:TestResult ID = "tr794D0413T2357Z777" name = "Numeric">
				<tr:TestData>
					<c:Datum value = "5.07867808" xsi:type="ts:TS_double" nonStandardUnit="volt" flags = "0x2400"/>
				</tr:TestData>
				<tr:TestLimits>
					<tr:Limits>
						<c:LimitPair operator = "AND">
							<c:Limit comparator = "GE">
								<c:Datum nonStandardUnit = "volt" value = "4.75" xsi:type="ts:TS_double" flags = "0x0000"/>
							</c:Limit>
							<c:Limit comparator = "LE">
								<c:Datum nonStandardUnit = "volt" value = "5.25" xsi:type="ts:TS_double" flags = "0x0000"/>
							</c:Limit>
						</c:LimitPair>
					</tr:Limits>
				</tr:TestLimits>
			</tr:TestResult>
		</tr:Test>
		<tr:Test ID = "1078" name = "5V 600mA Load" startDateTime = "2022-04-13T18:38:02.647"  endDateTime = "2022-04-13T18:38:03.896"  testReferenceID="ID#:hK5y13WF/UOw/cQ9FI1UED">
			<tr:Extension>
				<ts:TSStepProperties>
					<ts:StepType>NumericLimitTest</ts:StepType>
					<ts:StepGroup>Main</ts:StepGroup>
					<ts:BlockLevel value='0'/>
					<ts:Index value='10'/>
					<ts:TotalTime value='1.24924'/>
					<ts:ModuleTime value='1.24924'/>
				</ts:TSStepProperties>
			</tr:Extension>
			<tr:Outcome value = "Passed" />
			<tr:TestResult ID = "tr795D0413T2357Z777" name = "Numeric">
				<tr:TestData>
					<c:Datum value = "5.06110638" xsi:type="ts:TS_double" nonStandardUnit="volt" flags = "0x2400"/>
				</tr:TestData>
				<tr:TestLimits>
					<tr:Limits>
						<c:LimitPair operator = "AND">
							<c:Limit comparator = "GE">
								<c:Datum nonStandardUnit = "volt" value = "4.75" xsi:type="ts:TS_double" flags = "0x0000"/>
							</c:Limit>
							<c:Limit comparator = "LE">
								<c:Datum nonStandardUnit = "volt" value = "5.25" xsi:type="ts:TS_double" flags = "0x0000"/>
							</c:Limit>
						</c:LimitPair>
					</tr:Limits>
				</tr:TestLimits>
			</tr:TestResult>
		</tr:Test>
		<tr:Test ID = "1079" name = "3.3V Voltage Check" startDateTime = "2022-04-13T18:38:03.909"  endDateTime = "2022-04-13T18:38:04.643"  testReferenceID="ID#:dBBvwB2wHES0ifCY7PD/0B">
			<tr:Extension>
				<ts:TSStepProperties>
					<ts:StepType>NumericLimitTest</ts:StepType>
					<ts:StepGroup>Main</ts:StepGroup>
					<ts:BlockLevel value='0'/>
					<ts:Index value='12'/>
					<ts:TotalTime value='0.734318'/>
					<ts:ModuleTime value='0.734318'/>
				</ts:TSStepProperties>
			</tr:Extension>
			<tr:Outcome value = "Passed" />
			<tr:TestResult ID = "tr796D0413T2357Z777" name = "Numeric">
				<tr:TestData>
					<c:Datum value = "3.31535842" xsi:type="ts:TS_double" nonStandardUnit="volt" flags = "0x2400"/>
				</tr:TestData>
				<tr:TestLimits>
					<tr:Limits>
						<c:LimitPair operator = "AND">
							<c:Limit comparator = "GE">
								<c:Datum nonStandardUnit = "volt" value = "2.85" xsi:type="ts:TS_double" flags = "0x0000"/>
							</c:Limit>
							<c:Limit comparator = "LE">
								<c:Datum nonStandardUnit = "volt" value = "3.45" xsi:type="ts:TS_double" flags = "0x0000"/>
							</c:Limit>
						</c:LimitPair>
					</tr:Limits>
				</tr:TestLimits>
			</tr:TestResult>
		</tr:Test>
		<tr:Test ID = "1080" name = "Battery Voltage Check" startDateTime = "2022-04-13T18:38:04.654"  endDateTime = "2022-04-13T18:38:05.403"  testReferenceID="ID#:9ZyDVNqHmE+lSY/ulKlYSC">
			<tr:Extension>
				<ts:TSStepProperties>
					<ts:StepType>NumericLimitTest</ts:StepType>
					<ts:StepGroup>Main</ts:StepGroup>
					<ts:BlockLevel value='0'/>
					<ts:Index value='14'/>
					<ts:TotalTime value='0.748205'/>
					<ts:ModuleTime value='0.748205'/>
				</ts:TSStepProperties>
			</tr:Extension>
			<tr:Outcome value = "Passed" />
			<tr:TestResult ID = "tr797D0413T2357Z777" name = "Numeric">
				<tr:TestData>
					<c:Datum value = "3.22618714" xsi:type="ts:TS_double" nonStandardUnit="volt" flags = "0x2400"/>
				</tr:TestData>
				<tr:TestLimits>
					<tr:Limits>
						<c:LimitPair operator = "AND">
							<c:Limit comparator = "GE">
								<c:Datum nonStandardUnit = "volt" value = "2.85" xsi:type="ts:TS_double" flags = "0x0000"/>
							</c:Limit>
							<c:Limit comparator = "LE">
								<c:Datum nonStandardUnit = "volt" value = "3.45" xsi:type="ts:TS_double" flags = "0x0000"/>
							</c:Limit>
						</c:LimitPair>
					</tr:Limits>
				</tr:TestLimits>
			</tr:TestResult>
		</tr:Test>
		<tr:SessionAction ID = "1081" name = "Wait 10" startDateTime = "2022-04-13T18:38:05.408"  endDateTime = "2022-04-13T18:38:15.408"  testReferenceID="ID#:731Py5h0n0O4z4TxEZWZlC">
			<tr:Extension>
				<ts:TSStepProperties>
					<ts:StepType>NI_Wait</ts:StepType>
					<ts:StepGroup>Main</ts:StepGroup>
					<ts:BlockLevel value='0'/>
					<ts:Index value='15'/>
					<ts:TotalTime value='10.0005'/>
				</ts:TSStepProperties>
			</tr:Extension>
			<tr:ActionOutcome value = "Done" />
		</tr:SessionAction>
		<tr:Test ID = "1082" name = "Remote Command Set" startDateTime = "2022-04-13T18:38:15.412"  endDateTime = "2022-04-13T18:39:17.130"  testReferenceID="ID#:rwMhfIhvkEGEPElh2WthJB">
			<tr:Extension>
				<ts:TSStepProperties>
					<ts:StepType>PassFailTest</ts:StepType>
					<ts:StepGroup>Main</ts:StepGroup>
					<ts:BlockLevel value='0'/>
					<ts:Index value='16'/>
					<ts:TotalTime value='61.7173'/>
					<ts:ModuleTime value='61.7173'/>
				</ts:TSStepProperties>
			</tr:Extension>
			<tr:Outcome value = "Passed" />
		</tr:Test>
		<tr:Test ID = "1083" name = "Initialize SRAM and HC12" startDateTime = "2022-04-13T18:39:17.131"  endDateTime = "2022-04-13T18:39:26.619"  testReferenceID="ID#:2mvB+Nka+EKbhUY+CDsGaC">
			<tr:Extension>
				<ts:TSStepProperties>
					<ts:StepType>PassFailTest</ts:StepType>
					<ts:StepGroup>Main</ts:StepGroup>
					<ts:BlockLevel value='0'/>
					<ts:Index value='17'/>
					<ts:TotalTime value='9.48768'/>
					<ts:ModuleTime value='9.48768'/>
				</ts:TSStepProperties>
			</tr:Extension>
			<tr:Outcome value = "Passed" />
		</tr:Test>
		<tr:Test ID = "1084" name = "I2C Read Write Test" startDateTime = "2022-04-13T18:39:26.630"  endDateTime = "2022-04-13T18:39:29.614"  testReferenceID="ID#:fJAamqcq2k20eyHGphq6yD">
			<tr:Extension>
				<ts:TSStepProperties>
					<ts:StepType>PassFailTest</ts:StepType>
					<ts:StepGroup>Main</ts:StepGroup>
					<ts:BlockLevel value='0'/>
					<ts:Index value='19'/>
					<ts:TotalTime value='2.98444'/>
					<ts:ModuleTime value='2.98444'/>
				</ts:TSStepProperties>
			</tr:Extension>
			<tr:Outcome value = "Passed" />
			<tr:TestResult ID = "tr798D0413T2357Z777" name = "Alpha VCC">
				<tr:TestData>
					<c:Datum value = "5.0799318715" xsi:type="ts:TS_double" flags = "0x2000"/>
				</tr:TestData>
			</tr:TestResult>
		</tr:Test>
		<tr:Test ID = "1085" name = "Get VCC Sensor Value" startDateTime = "2022-04-13T18:39:29.620"  endDateTime = "2022-04-13T18:39:29.632"  testReferenceID="ID#:lLtihA257EqchQIoLTc4cD">
			<tr:Extension>
				<ts:TSStepProperties>
					<ts:StepType>NumericLimitTest</ts:StepType>
					<ts:StepGroup>Main</ts:StepGroup>
					<ts:BlockLevel value='0'/>
					<ts:Index value='20'/>
					<ts:TotalTime value='0.0122'/>
					<ts:ModuleTime value='0.0122'/>
				</ts:TSStepProperties>
			</tr:Extension>
			<tr:Outcome value = "Passed" />
			<tr:TestResult ID = "tr799D0413T2357Z777" name = "Numeric">
				<tr:TestData>
					<c:Datum value = "4.99224" xsi:type="ts:TS_double" nonStandardUnit="volt" flags = "0x2400"/>
				</tr:TestData>
				<tr:TestLimits>
					<tr:Limits>
						<c:LimitPair operator = "AND">
							<c:Limit comparator = "GE">
								<c:Datum nonStandardUnit = "volt" value = "4.75" xsi:type="ts:TS_double" flags = "0x0000"/>
							</c:Limit>
							<c:Limit comparator = "LE">
								<c:Datum nonStandardUnit = "volt" value = "5.25" xsi:type="ts:TS_double" flags = "0x0000"/>
							</c:Limit>
						</c:LimitPair>
					</tr:Limits>
				</tr:TestLimits>
			</tr:TestResult>
		</tr:Test>
		<tr:Test ID = "1086" name = "Get 15V Sensor Value" startDateTime = "2022-04-13T18:39:29.637"  endDateTime = "2022-04-13T18:39:29.649"  testReferenceID="ID#:OXQvCycUQEO2wsMJkgzwsB">
			<tr:Extension>
				<ts:TSStepProperties>
					<ts:StepType>NumericLimitTest</ts:StepType>
					<ts:StepGroup>Main</ts:StepGroup>
					<ts:BlockLevel value='0'/>
					<ts:Index value='21'/>
					<ts:TotalTime value='0.011917'/>
					<ts:ModuleTime value='0.011917'/>
				</ts:TSStepProperties>
			</tr:Extension>
			<tr:Outcome value = "Passed" />
			<tr:TestResult ID = "tr800D0413T2357Z777" name = "Numeric">
				<tr:TestData>
					<c:Datum value = "12.9876" xsi:type="ts:TS_double" nonStandardUnit="volt" flags = "0x2400"/>
				</tr:TestData>
				<tr:TestLimits>
					<tr:Limits>
						<c:LimitPair operator = "AND">
							<c:Limit comparator = "GE">
								<c:Datum nonStandardUnit = "volt" value = "12.16" xsi:type="ts:TS_double" flags = "0x0000"/>
							</c:Limit>
							<c:Limit comparator = "LE">
								<c:Datum nonStandardUnit = "volt" value = "13.44" xsi:type="ts:TS_double" flags = "0x0000"/>
							</c:Limit>
						</c:LimitPair>
					</tr:Limits>
				</tr:TestLimits>
			</tr:TestResult>
		</tr:Test>
		<tr:Test ID = "1087" name = "Get Power Sensor Value" startDateTime = "2022-04-13T18:39:29.653"  endDateTime = "2022-04-13T18:39:29.666"  testReferenceID="ID#:tq6ATEHbkk+HI/3GbKMbtB">
			<tr:Extension>
				<ts:TSStepProperties>
					<ts:StepType>NumericLimitTest</ts:StepType>
					<ts:StepGroup>Main</ts:StepGroup>
					<ts:BlockLevel value='0'/>
					<ts:Index value='22'/>
					<ts:TotalTime value='0.0122267'/>
					<ts:ModuleTime value='0.0122267'/>
				</ts:TSStepProperties>
			</tr:Extension>
			<tr:Outcome value = "Passed" />
			<tr:TestResult ID = "tr801D0413T2357Z777" name = "Numeric">
				<tr:TestData>
					<c:Datum value = "39.3464" xsi:type="ts:TS_double" nonStandardUnit="volt" flags = "0x2400"/>
				</tr:TestData>
				<tr:TestLimits>
					<tr:Limits>
						<c:LimitPair operator = "AND">
							<c:Limit comparator = "GE">
								<c:Datum nonStandardUnit = "volt" value = "38" xsi:type="ts:TS_double" flags = "0x0000"/>
							</c:Limit>
							<c:Limit comparator = "LE">
								<c:Datum nonStandardUnit = "volt" value = "42" xsi:type="ts:TS_double" flags = "0x0000"/>
							</c:Limit>
						</c:LimitPair>
					</tr:Limits>
				</tr:TestLimits>
			</tr:TestResult>
		</tr:Test>
		<tr:Test ID = "1088" name = "Lid Left Sensor Test" startDateTime = "2022-04-13T18:39:29.670"  endDateTime = "2022-04-13T18:39:29.682"  testReferenceID="ID#:mtZOusQhZ0aR9DOvVCf06B">
			<tr:Extension>
				<ts:TSStepProperties>
					<ts:StepType>NumericLimitTest</ts:StepType>
					<ts:StepGroup>Main</ts:StepGroup>
					<ts:BlockLevel value='0'/>
					<ts:Index value='23'/>
					<ts:TotalTime value='0.0118644'/>
					<ts:ModuleTime value='0.0118644'/>
				</ts:TSStepProperties>
			</tr:Extension>
			<tr:Outcome value = "Passed" />
			<tr:TestResult ID = "tr802D0413T2357Z777" name = "Numeric">
				<tr:TestData>
					<c:Datum value = "53" xsi:type="ts:TS_double" flags = "0x2400"/>
				</tr:TestData>
				<tr:TestLimits>
					<tr:Limits>
						<c:LimitPair operator = "AND">
							<c:Limit comparator = "GE">
								<c:Datum value = "50.179" xsi:type="ts:TS_double" flags = "0x0000"/>
							</c:Limit>
							<c:Limit comparator = "LE">
								<c:Datum value = "55.456" xsi:type="ts:TS_double" flags = "0x0000"/>
							</c:Limit>
						</c:LimitPair>
					</tr:Limits>
				</tr:TestLimits>
			</tr:TestResult>
		</tr:Test>
		<tr:Test ID = "1089" name = "Lid Right Sensor Test" startDateTime = "2022-04-13T18:39:29.687"  endDateTime = "2022-04-13T18:39:29.698"  testReferenceID="ID#:DJXkLSdTrEC0jp7Z2uRpTB">
			<tr:Extension>
				<ts:TSStepProperties>
					<ts:StepType>NumericLimitTest</ts:StepType>
					<ts:StepGroup>Main</ts:StepGroup>
					<ts:BlockLevel value='0'/>
					<ts:Index value='24'/>
					<ts:TotalTime value='0.0118712'/>
					<ts:ModuleTime value='0.0118712'/>
				</ts:TSStepProperties>
			</tr:Extension>
			<tr:Outcome value = "Passed" />
			<tr:TestResult ID = "tr803D0413T2357Z777" name = "Numeric">
				<tr:TestData>
					<c:Datum value = "53" xsi:type="ts:TS_double" flags = "0x2400"/>
				</tr:TestData>
				<tr:TestLimits>
					<tr:Limits>
						<c:LimitPair operator = "AND">
							<c:Limit comparator = "GE">
								<c:Datum value = "50.179" xsi:type="ts:TS_double" flags = "0x0000"/>
							</c:Limit>
							<c:Limit comparator = "LE">
								<c:Datum value = "55.456" xsi:type="ts:TS_double" flags = "0x0000"/>
							</c:Limit>
						</c:LimitPair>
					</tr:Limits>
				</tr:TestLimits>
			</tr:TestResult>
		</tr:Test>
		<tr:Test ID = "1090" name = "HS Left Sensor Test" startDateTime = "2022-04-13T18:39:29.703"  endDateTime = "2022-04-13T18:39:29.715"  testReferenceID="ID#:iFTOUj6L7EuXDBSu+DhS4D">
			<tr:Extension>
				<ts:TSStepProperties>
					<ts:StepType>NumericLimitTest</ts:StepType>
					<ts:StepGroup>Main</ts:StepGroup>
					<ts:BlockLevel value='0'/>
					<ts:Index value='25'/>
					<ts:TotalTime value='0.0120754'/>
					<ts:ModuleTime value='0.0120754'/>
				</ts:TSStepProperties>
			</tr:Extension>
			<tr:Outcome value = "Passed" />
			<tr:TestResult ID = "tr804D0413T2357Z777" name = "Numeric">
				<tr:TestData>
					<c:Datum value = "53.1" xsi:type="ts:TS_double" flags = "0x2400"/>
				</tr:TestData>
				<tr:TestLimits>
					<tr:Limits>
						<c:LimitPair operator = "AND">
							<c:Limit comparator = "GE">
								<c:Datum value = "50.179" xsi:type="ts:TS_double" flags = "0x0000"/>
							</c:Limit>
							<c:Limit comparator = "LE">
								<c:Datum value = "55.456" xsi:type="ts:TS_double" flags = "0x0000"/>
							</c:Limit>
						</c:LimitPair>
					</tr:Limits>
				</tr:TestLimits>
			</tr:TestResult>
		</tr:Test>
		<tr:Test ID = "1091" name = "HS Right Sensor Test" startDateTime = "2022-04-13T18:39:29.723"  endDateTime = "2022-04-13T18:39:29.741"  testReferenceID="ID#:WyP2dWG4mUyCXhu6wF0rwB">
			<tr:Extension>
				<ts:TSStepProperties>
					<ts:StepType>NumericLimitTest</ts:StepType>
					<ts:StepGroup>Main</ts:StepGroup>
					<ts:BlockLevel value='0'/>
					<ts:Index value='26'/>
					<ts:TotalTime value='0.017587'/>
					<ts:ModuleTime value='0.017587'/>
				</ts:TSStepProperties>
			</tr:Extension>
			<tr:Outcome value = "Passed" />
			<tr:TestResult ID = "tr805D0413T2357Z777" name = "Numeric">
				<tr:TestData>
					<c:Datum value = "53" xsi:type="ts:TS_double" flags = "0x2400"/>
				</tr:TestData>
				<tr:TestLimits>
					<tr:Limits>
						<c:LimitPair operator = "AND">
							<c:Limit comparator = "GE">
								<c:Datum value = "50.179" xsi:type="ts:TS_double" flags = "0x0000"/>
							</c:Limit>
							<c:Limit comparator = "LE">
								<c:Datum value = "55.456" xsi:type="ts:TS_double" flags = "0x0000"/>
							</c:Limit>
						</c:LimitPair>
					</tr:Limits>
				</tr:TestLimits>
			</tr:TestResult>
		</tr:Test>
		<tr:Test ID = "1092" name = "Get Amp2 Sensor Value" startDateTime = "2022-04-13T18:39:29.745"  endDateTime = "2022-04-13T18:39:29.758"  testReferenceID="ID#:+cEzB3eXu0GAFph0u4nGdD">
			<tr:Extension>
				<ts:TSStepProperties>
					<ts:StepType>NumericLimitTest</ts:StepType>
					<ts:StepGroup>Main</ts:StepGroup>
					<ts:BlockLevel value='0'/>
					<ts:Index value='27'/>
					<ts:TotalTime value='0.0124702'/>
					<ts:ModuleTime value='0.0124702'/>
				</ts:TSStepProperties>
			</tr:Extension>
			<tr:Outcome value = "Passed" />
			<tr:TestResult ID = "tr806D0413T2357Z777" name = "Numeric">
				<tr:TestData>
					<c:Datum value = "22.6" xsi:type="ts:TS_double" nonStandardUnit="degrees Celsius" flags = "0x2400"/>
				</tr:TestData>
				<tr:TestLimits>
					<tr:Limits>
						<c:LimitPair operator = "AND">
							<c:Limit comparator = "GE">
								<c:Datum nonStandardUnit = "degrees Celsius" value = "0" xsi:type="ts:TS_double" flags = "0x0000"/>
							</c:Limit>
							<c:Limit comparator = "LE">
								<c:Datum nonStandardUnit = "degrees Celsius" value = "50" xsi:type="ts:TS_double" flags = "0x0000"/>
							</c:Limit>
						</c:LimitPair>
					</tr:Limits>
				</tr:TestLimits>
			</tr:TestResult>
		</tr:Test>
		<tr:Test ID = "1093" name = "Get Amp Sensor Value" startDateTime = "2022-04-13T18:39:29.762"  endDateTime = "2022-04-13T18:39:29.774"  testReferenceID="ID#:ZeBOXyeCEkK/Q4rhF/s1TC">
			<tr:Extension>
				<ts:TSStepProperties>
					<ts:StepType>NumericLimitTest</ts:StepType>
					<ts:StepGroup>Main</ts:StepGroup>
					<ts:BlockLevel value='0'/>
					<ts:Index value='28'/>
					<ts:TotalTime value='0.0115927'/>
					<ts:ModuleTime value='0.0115927'/>
				</ts:TSStepProperties>
			</tr:Extension>
			<tr:Outcome value = "Passed" />
			<tr:TestResult ID = "tr807D0413T2357Z777" name = "Numeric">
				<tr:TestData>
					<c:Datum value = "22.3" xsi:type="ts:TS_double" nonStandardUnit="degrees Celsius" flags = "0x2400"/>
				</tr:TestData>
				<tr:TestLimits>
					<tr:Limits>
						<c:LimitPair operator = "AND">
							<c:Limit comparator = "GE">
								<c:Datum nonStandardUnit = "degrees Celsius" value = "0" xsi:type="ts:TS_double" flags = "0x0000"/>
							</c:Limit>
							<c:Limit comparator = "LE">
								<c:Datum nonStandardUnit = "degrees Celsius" value = "50" xsi:type="ts:TS_double" flags = "0x0000"/>
							</c:Limit>
						</c:LimitPair>
					</tr:Limits>
				</tr:TestLimits>
			</tr:TestResult>
		</tr:Test>
		<tr:Test ID = "1094" name = "Get Power Supply Sensor Value" startDateTime = "2022-04-13T18:39:29.777"  endDateTime = "2022-04-13T18:39:29.792"  testReferenceID="ID#:XJyw3lUbfk+DGfORDTDmaA">
			<tr:Extension>
				<ts:TSStepProperties>
					<ts:StepType>NumericLimitTest</ts:StepType>
					<ts:StepGroup>Main</ts:StepGroup>
					<ts:BlockLevel value='0'/>
					<ts:Index value='29'/>
					<ts:TotalTime value='0.0150895'/>
					<ts:ModuleTime value='0.0150895'/>
				</ts:TSStepProperties>
			</tr:Extension>
			<tr:Outcome value = "Passed" />
			<tr:TestResult ID = "tr808D0413T2357Z777" name = "Numeric">
				<tr:TestData>
					<c:Datum value = "25.3" xsi:type="ts:TS_double" nonStandardUnit="degrees Celsius" flags = "0x2400"/>
				</tr:TestData>
				<tr:TestLimits>
					<tr:Limits>
						<c:LimitPair operator = "AND">
							<c:Limit comparator = "GE">
								<c:Datum nonStandardUnit = "degrees Celsius" value = "-50" xsi:type="ts:TS_double" flags = "0x0000"/>
							</c:Limit>
							<c:Limit comparator = "LE">
								<c:Datum nonStandardUnit = "degrees Celsius" value = "50" xsi:type="ts:TS_double" flags = "0x0000"/>
							</c:Limit>
						</c:LimitPair>
					</tr:Limits>
				</tr:TestLimits>
			</tr:TestResult>
		</tr:Test>
		<tr:Test ID = "1095" name = "SRAM Page 0 Check" startDateTime = "2022-04-13T18:39:29.798"  endDateTime = "2022-04-13T18:40:20.151"  testReferenceID="ID#:3kcqtTylf0K2d4hJ13c0gD">
			<tr:Extension>
				<ts:TSStepProperties>
					<ts:StepType>PassFailTest</ts:StepType>
					<ts:StepGroup>Main</ts:StepGroup>
					<ts:BlockLevel value='0'/>
					<ts:Index value='31'/>
					<ts:TotalTime value='50.3537'/>
					<ts:ModuleTime value='50.3537'/>
				</ts:TSStepProperties>
			</tr:Extension>
			<tr:Outcome value = "Passed" />
		</tr:Test>
		<tr:Test ID = "1096" name = "SRAM Page 1 Check" startDateTime = "2022-04-13T18:40:20.168"  endDateTime = "2022-04-13T18:40:20.667"  testReferenceID="ID#:che6FvrUSUa/xqqXpET9gD">
			<tr:Extension>
				<ts:TSStepProperties>
					<ts:StepType>PassFailTest</ts:StepType>
					<ts:StepGroup>Main</ts:StepGroup>
					<ts:BlockLevel value='0'/>
					<ts:Index value='32'/>
					<ts:TotalTime value='0.499168'/>
					<ts:ModuleTime value='0.499168'/>
				</ts:TSStepProperties>
			</tr:Extension>
			<tr:Outcome value = "Passed" />
		</tr:Test>
		<tr:Test ID = "1097" name = "SRAM Page 2 Check" startDateTime = "2022-04-13T18:40:20.696"  endDateTime = "2022-04-13T18:40:21.120"  testReferenceID="ID#:cNXE9UJMRU6lposNdl02BA">
			<tr:Extension>
				<ts:TSStepProperties>
					<ts:StepType>PassFailTest</ts:StepType>
					<ts:StepGroup>Main</ts:StepGroup>
					<ts:BlockLevel value='0'/>
					<ts:Index value='33'/>
					<ts:TotalTime value='0.423789'/>
					<ts:ModuleTime value='0.423789'/>
				</ts:TSStepProperties>
			</tr:Extension>
			<tr:Outcome value = "Passed" />
		</tr:Test>
		<tr:Test ID = "1098" name = "SRAM Page 3 Check" startDateTime = "2022-04-13T18:40:21.124"  endDateTime = "2022-04-13T18:40:21.615"  testReferenceID="ID#:YqGUbJEF9EWgJpk574R7qA">
			<tr:Extension>
				<ts:TSStepProperties>
					<ts:StepType>PassFailTest</ts:StepType>
					<ts:StepGroup>Main</ts:StepGroup>
					<ts:BlockLevel value='0'/>
					<ts:Index value='34'/>
					<ts:TotalTime value='0.491625'/>
					<ts:ModuleTime value='0.491625'/>
				</ts:TSStepProperties>
			</tr:Extension>
			<tr:Outcome value = "Passed" />
		</tr:Test>
		<tr:Test ID = "1099" name = "Power Cycle Unit" startDateTime = "2022-04-13T18:40:21.620"  endDateTime = "2022-04-13T18:40:47.629"  testReferenceID="ID#:FIYuItwZckyYuf6JOYOSVD">
			<tr:Extension>
				<ts:TSStepProperties>
					<ts:StepType>PassFailTest</ts:StepType>
					<ts:StepGroup>Main</ts:StepGroup>
					<ts:BlockLevel value='0'/>
					<ts:Index value='35'/>
					<ts:TotalTime value='26.0093'/>
					<ts:ModuleTime value='26.0093'/>
				</ts:TSStepProperties>
			</tr:Extension>
			<tr:Outcome value = "Passed" />
		</tr:Test>
		<tr:Test ID = "1100" name = "Battery Backup Test" startDateTime = "2022-04-13T18:40:47.631"  endDateTime = "2022-04-13T18:40:48.670"  testReferenceID="ID#:p4VzON2s6EWvKBxp0H3nLC">
			<tr:Extension>
				<ts:TSStepProperties>
					<ts:StepType>PassFailTest</ts:StepType>
					<ts:StepGroup>Main</ts:StepGroup>
					<ts:BlockLevel value='0'/>
					<ts:Index value='36'/>
					<ts:TotalTime value='1.03979'/>
					<ts:ModuleTime value='1.03979'/>
				</ts:TSStepProperties>
			</tr:Extension>
			<tr:Outcome value = "Passed" />
		</tr:Test>
		<tr:Test ID = "1101" name = "Block Sensor 0 Check" startDateTime = "2022-04-13T18:40:48.673"  endDateTime = "2022-04-13T18:40:48.683"  testReferenceID="ID#:Sq3nktOnbEmcuPOiOZYrGC">
			<tr:Extension>
				<ts:TSStepProperties>
					<ts:StepType>NumericLimitTest</ts:StepType>
					<ts:StepGroup>Main</ts:StepGroup>
					<ts:BlockLevel value='0'/>
					<ts:Index value='38'/>
					<ts:TotalTime value='0.0097791'/>
					<ts:ModuleTime value='0.0097791'/>
				</ts:TSStepProperties>
			</tr:Extension>
			<tr:Outcome value = "Passed" />
			<tr:TestResult ID = "tr809D0413T2357Z777" name = "Numeric">
				<tr:TestData>
					<c:Datum value = "52.9" xsi:type="ts:TS_double" nonStandardUnit="degrees Celsius" flags = "0x2400"/>
				</tr:TestData>
				<tr:TestLimits>
					<tr:Limits>
						<c:LimitPair operator = "AND">
							<c:Limit comparator = "GE">
								<c:Datum nonStandardUnit = "degrees Celsius" value = "50.179" xsi:type="ts:TS_double" flags = "0x0000"/>
							</c:Limit>
							<c:Limit comparator = "LE">
								<c:Datum nonStandardUnit = "degrees Celsius" value = "55.456" xsi:type="ts:TS_double" flags = "0x0000"/>
							</c:Limit>
						</c:LimitPair>
					</tr:Limits>
				</tr:TestLimits>
			</tr:TestResult>
		</tr:Test>
		<tr:Test ID = "1102" name = "Block Sensor 1 Check" startDateTime = "2022-04-13T18:40:48.686"  endDateTime = "2022-04-13T18:40:48.697"  testReferenceID="ID#:BbHOPCRl5Um67zlPcNi5oB">
			<tr:Extension>
				<ts:TSStepProperties>
					<ts:StepType>NumericLimitTest</ts:StepType>
					<ts:StepGroup>Main</ts:StepGroup>
					<ts:BlockLevel value='0'/>
					<ts:Index value='39'/>
					<ts:TotalTime value='0.0111654'/>
					<ts:ModuleTime value='0.0111654'/>
				</ts:TSStepProperties>
			</tr:Extension>
			<tr:Outcome value = "Passed" />
			<tr:TestResult ID = "tr810D0413T2357Z777" name = "Numeric">
				<tr:TestData>
					<c:Datum value = "52.87" xsi:type="ts:TS_double" nonStandardUnit="degrees Celsius" flags = "0x2400"/>
				</tr:TestData>
				<tr:TestLimits>
					<tr:Limits>
						<c:LimitPair operator = "AND">
							<c:Limit comparator = "GE">
								<c:Datum nonStandardUnit = "degrees Celsius" value = "50.179" xsi:type="ts:TS_double" flags = "0x0000"/>
							</c:Limit>
							<c:Limit comparator = "LE">
								<c:Datum nonStandardUnit = "degrees Celsius" value = "55.456" xsi:type="ts:TS_double" flags = "0x0000"/>
							</c:Limit>
						</c:LimitPair>
					</tr:Limits>
				</tr:TestLimits>
			</tr:TestResult>
		</tr:Test>
		<tr:Test ID = "1103" name = "Block Sensor 2 Check" startDateTime = "2022-04-13T18:40:48.705"  endDateTime = "2022-04-13T18:40:48.716"  testReferenceID="ID#:d2vFO0lGmE+F/QuX5inooA">
			<tr:Extension>
				<ts:TSStepProperties>
					<ts:StepType>NumericLimitTest</ts:StepType>
					<ts:StepGroup>Main</ts:StepGroup>
					<ts:BlockLevel value='0'/>
					<ts:Index value='40'/>
					<ts:TotalTime value='0.01019'/>
					<ts:ModuleTime value='0.01019'/>
				</ts:TSStepProperties>
			</tr:Extension>
			<tr:Outcome value = "Passed" />
			<tr:TestResult ID = "tr811D0413T2357Z777" name = "Numeric">
				<tr:TestData>
					<c:Datum value = "52.87" xsi:type="ts:TS_double" nonStandardUnit="degrees Celsius" flags = "0x2400"/>
				</tr:TestData>
				<tr:TestLimits>
					<tr:Limits>
						<c:LimitPair operator = "AND">
							<c:Limit comparator = "GE">
								<c:Datum nonStandardUnit = "degrees Celsius" value = "50.179" xsi:type="ts:TS_double" flags = "0x0000"/>
							</c:Limit>
							<c:Limit comparator = "LE">
								<c:Datum nonStandardUnit = "degrees Celsius" value = "55.456" xsi:type="ts:TS_double" flags = "0x0000"/>
							</c:Limit>
						</c:LimitPair>
					</tr:Limits>
				</tr:TestLimits>
			</tr:TestResult>
		</tr:Test>
		<tr:Test ID = "1104" name = "Block Sensor 3 Check" startDateTime = "2022-04-13T18:40:48.719"  endDateTime = "2022-04-13T18:40:48.729"  testReferenceID="ID#:lGDHqMrBvEe0/XaoG1N5ZC">
			<tr:Extension>
				<ts:TSStepProperties>
					<ts:StepType>NumericLimitTest</ts:StepType>
					<ts:StepGroup>Main</ts:StepGroup>
					<ts:BlockLevel value='0'/>
					<ts:Index value='41'/>
					<ts:TotalTime value='0.0097487'/>
					<ts:ModuleTime value='0.0097487'/>
				</ts:TSStepProperties>
			</tr:Extension>
			<tr:Outcome value = "Passed" />
			<tr:TestResult ID = "tr812D0413T2357Z777" name = "Numeric">
				<tr:TestData>
					<c:Datum value = "52.87" xsi:type="ts:TS_double" nonStandardUnit="degrees Celsius" flags = "0x2400"/>
				</tr:TestData>
				<tr:TestLimits>
					<tr:Limits>
						<c:LimitPair operator = "AND">
							<c:Limit comparator = "GE">
								<c:Datum nonStandardUnit = "degrees Celsius" value = "50.179" xsi:type="ts:TS_double" flags = "0x0000"/>
							</c:Limit>
							<c:Limit comparator = "LE">
								<c:Datum nonStandardUnit = "degrees Celsius" value = "55.456" xsi:type="ts:TS_double" flags = "0x0000"/>
							</c:Limit>
						</c:LimitPair>
					</tr:Limits>
				</tr:TestLimits>
			</tr:TestResult>
		</tr:Test>
		<tr:Test ID = "1105" name = "Block Sensor 4 Check" startDateTime = "2022-04-13T18:40:48.732"  endDateTime = "2022-04-13T18:40:48.742"  testReferenceID="ID#:KtKGZ/k25EWm0Ydfq9zs3D">
			<tr:Extension>
				<ts:TSStepProperties>
					<ts:StepType>NumericLimitTest</ts:StepType>
					<ts:StepGroup>Main</ts:StepGroup>
					<ts:BlockLevel value='0'/>
					<ts:Index value='42'/>
					<ts:TotalTime value='0.00998'/>
					<ts:ModuleTime value='0.00998'/>
				</ts:TSStepProperties>
			</tr:Extension>
			<tr:Outcome value = "Passed" />
			<tr:TestResult ID = "tr813D0413T2357Z777" name = "Numeric">
				<tr:TestData>
					<c:Datum value = "52.9" xsi:type="ts:TS_double" nonStandardUnit="degrees Celsius" flags = "0x2400"/>
				</tr:TestData>
				<tr:TestLimits>
					<tr:Limits>
						<c:LimitPair operator = "AND">
							<c:Limit comparator = "GE">
								<c:Datum nonStandardUnit = "degrees Celsius" value = "50.179" xsi:type="ts:TS_double" flags = "0x0000"/>
							</c:Limit>
							<c:Limit comparator = "LE">
								<c:Datum nonStandardUnit = "degrees Celsius" value = "55.456" xsi:type="ts:TS_double" flags = "0x0000"/>
							</c:Limit>
						</c:LimitPair>
					</tr:Limits>
				</tr:TestLimits>
			</tr:TestResult>
		</tr:Test>
		<tr:Test ID = "1106" name = "Block Sensor 5 Check" startDateTime = "2022-04-13T18:40:48.746"  endDateTime = "2022-04-13T18:40:48.757"  testReferenceID="ID#:3GZetcK/dk6icYqYr6ufRC">
			<tr:Extension>
				<ts:TSStepProperties>
					<ts:StepType>NumericLimitTest</ts:StepType>
					<ts:StepGroup>Main</ts:StepGroup>
					<ts:BlockLevel value='0'/>
					<ts:Index value='43'/>
					<ts:TotalTime value='0.0110159'/>
					<ts:ModuleTime value='0.0110159'/>
				</ts:TSStepProperties>
			</tr:Extension>
			<tr:Outcome value = "Passed" />
			<tr:TestResult ID = "tr814D0413T2357Z777" name = "Numeric">
				<tr:TestData>
					<c:Datum value = "52.9" xsi:type="ts:TS_double" nonStandardUnit="degrees Celsius" flags = "0x2400"/>
				</tr:TestData>
				<tr:TestLimits>
					<tr:Limits>
						<c:LimitPair operator = "AND">
							<c:Limit comparator = "GE">
								<c:Datum nonStandardUnit = "degrees Celsius" value = "50.179" xsi:type="ts:TS_double" flags = "0x0000"/>
							</c:Limit>
							<c:Limit comparator = "LE">
								<c:Datum nonStandardUnit = "degrees Celsius" value = "55.456" xsi:type="ts:TS_double" flags = "0x0000"/>
							</c:Limit>
						</c:LimitPair>
					</tr:Limits>
				</tr:TestLimits>
			</tr:TestResult>
		</tr:Test>
		<tr:Test ID = "1107" name = "TE CH0 Posistive Direction Check" startDateTime = "2022-04-13T18:40:48.764"  endDateTime = "2022-04-13T18:40:49.540"  testReferenceID="ID#:wft4dbLGH0OE3xVoyu02CD">
			<tr:Extension>
				<ts:TSStepProperties>
					<ts:StepType>NumericLimitTest</ts:StepType>
					<ts:StepGroup>Main</ts:StepGroup>
					<ts:BlockLevel value='0'/>
					<ts:Index value='45'/>
					<ts:TotalTime value='0.776794'/>
					<ts:ModuleTime value='0.776794'/>
				</ts:TSStepProperties>
			</tr:Extension>
			<tr:Outcome value = "Passed" />
			<tr:TestResult ID = "tr815D0413T2357Z777" name = "Numeric">
				<tr:TestData>
					<c:Datum value = "10.6352952" xsi:type="ts:TS_double" nonStandardUnit="ampere" flags = "0x2400"/>
				</tr:TestData>
				<tr:TestLimits>
					<tr:Limits>
						<c:LimitPair operator = "AND">
							<c:Limit comparator = "GE">
								<c:Datum nonStandardUnit = "ampere" value = "10.165" xsi:type="ts:TS_double" flags = "0x0000"/>
							</c:Limit>
							<c:Limit comparator = "LE">
								<c:Datum nonStandardUnit = "ampere" value = "11.235" xsi:type="ts:TS_double" flags = "0x0000"/>
							</c:Limit>
						</c:LimitPair>
					</tr:Limits>
				</tr:TestLimits>
			</tr:TestResult>
		</tr:Test>
		<tr:Test ID = "1108" name = "TE CH0 Negative Direction Check" startDateTime = "2022-04-13T18:40:49.544"  endDateTime = "2022-04-13T18:40:50.303"  testReferenceID="ID#:LOhQjTzEUESri0TYHJJM5B">
			<tr:Extension>
				<ts:TSStepProperties>
					<ts:StepType>NumericLimitTest</ts:StepType>
					<ts:StepGroup>Main</ts:StepGroup>
					<ts:BlockLevel value='0'/>
					<ts:Index value='46'/>
					<ts:TotalTime value='0.758938'/>
					<ts:ModuleTime value='0.758938'/>
				</ts:TSStepProperties>
			</tr:Extension>
			<tr:Outcome value = "Passed" />
			<tr:TestResult ID = "tr816D0413T2357Z777" name = "Numeric">
				<tr:TestData>
					<c:Datum value = "-10.63473485" xsi:type="ts:TS_double" nonStandardUnit="ampere" flags = "0x2400"/>
				</tr:TestData>
				<tr:TestLimits>
					<tr:Limits>
						<c:LimitPair operator = "AND">
							<c:Limit comparator = "GE">
								<c:Datum nonStandardUnit = "ampere" value = "-11.235" xsi:type="ts:TS_double" flags = "0x0000"/>
							</c:Limit>
							<c:Limit comparator = "LE">
								<c:Datum nonStandardUnit = "ampere" value = "-10.165" xsi:type="ts:TS_double" flags = "0x0000"/>
							</c:Limit>
						</c:LimitPair>
					</tr:Limits>
				</tr:TestLimits>
			</tr:TestResult>
		</tr:Test>
		<tr:Test ID = "1109" name = "TE CH1 Posistive Direction Check" startDateTime = "2022-04-13T18:40:50.316"  endDateTime = "2022-04-13T18:40:51.127"  testReferenceID="ID#:/UGvDafsdEWLjx/wkIcdGD">
			<tr:Extension>
				<ts:TSStepProperties>
					<ts:StepType>NumericLimitTest</ts:StepType>
					<ts:StepGroup>Main</ts:StepGroup>
					<ts:BlockLevel value='0'/>
					<ts:Index value='47'/>
					<ts:TotalTime value='0.811786'/>
					<ts:ModuleTime value='0.811786'/>
				</ts:TSStepProperties>
			</tr:Extension>
			<tr:Outcome value = "Passed" />
			<tr:TestResult ID = "tr817D0413T2357Z777" name = "Numeric">
				<tr:TestData>
					<c:Datum value = "10.68237486667" xsi:type="ts:TS_double" nonStandardUnit="ampere" flags = "0x2400"/>
				</tr:TestData>
				<tr:TestLimits>
					<tr:Limits>
						<c:LimitPair operator = "AND">
							<c:Limit comparator = "GE">
								<c:Datum nonStandardUnit = "ampere" value = "10.165" xsi:type="ts:TS_double" flags = "0x0000"/>
							</c:Limit>
							<c:Limit comparator = "LE">
								<c:Datum nonStandardUnit = "ampere" value = "11.235" xsi:type="ts:TS_double" flags = "0x0000"/>
							</c:Limit>
						</c:LimitPair>
					</tr:Limits>
				</tr:TestLimits>
			</tr:TestResult>
		</tr:Test>
		<tr:Test ID = "1110" name = "TE CH1 Negative Direction Check" startDateTime = "2022-04-13T18:40:51.140"  endDateTime = "2022-04-13T18:40:51.925"  testReferenceID="ID#:Dja3YmK9y0WZKpGK9X0dOB">
			<tr:Extension>
				<ts:TSStepProperties>
					<ts:StepType>NumericLimitTest</ts:StepType>
					<ts:StepGroup>Main</ts:StepGroup>
					<ts:BlockLevel value='0'/>
					<ts:Index value='48'/>
					<ts:TotalTime value='0.784227'/>
					<ts:ModuleTime value='0.784227'/>
				</ts:TSStepProperties>
			</tr:Extension>
			<tr:Outcome value = "Passed" />
			<tr:TestResult ID = "tr818D0413T2357Z777" name = "Numeric">
				<tr:TestData>
					<c:Datum value = "-10.68494313333" xsi:type="ts:TS_double" nonStandardUnit="ampere" flags = "0x2400"/>
				</tr:TestData>
				<tr:TestLimits>
					<tr:Limits>
						<c:LimitPair operator = "AND">
							<c:Limit comparator = "GE">
								<c:Datum nonStandardUnit = "ampere" value = "-11.235" xsi:type="ts:TS_double" flags = "0x0000"/>
							</c:Limit>
							<c:Limit comparator = "LE">
								<c:Datum nonStandardUnit = "ampere" value = "-10.165" xsi:type="ts:TS_double" flags = "0x0000"/>
							</c:Limit>
						</c:LimitPair>
					</tr:Limits>
				</tr:TestLimits>
			</tr:TestResult>
		</tr:Test>
		<tr:Test ID = "1111" name = "TE CH2 Posistive Direction Check" startDateTime = "2022-04-13T18:40:51.937"  endDateTime = "2022-04-13T18:40:52.728"  testReferenceID="ID#:KJVxC0mgxESHhK9gy2wDBD">
			<tr:Extension>
				<ts:TSStepProperties>
					<ts:StepType>NumericLimitTest</ts:StepType>
					<ts:StepGroup>Main</ts:StepGroup>
					<ts:BlockLevel value='0'/>
					<ts:Index value='49'/>
					<ts:TotalTime value='0.790252'/>
					<ts:ModuleTime value='0.790252'/>
				</ts:TSStepProperties>
			</tr:Extension>
			<tr:Outcome value = "Passed" />
			<tr:TestResult ID = "tr819D0413T2357Z777" name = "Numeric">
				<tr:TestData>
					<c:Datum value = "10.71897863333" xsi:type="ts:TS_double" nonStandardUnit="ampere" flags = "0x2400"/>
				</tr:TestData>
				<tr:TestLimits>
					<tr:Limits>
						<c:LimitPair operator = "AND">
							<c:Limit comparator = "GE">
								<c:Datum nonStandardUnit = "ampere" value = "10.165" xsi:type="ts:TS_double" flags = "0x0000"/>
							</c:Limit>
							<c:Limit comparator = "LE">
								<c:Datum nonStandardUnit = "ampere" value = "11.235" xsi:type="ts:TS_double" flags = "0x0000"/>
							</c:Limit>
						</c:LimitPair>
					</tr:Limits>
				</tr:TestLimits>
			</tr:TestResult>
		</tr:Test>
		<tr:Test ID = "1112" name = "TE CH2 Negative Direction Check" startDateTime = "2022-04-13T18:40:52.741"  endDateTime = "2022-04-13T18:40:53.523"  testReferenceID="ID#:rm6qR2MdC0+ViheEO+3QWC">
			<tr:Extension>
				<ts:TSStepProperties>
					<ts:StepType>NumericLimitTest</ts:StepType>
					<ts:StepGroup>Main</ts:StepGroup>
					<ts:BlockLevel value='0'/>
					<ts:Index value='50'/>
					<ts:TotalTime value='0.78127'/>
					<ts:ModuleTime value='0.78127'/>
				</ts:TSStepProperties>
			</tr:Extension>
			<tr:Outcome value = "Passed" />
			<tr:TestResult ID = "tr820D0413T2357Z777" name = "Numeric">
				<tr:TestData>
					<c:Datum value = "-10.72511675" xsi:type="ts:TS_double" nonStandardUnit="ampere" flags = "0x2400"/>
				</tr:TestData>
				<tr:TestLimits>
					<tr:Limits>
						<c:LimitPair operator = "AND">
							<c:Limit comparator = "GE">
								<c:Datum nonStandardUnit = "ampere" value = "-11.235" xsi:type="ts:TS_double" flags = "0x0000"/>
							</c:Limit>
							<c:Limit comparator = "LE">
								<c:Datum nonStandardUnit = "ampere" value = "-10.165" xsi:type="ts:TS_double" flags = "0x0000"/>
							</c:Limit>
						</c:LimitPair>
					</tr:Limits>
				</tr:TestLimits>
			</tr:TestResult>
		</tr:Test>
		<tr:Test ID = "1113" name = "TE CH3 Posistive Direction Check" startDateTime = "2022-04-13T18:40:53.536"  endDateTime = "2022-04-13T18:40:54.339"  testReferenceID="ID#:wRiEJh5U+Eun0KY+R/t4tC">
			<tr:Extension>
				<ts:TSStepProperties>
					<ts:StepType>NumericLimitTest</ts:StepType>
					<ts:StepGroup>Main</ts:StepGroup>
					<ts:BlockLevel value='0'/>
					<ts:Index value='51'/>
					<ts:TotalTime value='0.803509'/>
					<ts:ModuleTime value='0.803509'/>
				</ts:TSStepProperties>
			</tr:Extension>
			<tr:Outcome value = "Passed" />
			<tr:TestResult ID = "tr821D0413T2357Z777" name = "Numeric">
				<tr:TestData>
					<c:Datum value = "10.66019313333" xsi:type="ts:TS_double" nonStandardUnit="ampere" flags = "0x2400"/>
				</tr:TestData>
				<tr:TestLimits>
					<tr:Limits>
						<c:LimitPair operator = "AND">
							<c:Limit comparator = "GE">
								<c:Datum nonStandardUnit = "ampere" value = "10.165" xsi:type="ts:TS_double" flags = "0x0000"/>
							</c:Limit>
							<c:Limit comparator = "LE">
								<c:Datum nonStandardUnit = "ampere" value = "11.235" xsi:type="ts:TS_double" flags = "0x0000"/>
							</c:Limit>
						</c:LimitPair>
					</tr:Limits>
				</tr:TestLimits>
			</tr:TestResult>
		</tr:Test>
		<tr:Test ID = "1114" name = "TE CH3 Negative Direction Check" startDateTime = "2022-04-13T18:40:54.352"  endDateTime = "2022-04-13T18:40:55.167"  testReferenceID="ID#:coDVB3H0dkyDIE9HayPZJB">
			<tr:Extension>
				<ts:TSStepProperties>
					<ts:StepType>NumericLimitTest</ts:StepType>
					<ts:StepGroup>Main</ts:StepGroup>
					<ts:BlockLevel value='0'/>
					<ts:Index value='52'/>
					<ts:TotalTime value='0.814703'/>
					<ts:ModuleTime value='0.814703'/>
				</ts:TSStepProperties>
			</tr:Extension>
			<tr:Outcome value = "Passed" />
			<tr:TestResult ID = "tr822D0413T2357Z777" name = "Numeric">
				<tr:TestData>
					<c:Datum value = "-10.67108613333" xsi:type="ts:TS_double" nonStandardUnit="ampere" flags = "0x2400"/>
				</tr:TestData>
				<tr:TestLimits>
					<tr:Limits>
						<c:LimitPair operator = "AND">
							<c:Limit comparator = "GE">
								<c:Datum nonStandardUnit = "ampere" value = "-11.235" xsi:type="ts:TS_double" flags = "0x0000"/>
							</c:Limit>
							<c:Limit comparator = "LE">
								<c:Datum nonStandardUnit = "ampere" value = "-10.165" xsi:type="ts:TS_double" flags = "0x0000"/>
							</c:Limit>
						</c:LimitPair>
					</tr:Limits>
				</tr:TestLimits>
			</tr:TestResult>
		</tr:Test>
		<tr:Test ID = "1115" name = "TE CH4 Posistive Direction Check" startDateTime = "2022-04-13T18:40:55.180"  endDateTime = "2022-04-13T18:40:55.972"  testReferenceID="ID#:5MY0Qves/0Smny/+tmcmqA">
			<tr:Extension>
				<ts:TSStepProperties>
					<ts:StepType>NumericLimitTest</ts:StepType>
					<ts:StepGroup>Main</ts:StepGroup>
					<ts:BlockLevel value='0'/>
					<ts:Index value='53'/>
					<ts:TotalTime value='0.79211'/>
					<ts:ModuleTime value='0.79211'/>
				</ts:TSStepProperties>
			</tr:Extension>
			<tr:Outcome value = "Passed" />
			<tr:TestResult ID = "tr823D0413T2357Z777" name = "Numeric">
				<tr:TestData>
					<c:Datum value = "10.67026565" xsi:type="ts:TS_double" nonStandardUnit="ampere" flags = "0x2400"/>
				</tr:TestData>
				<tr:TestLimits>
					<tr:Limits>
						<c:LimitPair operator = "AND">
							<c:Limit comparator = "GE">
								<c:Datum nonStandardUnit = "ampere" value = "10.165" xsi:type="ts:TS_double" flags = "0x0000"/>
							</c:Limit>
							<c:Limit comparator = "LE">
								<c:Datum nonStandardUnit = "ampere" value = "11.235" xsi:type="ts:TS_double" flags = "0x0000"/>
							</c:Limit>
						</c:LimitPair>
					</tr:Limits>
				</tr:TestLimits>
			</tr:TestResult>
		</tr:Test>
		<tr:Test ID = "1116" name = "TE CH4 Negative Direction Check" startDateTime = "2022-04-13T18:40:55.986"  endDateTime = "2022-04-13T18:40:56.773"  testReferenceID="ID#:Y+gR6YcIxU+RqEpITdJ/AB">
			<tr:Extension>
				<ts:TSStepProperties>
					<ts:StepType>NumericLimitTest</ts:StepType>
					<ts:StepGroup>Main</ts:StepGroup>
					<ts:BlockLevel value='0'/>
					<ts:Index value='54'/>
					<ts:TotalTime value='0.787017'/>
					<ts:ModuleTime value='0.787017'/>
				</ts:TSStepProperties>
			</tr:Extension>
			<tr:Outcome value = "Passed" />
			<tr:TestResult ID = "tr824D0413T2357Z777" name = "Numeric">
				<tr:TestData>
					<c:Datum value = "-10.66421523333" xsi:type="ts:TS_double" nonStandardUnit="ampere" flags = "0x2400"/>
				</tr:TestData>
				<tr:TestLimits>
					<tr:Limits>
						<c:LimitPair operator = "AND">
							<c:Limit comparator = "GE">
								<c:Datum nonStandardUnit = "ampere" value = "-11.235" xsi:type="ts:TS_double" flags = "0x0000"/>
							</c:Limit>
							<c:Limit comparator = "LE">
								<c:Datum nonStandardUnit = "ampere" value = "-10.165" xsi:type="ts:TS_double" flags = "0x0000"/>
							</c:Limit>
						</c:LimitPair>
					</tr:Limits>
				</tr:TestLimits>
			</tr:TestResult>
		</tr:Test>
		<tr:Test ID = "1117" name = "TE CH5 Posistive Direction Check" startDateTime = "2022-04-13T18:40:56.810"  endDateTime = "2022-04-13T18:40:57.599"  testReferenceID="ID#:BaOtgXz+REuaodw2owY5qD">
			<tr:Extension>
				<ts:TSStepProperties>
					<ts:StepType>NumericLimitTest</ts:StepType>
					<ts:StepGroup>Main</ts:StepGroup>
					<ts:BlockLevel value='0'/>
					<ts:Index value='55'/>
					<ts:TotalTime value='0.789049'/>
					<ts:ModuleTime value='0.789049'/>
				</ts:TSStepProperties>
			</tr:Extension>
			<tr:Outcome value = "Passed" />
			<tr:TestResult ID = "tr825D0413T2357Z777" name = "Numeric">
				<tr:TestData>
					<c:Datum value = "10.66295661667" xsi:type="ts:TS_double" nonStandardUnit="ampere" flags = "0x2400"/>
				</tr:TestData>
				<tr:TestLimits>
					<tr:Limits>
						<c:LimitPair operator = "AND">
							<c:Limit comparator = "GE">
								<c:Datum nonStandardUnit = "ampere" value = "10.165" xsi:type="ts:TS_double" flags = "0x0000"/>
							</c:Limit>
							<c:Limit comparator = "LE">
								<c:Datum nonStandardUnit = "ampere" value = "11.235" xsi:type="ts:TS_double" flags = "0x0000"/>
							</c:Limit>
						</c:LimitPair>
					</tr:Limits>
				</tr:TestLimits>
			</tr:TestResult>
		</tr:Test>
		<tr:Test ID = "1118" name = "TE CH5 Negative Direction Check" startDateTime = "2022-04-13T18:40:57.612"  endDateTime = "2022-04-13T18:40:58.407"  testReferenceID="ID#:VE/CPzbXEUGoC2cohZLciB">
			<tr:Extension>
				<ts:TSStepProperties>
					<ts:StepType>NumericLimitTest</ts:StepType>
					<ts:StepGroup>Main</ts:StepGroup>
					<ts:BlockLevel value='0'/>
					<ts:Index value='56'/>
					<ts:TotalTime value='0.795644'/>
					<ts:ModuleTime value='0.795644'/>
				</ts:TSStepProperties>
			</tr:Extension>
			<tr:Outcome value = "Passed" />
			<tr:TestResult ID = "tr826D0413T2357Z777" name = "Numeric">
				<tr:TestData>
					<c:Datum value = "-10.65640521667" xsi:type="ts:TS_double" nonStandardUnit="ampere" flags = "0x2400"/>
				</tr:TestData>
				<tr:TestLimits>
					<tr:Limits>
						<c:LimitPair operator = "AND">
							<c:Limit comparator = "GE">
								<c:Datum nonStandardUnit = "ampere" value = "-11.235" xsi:type="ts:TS_double" flags = "0x0000"/>
							</c:Limit>
							<c:Limit comparator = "LE">
								<c:Datum nonStandardUnit = "ampere" value = "-10.165" xsi:type="ts:TS_double" flags = "0x0000"/>
							</c:Limit>
						</c:LimitPair>
					</tr:Limits>
				</tr:TestLimits>
			</tr:TestResult>
		</tr:Test>
		<tr:Test ID = "1119" name = "TE CH0 4.9A Current Check" startDateTime = "2022-04-13T18:40:58.420"  endDateTime = "2022-04-13T18:40:59.215"  testReferenceID="ID#:HXtev7hBbEqHckdeyDggjC">
			<tr:Extension>
				<ts:TSStepProperties>
					<ts:StepType>NumericLimitTest</ts:StepType>
					<ts:StepGroup>Main</ts:StepGroup>
					<ts:BlockLevel value='0'/>
					<ts:Index value='57'/>
					<ts:TotalTime value='0.794895'/>
					<ts:ModuleTime value='0.794895'/>
				</ts:TSStepProperties>
			</tr:Extension>
			<tr:Outcome value = "Passed" />
			<tr:TestResult ID = "tr827D0413T2357Z777" name = "Numeric">
				<tr:TestData>
					<c:Datum value = "4.897912633333" xsi:type="ts:TS_double" nonStandardUnit="ampere" flags = "0x2400"/>
				</tr:TestData>
				<tr:TestLimits>
					<tr:Limits>
						<c:LimitPair operator = "AND">
							<c:Limit comparator = "GE">
								<c:Datum nonStandardUnit = "ampere" value = "4.65" xsi:type="ts:TS_double" flags = "0x0000"/>
							</c:Limit>
							<c:Limit comparator = "LE">
								<c:Datum nonStandardUnit = "ampere" value = "5.15" xsi:type="ts:TS_double" flags = "0x0000"/>
							</c:Limit>
						</c:LimitPair>
					</tr:Limits>
				</tr:TestLimits>
			</tr:TestResult>
		</tr:Test>
		<tr:Test ID = "1120" name = "TE CH1 4.9A Current Check" startDateTime = "2022-04-13T18:40:59.229"  endDateTime = "2022-04-13T18:41:00.023"  testReferenceID="ID#:E9ohR7rRd06h1Ub0N5DZyA">
			<tr:Extension>
				<ts:TSStepProperties>
					<ts:StepType>NumericLimitTest</ts:StepType>
					<ts:StepGroup>Main</ts:StepGroup>
					<ts:BlockLevel value='0'/>
					<ts:Index value='58'/>
					<ts:TotalTime value='0.793866'/>
					<ts:ModuleTime value='0.793866'/>
				</ts:TSStepProperties>
			</tr:Extension>
			<tr:Outcome value = "Passed" />
			<tr:TestResult ID = "tr828D0413T2357Z777" name = "Numeric">
				<tr:TestData>
					<c:Datum value = "4.9406549" xsi:type="ts:TS_double" nonStandardUnit="ampere" flags = "0x2400"/>
				</tr:TestData>
				<tr:TestLimits>
					<tr:Limits>
						<c:LimitPair operator = "AND">
							<c:Limit comparator = "GE">
								<c:Datum nonStandardUnit = "ampere" value = "4.65" xsi:type="ts:TS_double" flags = "0x0000"/>
							</c:Limit>
							<c:Limit comparator = "LE">
								<c:Datum nonStandardUnit = "ampere" value = "5.15" xsi:type="ts:TS_double" flags = "0x0000"/>
							</c:Limit>
						</c:LimitPair>
					</tr:Limits>
				</tr:TestLimits>
			</tr:TestResult>
		</tr:Test>
		<tr:Test ID = "1121" name = "TE CH2 4.9A Current Check" startDateTime = "2022-04-13T18:41:00.036"  endDateTime = "2022-04-13T18:41:00.808"  testReferenceID="ID#:Y3I5o2JSWECvuZc5LEbuSC">
			<tr:Extension>
				<ts:TSStepProperties>
					<ts:StepType>NumericLimitTest</ts:StepType>
					<ts:StepGroup>Main</ts:StepGroup>
					<ts:BlockLevel value='0'/>
					<ts:Index value='59'/>
					<ts:TotalTime value='0.771234'/>
					<ts:ModuleTime value='0.771234'/>
				</ts:TSStepProperties>
			</tr:Extension>
			<tr:Outcome value = "Passed" />
			<tr:TestResult ID = "tr829D0413T2357Z777" name = "Numeric">
				<tr:TestData>
					<c:Datum value = "4.950385466667" xsi:type="ts:TS_double" nonStandardUnit="ampere" flags = "0x2400"/>
				</tr:TestData>
				<tr:TestLimits>
					<tr:Limits>
						<c:LimitPair operator = "AND">
							<c:Limit comparator = "GE">
								<c:Datum nonStandardUnit = "ampere" value = "4.65" xsi:type="ts:TS_double" flags = "0x0000"/>
							</c:Limit>
							<c:Limit comparator = "LE">
								<c:Datum nonStandardUnit = "ampere" value = "5.15" xsi:type="ts:TS_double" flags = "0x0000"/>
							</c:Limit>
						</c:LimitPair>
					</tr:Limits>
				</tr:TestLimits>
			</tr:TestResult>
		</tr:Test>
		<tr:Test ID = "1122" name = "TE CH3 4.9A Current Check" startDateTime = "2022-04-13T18:41:00.820"  endDateTime = "2022-04-13T18:41:01.614"  testReferenceID="ID#:cgTfSE0f50qk4vd7/g62eA">
			<tr:Extension>
				<ts:TSStepProperties>
					<ts:StepType>NumericLimitTest</ts:StepType>
					<ts:StepGroup>Main</ts:StepGroup>
					<ts:BlockLevel value='0'/>
					<ts:Index value='60'/>
					<ts:TotalTime value='0.793496'/>
					<ts:ModuleTime value='0.793496'/>
				</ts:TSStepProperties>
			</tr:Extension>
			<tr:Outcome value = "Passed" />
			<tr:TestResult ID = "tr830D0413T2357Z777" name = "Numeric">
				<tr:TestData>
					<c:Datum value = "4.84403495" xsi:type="ts:TS_double" nonStandardUnit="ampere" flags = "0x2400"/>
				</tr:TestData>
				<tr:TestLimits>
					<tr:Limits>
						<c:LimitPair operator = "AND">
							<c:Limit comparator = "GE">
								<c:Datum nonStandardUnit = "ampere" value = "4.65" xsi:type="ts:TS_double" flags = "0x0000"/>
							</c:Limit>
							<c:Limit comparator = "LE">
								<c:Datum nonStandardUnit = "ampere" value = "5.15" xsi:type="ts:TS_double" flags = "0x0000"/>
							</c:Limit>
						</c:LimitPair>
					</tr:Limits>
				</tr:TestLimits>
			</tr:TestResult>
		</tr:Test>
		<tr:Test ID = "1123" name = "TE CH4 4.9A Current Check" startDateTime = "2022-04-13T18:41:01.627"  endDateTime = "2022-04-13T18:41:02.413"  testReferenceID="ID#:qZmQ+0ejzUCfnDZbcGD3FD">
			<tr:Extension>
				<ts:TSStepProperties>
					<ts:StepType>NumericLimitTest</ts:StepType>
					<ts:StepGroup>Main</ts:StepGroup>
					<ts:BlockLevel value='0'/>
					<ts:Index value='61'/>
					<ts:TotalTime value='0.785952'/>
					<ts:ModuleTime value='0.785952'/>
				</ts:TSStepProperties>
			</tr:Extension>
			<tr:Outcome value = "Passed" />
			<tr:TestResult ID = "tr831D0413T2357Z777" name = "Numeric">
				<tr:TestData>
					<c:Datum value = "4.897586316667" xsi:type="ts:TS_double" nonStandardUnit="ampere" flags = "0x2400"/>
				</tr:TestData>
				<tr:TestLimits>
					<tr:Limits>
						<c:LimitPair operator = "AND">
							<c:Limit comparator = "GE">
								<c:Datum nonStandardUnit = "ampere" value = "4.65" xsi:type="ts:TS_double" flags = "0x0000"/>
							</c:Limit>
							<c:Limit comparator = "LE">
								<c:Datum nonStandardUnit = "ampere" value = "5.15" xsi:type="ts:TS_double" flags = "0x0000"/>
							</c:Limit>
						</c:LimitPair>
					</tr:Limits>
				</tr:TestLimits>
			</tr:TestResult>
		</tr:Test>
		<tr:Test ID = "1124" name = "TE CH5 4.9A Current Check" startDateTime = "2022-04-13T18:41:02.426"  endDateTime = "2022-04-13T18:41:03.215"  testReferenceID="ID#:W+O0m6YLCUyKsJZATJ5u7D">
			<tr:Extension>
				<ts:TSStepProperties>
					<ts:StepType>NumericLimitTest</ts:StepType>
					<ts:StepGroup>Main</ts:StepGroup>
					<ts:BlockLevel value='0'/>
					<ts:Index value='62'/>
					<ts:TotalTime value='0.789287'/>
					<ts:ModuleTime value='0.789287'/>
				</ts:TSStepProperties>
			</tr:Extension>
			<tr:Outcome value = "Passed" />
			<tr:TestResult ID = "tr832D0413T2357Z777" name = "Numeric">
				<tr:TestData>
					<c:Datum value = "4.8987273" xsi:type="ts:TS_double" nonStandardUnit="ampere" flags = "0x2400"/>
				</tr:TestData>
				<tr:TestLimits>
					<tr:Limits>
						<c:LimitPair operator = "AND">
							<c:Limit comparator = "GE">
								<c:Datum nonStandardUnit = "ampere" value = "4.65" xsi:type="ts:TS_double" flags = "0x0000"/>
							</c:Limit>
							<c:Limit comparator = "LE">
								<c:Datum nonStandardUnit = "ampere" value = "5.15" xsi:type="ts:TS_double" flags = "0x0000"/>
							</c:Limit>
						</c:LimitPair>
					</tr:Limits>
				</tr:TestLimits>
			</tr:TestResult>
		</tr:Test>
		<tr:Test ID = "1125" name = "TE CH0 1.3A Current Check" startDateTime = "2022-04-13T18:41:03.226"  endDateTime = "2022-04-13T18:41:04.015"  testReferenceID="ID#:zAMmmENuhU6nwXzNCkCpAB">
			<tr:Extension>
				<ts:TSStepProperties>
					<ts:StepType>NumericLimitTest</ts:StepType>
					<ts:StepGroup>Main</ts:StepGroup>
					<ts:BlockLevel value='0'/>
					<ts:Index value='63'/>
					<ts:TotalTime value='0.789332'/>
					<ts:ModuleTime value='0.789332'/>
				</ts:TSStepProperties>
			</tr:Extension>
			<tr:Outcome value = "Passed" />
			<tr:TestResult ID = "tr833D0413T2357Z777" name = "Numeric">
				<tr:TestData>
					<c:Datum value = "1.443605921667" xsi:type="ts:TS_double" nonStandardUnit="ampere" flags = "0x2400"/>
				</tr:TestData>
				<tr:TestLimits>
					<tr:Limits>
						<c:LimitPair operator = "AND">
							<c:Limit comparator = "GE">
								<c:Datum nonStandardUnit = "ampere" value = "1.214" xsi:type="ts:TS_double" flags = "0x0000"/>
							</c:Limit>
							<c:Limit comparator = "LE">
								<c:Datum nonStandardUnit = "ampere" value = "1.64" xsi:type="ts:TS_double" flags = "0x0000"/>
							</c:Limit>
						</c:LimitPair>
					</tr:Limits>
				</tr:TestLimits>
			</tr:TestResult>
		</tr:Test>
		<tr:Test ID = "1126" name = "TE CH1 1.3A Current Check" startDateTime = "2022-04-13T18:41:04.028"  endDateTime = "2022-04-13T18:41:04.825"  testReferenceID="ID#:+mkxle4HCUuueQvr1qk9lA">
			<tr:Extension>
				<ts:TSStepProperties>
					<ts:StepType>NumericLimitTest</ts:StepType>
					<ts:StepGroup>Main</ts:StepGroup>
					<ts:BlockLevel value='0'/>
					<ts:Index value='64'/>
					<ts:TotalTime value='0.796963'/>
					<ts:ModuleTime value='0.796963'/>
				</ts:TSStepProperties>
			</tr:Extension>
			<tr:Outcome value = "Passed" />
			<tr:TestResult ID = "tr834D0413T2357Z777" name = "Numeric">
				<tr:TestData>
					<c:Datum value = "1.459209033333" xsi:type="ts:TS_double" nonStandardUnit="ampere" flags = "0x2400"/>
				</tr:TestData>
				<tr:TestLimits>
					<tr:Limits>
						<c:LimitPair operator = "AND">
							<c:Limit comparator = "GE">
								<c:Datum nonStandardUnit = "ampere" value = "1.314" xsi:type="ts:TS_double" flags = "0x0000"/>
							</c:Limit>
							<c:Limit comparator = "LE">
								<c:Datum nonStandardUnit = "ampere" value = "1.64" xsi:type="ts:TS_double" flags = "0x0000"/>
							</c:Limit>
						</c:LimitPair>
					</tr:Limits>
				</tr:TestLimits>
			</tr:TestResult>
		</tr:Test>
		<tr:Test ID = "1127" name = "TE CH2 1.3A Current Check" startDateTime = "2022-04-13T18:41:04.839"  endDateTime = "2022-04-13T18:41:05.641"  testReferenceID="ID#:dQAAUs4UnE2mZArRjriTfB">
			<tr:Extension>
				<ts:TSStepProperties>
					<ts:StepType>NumericLimitTest</ts:StepType>
					<ts:StepGroup>Main</ts:StepGroup>
					<ts:BlockLevel value='0'/>
					<ts:Index value='65'/>
					<ts:TotalTime value='0.802065'/>
					<ts:ModuleTime value='0.802065'/>
				</ts:TSStepProperties>
			</tr:Extension>
			<tr:Outcome value = "Passed" />
			<tr:TestResult ID = "tr835D0413T2357Z777" name = "Numeric">
				<tr:TestData>
					<c:Datum value = "1.467788556667" xsi:type="ts:TS_double" nonStandardUnit="ampere" flags = "0x2400"/>
				</tr:TestData>
				<tr:TestLimits>
					<tr:Limits>
						<c:LimitPair operator = "AND">
							<c:Limit comparator = "GE">
								<c:Datum nonStandardUnit = "ampere" value = "1.314" xsi:type="ts:TS_double" flags = "0x0000"/>
							</c:Limit>
							<c:Limit comparator = "LE">
								<c:Datum nonStandardUnit = "ampere" value = "1.64" xsi:type="ts:TS_double" flags = "0x0000"/>
							</c:Limit>
						</c:LimitPair>
					</tr:Limits>
				</tr:TestLimits>
			</tr:TestResult>
		</tr:Test>
		<tr:Test ID = "1128" name = "TE CH3 1.3A Current Check" startDateTime = "2022-04-13T18:41:05.653"  endDateTime = "2022-04-13T18:41:06.446"  testReferenceID="ID#:/oo1b9hIYEyxdUgLN0ylID">
			<tr:Extension>
				<ts:TSStepProperties>
					<ts:StepType>NumericLimitTest</ts:StepType>
					<ts:StepGroup>Main</ts:StepGroup>
					<ts:BlockLevel value='0'/>
					<ts:StepCausedSequenceFailure value='true'/>
					<ts:Index value='66'/>
					<ts:TotalTime value='0.793045'/>
					<ts:ModuleTime value='0.793045'/>
				</ts:TSStepProperties>
			</tr:Extension>
			<tr:Outcome value = "Failed" />
			<tr:TestResult ID = "tr836D0413T2357Z777" name = "Numeric">
				<tr:TestData>
					<c:Datum value = "1.189061411667" xsi:type="ts:TS_double" nonStandardUnit="ampere" flags = "0x2400"/>
				</tr:TestData>
				<tr:TestLimits>
					<tr:Limits>
						<c:LimitPair operator = "AND">
							<c:Limit comparator = "GE">
								<c:Datum nonStandardUnit = "ampere" value = "1.314" xsi:type="ts:TS_double" flags = "0x0000"/>
							</c:Limit>
							<c:Limit comparator = "LE">
								<c:Datum nonStandardUnit = "ampere" value = "1.64" xsi:type="ts:TS_double" flags = "0x0000"/>
							</c:Limit>
						</c:LimitPair>
					</tr:Limits>
				</tr:TestLimits>
			</tr:TestResult>
		</tr:Test>
		<tr:Test ID = "1129" name = "TE CH4 1.3A Current Check" startDateTime = "2022-04-13T18:41:06.457"  endDateTime = "2022-04-13T18:41:12.873"  testReferenceID="ID#:OWUY9JrbL0y0W9igGkvdlC">
			<tr:Extension>
				<ts:TSStepProperties>
					<ts:StepType>NumericLimitTest</ts:StepType>
					<ts:StepGroup>Main</ts:StepGroup>
					<ts:BlockLevel value='0'/>
					<ts:Index value='67'/>
					<ts:LoopingProperties>
						<ts:NumLoops value='8' xsi:type='c:double'/>
						<ts:NumPassed value='8' xsi:type='c:double'/>
						<ts:NumFailed value='0' xsi:type='c:double'/>
						<ts:EndingLoopIndex value='8' xsi:type='c:double'/>
					</ts:LoopingProperties>
					<ts:TotalTime value='6.41562'/>
					<ts:ModuleTime value='6.41562'/>
				</ts:TSStepProperties>
			</tr:Extension>
			<tr:Outcome value = "Passed" />
			<tr:TestResult ID = "tr837D0413T2357Z777" name = "Numeric">
				<tr:TestData>
					<c:Datum value = "1.417858288333" xsi:type="ts:TS_double" nonStandardUnit="ampere" flags = "0x2400"/>
				</tr:TestData>
				<tr:TestLimits>
					<tr:Limits>
						<c:LimitPair operator = "AND">
							<c:Limit comparator = "GE">
								<c:Datum nonStandardUnit = "ampere" value = "1.314" xsi:type="ts:TS_double" flags = "0x0000"/>
							</c:Limit>
							<c:Limit comparator = "LE">
								<c:Datum nonStandardUnit = "ampere" value = "1.64" xsi:type="ts:TS_double" flags = "0x0000"/>
							</c:Limit>
						</c:LimitPair>
					</tr:Limits>
				</tr:TestLimits>
			</tr:TestResult>
		</tr:Test>
		<tr:Test ID = "1130" name = "TE CH4 1.3A Current Check (Loop Index:0)"  startDateTime = "2022-04-13T18:41:06.457"  endDateTime = "2022-04-13T18:41:07.273"  testReferenceID="ID#:OWUY9JrbL0y0W9igGkvdlC">
			<tr:Extension>
				<ts:TSStepProperties>
					<ts:StepType>NumericLimitTest</ts:StepType>
					<ts:StepGroup>Main</ts:StepGroup>
					<ts:BlockLevel value='0'/>
					<ts:Index value='67'/>
					<ts:LoopingProperties>
						<ts:LoopIndex value='0' xsi:type='c:double'/>
					</ts:LoopingProperties>
					<ts:TotalTime value='0.815904'/>
					<ts:ModuleTime value='0.815904'/>
				</ts:TSStepProperties>
			</tr:Extension>
			<tr:Outcome value = "Passed" />
			<tr:TestResult ID = "tr838D0413T2357Z777" name = "Numeric">
				<tr:TestData>
					<c:Datum value = "1.416021175" xsi:type="ts:TS_double" nonStandardUnit="ampere" flags = "0x2400"/>
				</tr:TestData>
				<tr:TestLimits>
					<tr:Limits>
						<c:LimitPair operator = "AND">
							<c:Limit comparator = "GE">
								<c:Datum nonStandardUnit = "ampere" value = "1.314" xsi:type="ts:TS_double" flags = "0x0000"/>
							</c:Limit>
							<c:Limit comparator = "LE">
								<c:Datum nonStandardUnit = "ampere" value = "1.64" xsi:type="ts:TS_double" flags = "0x0000"/>
							</c:Limit>
						</c:LimitPair>
					</tr:Limits>
				</tr:TestLimits>
			</tr:TestResult>
		</tr:Test>
		<tr:Test ID = "1131" name = "TE CH4 1.3A Current Check (Loop Index:1)"  startDateTime = "2022-04-13T18:41:07.277"  endDateTime = "2022-04-13T18:41:08.071"  testReferenceID="ID#:OWUY9JrbL0y0W9igGkvdlC">
			<tr:Extension>
				<ts:TSStepProperties>
					<ts:StepType>NumericLimitTest</ts:StepType>
					<ts:StepGroup>Main</ts:StepGroup>
					<ts:BlockLevel value='0'/>
					<ts:Index value='67'/>
					<ts:LoopingProperties>
						<ts:LoopIndex value='1' xsi:type='c:double'/>
					</ts:LoopingProperties>
					<ts:TotalTime value='0.793804'/>
					<ts:ModuleTime value='0.793804'/>
				</ts:TSStepProperties>
			</tr:Extension>
			<tr:Outcome value = "Passed" />
			<tr:TestResult ID = "tr839D0413T2357Z777" name = "Numeric">
				<tr:TestData>
					<c:Datum value = "1.418305396667" xsi:type="ts:TS_double" nonStandardUnit="ampere" flags = "0x2400"/>
				</tr:TestData>
				<tr:TestLimits>
					<tr:Limits>
						<c:LimitPair operator = "AND">
							<c:Limit comparator = "GE">
								<c:Datum nonStandardUnit = "ampere" value = "1.314" xsi:type="ts:TS_double" flags = "0x0000"/>
							</c:Limit>
							<c:Limit comparator = "LE">
								<c:Datum nonStandardUnit = "ampere" value = "1.64" xsi:type="ts:TS_double" flags = "0x0000"/>
							</c:Limit>
						</c:LimitPair>
					</tr:Limits>
				</tr:TestLimits>
			</tr:TestResult>
		</tr:Test>
		<tr:Test ID = "1132" name = "TE CH4 1.3A Current Check (Loop Index:2)"  startDateTime = "2022-04-13T18:41:08.075"  endDateTime = "2022-04-13T18:41:08.870"  testReferenceID="ID#:OWUY9JrbL0y0W9igGkvdlC">
			<tr:Extension>
				<ts:TSStepProperties>
					<ts:StepType>NumericLimitTest</ts:StepType>
					<ts:StepGroup>Main</ts:StepGroup>
					<ts:BlockLevel value='0'/>
					<ts:Index value='67'/>
					<ts:LoopingProperties>
						<ts:LoopIndex value='2' xsi:type='c:double'/>
					</ts:LoopingProperties>
					<ts:TotalTime value='0.795041'/>
					<ts:ModuleTime value='0.795041'/>
				</ts:TSStepProperties>
			</tr:Extension>
			<tr:Outcome value = "Passed" />
			<tr:TestResult ID = "tr840D0413T2357Z777" name = "Numeric">
				<tr:TestData>
					<c:Datum value = "1.415193825" xsi:type="ts:TS_double" nonStandardUnit="ampere" flags = "0x2400"/>
				</tr:TestData>
				<tr:TestLimits>
					<tr:Limits>
						<c:LimitPair operator = "AND">
							<c:Limit comparator = "GE">
								<c:Datum nonStandardUnit = "ampere" value = "1.314" xsi:type="ts:TS_double" flags = "0x0000"/>
							</c:Limit>
							<c:Limit comparator = "LE">
								<c:Datum nonStandardUnit = "ampere" value = "1.64" xsi:type="ts:TS_double" flags = "0x0000"/>
							</c:Limit>
						</c:LimitPair>
					</tr:Limits>
				</tr:TestLimits>
			</tr:TestResult>
		</tr:Test>
		<tr:Test ID = "1133" name = "TE CH4 1.3A Current Check (Loop Index:3)"  startDateTime = "2022-04-13T18:41:08.875"  endDateTime = "2022-04-13T18:41:09.667"  testReferenceID="ID#:OWUY9JrbL0y0W9igGkvdlC">
			<tr:Extension>
				<ts:TSStepProperties>
					<ts:StepType>NumericLimitTest</ts:StepType>
					<ts:StepGroup>Main</ts:StepGroup>
					<ts:BlockLevel value='0'/>
					<ts:Index value='67'/>
					<ts:LoopingProperties>
						<ts:LoopIndex value='3' xsi:type='c:double'/>
					</ts:LoopingProperties>
					<ts:TotalTime value='0.792446'/>
					<ts:ModuleTime value='0.792446'/>
				</ts:TSStepProperties>
			</tr:Extension>
			<tr:Outcome value = "Passed" />
			<tr:TestResult ID = "tr841D0413T2357Z777" name = "Numeric">
				<tr:TestData>
					<c:Datum value = "1.414800911667" xsi:type="ts:TS_double" nonStandardUnit="ampere" flags = "0x2400"/>
				</tr:TestData>
				<tr:TestLimits>
					<tr:Limits>
						<c:LimitPair operator = "AND">
							<c:Limit comparator = "GE">
								<c:Datum nonStandardUnit = "ampere" value = "1.314" xsi:type="ts:TS_double" flags = "0x0000"/>
							</c:Limit>
							<c:Limit comparator = "LE">
								<c:Datum nonStandardUnit = "ampere" value = "1.64" xsi:type="ts:TS_double" flags = "0x0000"/>
							</c:Limit>
						</c:LimitPair>
					</tr:Limits>
				</tr:TestLimits>
			</tr:TestResult>
		</tr:Test>
		<tr:Test ID = "1134" name = "TE CH4 1.3A Current Check (Loop Index:4)"  startDateTime = "2022-04-13T18:41:09.669"  endDateTime = "2022-04-13T18:41:10.472"  testReferenceID="ID#:OWUY9JrbL0y0W9igGkvdlC">
			<tr:Extension>
				<ts:TSStepProperties>
					<ts:StepType>NumericLimitTest</ts:StepType>
					<ts:StepGroup>Main</ts:StepGroup>
					<ts:BlockLevel value='0'/>
					<ts:Index value='67'/>
					<ts:LoopingProperties>
						<ts:LoopIndex value='4' xsi:type='c:double'/>
					</ts:LoopingProperties>
					<ts:TotalTime value='0.803015'/>
					<ts:ModuleTime value='0.803015'/>
				</ts:TSStepProperties>
			</tr:Extension>
			<tr:Outcome value = "Passed" />
			<tr:TestResult ID = "tr842D0413T2357Z777" name = "Numeric">
				<tr:TestData>
					<c:Datum value = "1.415884363333" xsi:type="ts:TS_double" nonStandardUnit="ampere" flags = "0x2400"/>
				</tr:TestData>
				<tr:TestLimits>
					<tr:Limits>
						<c:LimitPair operator = "AND">
							<c:Limit comparator = "GE">
								<c:Datum nonStandardUnit = "ampere" value = "1.314" xsi:type="ts:TS_double" flags = "0x0000"/>
							</c:Limit>
							<c:Limit comparator = "LE">
								<c:Datum nonStandardUnit = "ampere" value = "1.64" xsi:type="ts:TS_double" flags = "0x0000"/>
							</c:Limit>
						</c:LimitPair>
					</tr:Limits>
				</tr:TestLimits>
			</tr:TestResult>
		</tr:Test>
		<tr:Test ID = "1135" name = "TE CH4 1.3A Current Check (Loop Index:5)"  startDateTime = "2022-04-13T18:41:10.477"  endDateTime = "2022-04-13T18:41:11.274"  testReferenceID="ID#:OWUY9JrbL0y0W9igGkvdlC">
			<tr:Extension>
				<ts:TSStepProperties>
					<ts:StepType>NumericLimitTest</ts:StepType>
					<ts:StepGroup>Main</ts:StepGroup>
					<ts:BlockLevel value='0'/>
					<ts:Index value='67'/>
					<ts:LoopingProperties>
						<ts:LoopIndex value='5' xsi:type='c:double'/>
					</ts:LoopingProperties>
					<ts:TotalTime value='0.797598'/>
					<ts:ModuleTime value='0.797598'/>
				</ts:TSStepProperties>
			</tr:Extension>
			<tr:Outcome value = "Passed" />
			<tr:TestResult ID = "tr843D0413T2357Z777" name = "Numeric">
				<tr:TestData>
					<c:Datum value = "1.416540163333" xsi:type="ts:TS_double" nonStandardUnit="ampere" flags = "0x2400"/>
				</tr:TestData>
				<tr:TestLimits>
					<tr:Limits>
						<c:LimitPair operator = "AND">
							<c:Limit comparator = "GE">
								<c:Datum nonStandardUnit = "ampere" value = "1.314" xsi:type="ts:TS_double" flags = "0x0000"/>
							</c:Limit>
							<c:Limit comparator = "LE">
								<c:Datum nonStandardUnit = "ampere" value = "1.64" xsi:type="ts:TS_double" flags = "0x0000"/>
							</c:Limit>
						</c:LimitPair>
					</tr:Limits>
				</tr:TestLimits>
			</tr:TestResult>
		</tr:Test>
		<tr:Test ID = "1136" name = "TE CH4 1.3A Current Check (Loop Index:6)"  startDateTime = "2022-04-13T18:41:11.279"  endDateTime = "2022-04-13T18:41:12.077"  testReferenceID="ID#:OWUY9JrbL0y0W9igGkvdlC">
			<tr:Extension>
				<ts:TSStepProperties>
					<ts:StepType>NumericLimitTest</ts:StepType>
					<ts:StepGroup>Main</ts:StepGroup>
					<ts:BlockLevel value='0'/>
					<ts:Index value='67'/>
					<ts:LoopingProperties>
						<ts:LoopIndex value='6' xsi:type='c:double'/>
					</ts:LoopingProperties>
					<ts:TotalTime value='0.798423'/>
					<ts:ModuleTime value='0.798423'/>
				</ts:TSStepProperties>
			</tr:Extension>
			<tr:Outcome value = "Passed" />
			<tr:TestResult ID = "tr844D0413T2357Z777" name = "Numeric">
				<tr:TestData>
					<c:Datum value = "1.419118781667" xsi:type="ts:TS_double" nonStandardUnit="ampere" flags = "0x2400"/>
				</tr:TestData>
				<tr:TestLimits>
					<tr:Limits>
						<c:LimitPair operator = "AND">
							<c:Limit comparator = "GE">
								<c:Datum nonStandardUnit = "ampere" value = "1.314" xsi:type="ts:TS_double" flags = "0x0000"/>
							</c:Limit>
							<c:Limit comparator = "LE">
								<c:Datum nonStandardUnit = "ampere" value = "1.64" xsi:type="ts:TS_double" flags = "0x0000"/>
							</c:Limit>
						</c:LimitPair>
					</tr:Limits>
				</tr:TestLimits>
			</tr:TestResult>
		</tr:Test>
		<tr:Test ID = "1137" name = "TE CH4 1.3A Current Check (Loop Index:7)"  startDateTime = "2022-04-13T18:41:12.081"  endDateTime = "2022-04-13T18:41:12.872"  testReferenceID="ID#:OWUY9JrbL0y0W9igGkvdlC">
			<tr:Extension>
				<ts:TSStepProperties>
					<ts:StepType>NumericLimitTest</ts:StepType>
					<ts:StepGroup>Main</ts:StepGroup>
					<ts:BlockLevel value='0'/>
					<ts:Index value='67'/>
					<ts:LoopingProperties>
						<ts:LoopIndex value='7' xsi:type='c:double'/>
					</ts:LoopingProperties>
					<ts:TotalTime value='0.791197'/>
					<ts:ModuleTime value='0.791197'/>
				</ts:TSStepProperties>
			</tr:Extension>
			<tr:Outcome value = "Passed" />
			<tr:TestResult ID = "tr845D0413T2357Z777" name = "Numeric">
				<tr:TestData>
					<c:Datum value = "1.417858288333" xsi:type="ts:TS_double" nonStandardUnit="ampere" flags = "0x2400"/>
				</tr:TestData>
				<tr:TestLimits>
					<tr:Limits>
						<c:LimitPair operator = "AND">
							<c:Limit comparator = "GE">
								<c:Datum nonStandardUnit = "ampere" value = "1.314" xsi:type="ts:TS_double" flags = "0x0000"/>
							</c:Limit>
							<c:Limit comparator = "LE">
								<c:Datum nonStandardUnit = "ampere" value = "1.64" xsi:type="ts:TS_double" flags = "0x0000"/>
							</c:Limit>
						</c:LimitPair>
					</tr:Limits>
				</tr:TestLimits>
			</tr:TestResult>
		</tr:Test>
		<tr:Test ID = "1138" name = "TE CH5 1.3A Current Check" startDateTime = "2022-04-13T18:41:12.887"  endDateTime = "2022-04-13T18:41:13.677"  testReferenceID="ID#:R0Ef4Ih3eUiMFNQqMTjZUA">
			<tr:Extension>
				<ts:TSStepProperties>
					<ts:StepType>NumericLimitTest</ts:StepType>
					<ts:StepGroup>Main</ts:StepGroup>
					<ts:BlockLevel value='0'/>
					<ts:Index value='68'/>
					<ts:LoopingProperties>
						<ts:NumLoops value='1' xsi:type='c:double'/>
						<ts:NumPassed value='1' xsi:type='c:double'/>
						<ts:NumFailed value='0' xsi:type='c:double'/>
						<ts:EndingLoopIndex value='1' xsi:type='c:double'/>
					</ts:LoopingProperties>
					<ts:TotalTime value='0.790182'/>
					<ts:ModuleTime value='0.790182'/>
				</ts:TSStepProperties>
			</tr:Extension>
			<tr:Outcome value = "Passed" />
			<tr:TestResult ID = "tr846D0413T2357Z777" name = "Numeric">
				<tr:TestData>
					<c:Datum value = "1.440192758333" xsi:type="ts:TS_double" nonStandardUnit="ampere" flags = "0x2400"/>
				</tr:TestData>
				<tr:TestLimits>
					<tr:Limits>
						<c:LimitPair operator = "AND">
							<c:Limit comparator = "GE">
								<c:Datum nonStandardUnit = "ampere" value = "1.314" xsi:type="ts:TS_double" flags = "0x0000"/>
							</c:Limit>
							<c:Limit comparator = "LE">
								<c:Datum nonStandardUnit = "ampere" value = "1.64" xsi:type="ts:TS_double" flags = "0x0000"/>
							</c:Limit>
						</c:LimitPair>
					</tr:Limits>
				</tr:TestLimits>
			</tr:TestResult>
		</tr:Test>
		<tr:Test ID = "1139" name = "Heartbeat Led Test" startDateTime = "2022-04-13T18:41:13.690"  endDateTime = "2022-04-13T18:41:47.434"  testReferenceID="ID#:EyKgFGEY0kqT47pLtUVfGB">
			<tr:Extension>
				<ts:TSStepProperties>
					<ts:StepType>PassFailTest</ts:StepType>
					<ts:StepGroup>Main</ts:StepGroup>
					<ts:BlockLevel value='0'/>
					<ts:Index value='69'/>
					<ts:TotalTime value='33.7439'/>
					<ts:ModuleTime value='33.7439'/>
				</ts:TSStepProperties>
			</tr:Extension>
			<tr:Outcome value = "Passed" />
		</tr:Test>
		<tr:Test ID = "1140" name = "External Led Blinking Test" startDateTime = "2022-04-13T18:41:47.444"  endDateTime = "2022-04-13T18:41:47.930"  testReferenceID="ID#:+qhaouIhzUSi4J9NjcFEqB">
			<tr:Extension>
				<ts:TSStepProperties>
					<ts:StepType>PassFailTest</ts:StepType>
					<ts:StepGroup>Main</ts:StepGroup>
					<ts:BlockLevel value='0'/>
					<ts:Index value='70'/>
					<ts:TotalTime value='0.486015'/>
					<ts:ModuleTime value='0.486015'/>
				</ts:TSStepProperties>
			</tr:Extension>
			<tr:Outcome value = "Passed" />
		</tr:Test>
		<tr:Test ID = "1141" name = "Low Lid 1 Voltage Check" startDateTime = "2022-04-13T18:41:47.948"  endDateTime = "2022-04-13T18:41:48.709"  testReferenceID="ID#:fVk977wyHUOWQIPid4rfrB">
			<tr:Extension>
				<ts:TSStepProperties>
					<ts:StepType>NumericLimitTest</ts:StepType>
					<ts:StepGroup>Main</ts:StepGroup>
					<ts:BlockLevel value='0'/>
					<ts:Index value='72'/>
					<ts:TotalTime value='0.760815'/>
					<ts:ModuleTime value='0.760815'/>
				</ts:TSStepProperties>
			</tr:Extension>
			<tr:Outcome value = "Passed" />
			<tr:TestResult ID = "tr847D0413T2357Z777" name = "Numeric">
				<tr:TestData>
					<c:Datum value = "19.5284186" xsi:type="ts:TS_double" nonStandardUnit="volt" flags = "0x2400"/>
				</tr:TestData>
				<tr:TestLimits>
					<tr:Limits>
						<c:LimitPair operator = "AND">
							<c:Limit comparator = "GE">
								<c:Datum nonStandardUnit = "volt" value = "18.7435" xsi:type="ts:TS_double" flags = "0x0000"/>
							</c:Limit>
							<c:Limit comparator = "LE">
								<c:Datum nonStandardUnit = "volt" value = "20.7165" xsi:type="ts:TS_double" flags = "0x0000"/>
							</c:Limit>
						</c:LimitPair>
					</tr:Limits>
				</tr:TestLimits>
			</tr:TestResult>
		</tr:Test>
		<tr:Test ID = "1142" name = "Low Lid 2 Voltage Check" startDateTime = "2022-04-13T18:41:48.713"  endDateTime = "2022-04-13T18:41:49.497"  testReferenceID="ID#:H0kPcLeDmEypF9qrc47cCD">
			<tr:Extension>
				<ts:TSStepProperties>
					<ts:StepType>NumericLimitTest</ts:StepType>
					<ts:StepGroup>Main</ts:StepGroup>
					<ts:BlockLevel value='0'/>
					<ts:Index value='73'/>
					<ts:TotalTime value='0.78373'/>
					<ts:ModuleTime value='0.78373'/>
				</ts:TSStepProperties>
			</tr:Extension>
			<tr:Outcome value = "Passed" />
			<tr:TestResult ID = "tr848D0413T2357Z777" name = "Numeric">
				<tr:TestData>
					<c:Datum value = "19.518774" xsi:type="ts:TS_double" nonStandardUnit="volt" flags = "0x2400"/>
				</tr:TestData>
				<tr:TestLimits>
					<tr:Limits>
						<c:LimitPair operator = "AND">
							<c:Limit comparator = "GE">
								<c:Datum nonStandardUnit = "volt" value = "18.7435" xsi:type="ts:TS_double" flags = "0x0000"/>
							</c:Limit>
							<c:Limit comparator = "LE">
								<c:Datum nonStandardUnit = "volt" value = "20.7165" xsi:type="ts:TS_double" flags = "0x0000"/>
							</c:Limit>
						</c:LimitPair>
					</tr:Limits>
				</tr:TestLimits>
			</tr:TestResult>
		</tr:Test>
		<tr:Test ID = "1143" name = "Hi Lid 1 Voltage Check" startDateTime = "2022-04-13T18:41:49.510"  endDateTime = "2022-04-13T18:41:50.311"  testReferenceID="ID#:Kk4NQpJUCECGblV0OdhKVB">
			<tr:Extension>
				<ts:TSStepProperties>
					<ts:StepType>NumericLimitTest</ts:StepType>
					<ts:StepGroup>Main</ts:StepGroup>
					<ts:BlockLevel value='0'/>
					<ts:Index value='74'/>
					<ts:TotalTime value='0.801355'/>
					<ts:ModuleTime value='0.801355'/>
				</ts:TSStepProperties>
			</tr:Extension>
			<tr:Outcome value = "Aborted" qualifier= "Terminated" />
			<tr:TestResult ID = "tr849D0413T2357Z777" name = "Numeric">
				<tr:TestData>
					<c:Datum value = "33.9886444" xsi:type="ts:TS_double" nonStandardUnit="volt" flags = "0x2400"/>
				</tr:TestData>
				<tr:TestLimits>
					<tr:Limits>
						<c:LimitPair operator = "AND">
							<c:Limit comparator = "GE">
								<c:Datum nonStandardUnit = "volt" value = "32.585" xsi:type="ts:TS_double" flags = "0x0000"/>
							</c:Limit>
							<c:Limit comparator = "LE">
								<c:Datum nonStandardUnit = "volt" value = "36.015" xsi:type="ts:TS_double" flags = "0x0000"/>
							</c:Limit>
						</c:LimitPair>
					</tr:Limits>
				</tr:TestLimits>
			</tr:TestResult>
		</tr:Test>
		<tr:SessionAction ID = "1144" name = "Power Off" startDateTime = "2022-04-13T18:41:50.311"  endDateTime = "2022-04-13T18:41:50.470"  testReferenceID="ID#:+HcHQC/MrEW6zKqBfNUvNB">
			<tr:Extension>
				<ts:TSStepProperties>
					<ts:StepType>Action</ts:StepType>
					<ts:StepGroup>Cleanup</ts:StepGroup>
					<ts:BlockLevel value='0'/>
					<ts:Index value='0'/>
					<ts:TotalTime value='0.159014'/>
					<ts:ModuleTime value='0.159014'/>
				</ts:TSStepProperties>
			</tr:Extension>
			<tr:ActionOutcome value = "Done" />
		</tr:SessionAction>
		<tr:SessionAction ID = "1145" name = "DC Power Off" startDateTime = "2022-04-13T18:41:50.470"  endDateTime = "2022-04-13T18:41:50.787"  testReferenceID="ID#:uHxAHNpOc02A2ZVKR0dFLB">
			<tr:Extension>
				<ts:TSStepProperties>
					<ts:StepType>Action</ts:StepType>
					<ts:StepGroup>Cleanup</ts:StepGroup>
					<ts:BlockLevel value='0'/>
					<ts:Index value='1'/>
					<ts:TotalTime value='0.316556'/>
					<ts:ModuleTime value='0.316556'/>
				</ts:TSStepProperties>
			</tr:Extension>
			<tr:ActionOutcome value = "Done" />
		</tr:SessionAction>
		<tr:Test ID = "1146" name = "Wait 10" startDateTime = "2022-04-13T18:41:50.787"  endDateTime = "2022-04-13T18:41:56.937"  testReferenceID="ID#:vYX24mrHDEm0g32FqlewxC">
			<tr:Extension>
				<ts:TSStepProperties>
					<ts:StepType>NI_Wait</ts:StepType>
					<ts:StepGroup>Cleanup</ts:StepGroup>
					<ts:BlockLevel value='0'/>
					<ts:Index value='2'/>
					<ts:TotalTime value='6.15014'/>
				</ts:TSStepProperties>
			</tr:Extension>
			<tr:Outcome value = "Aborted" qualifier= "Terminated" />
		</tr:Test>
	</tr:ResultSet>
	<tr:TestProgram>
		<c:SerialNumber>
			CFTP1
		</c:SerialNumber>
		<tr:Configuration>
			<c:Collection xsi:type="ts:TS_Collection" flags = "0x0000">
				<c:Item name = "IncludeTSExtensionElements">
					<c:Datum value = "true" xsi:type="ts:TS_boolean" flags = "0x0000"/>
				</c:Item>
				<c:Item name = "IncludeAttributes">
					<c:Datum value = "false" xsi:type="ts:TS_boolean" flags = "0x0000"/>
				</c:Item>
				<c:Item name = "IncludeLimits">
					<c:Datum value = "true" xsi:type="ts:TS_boolean" flags = "0x0000"/>
				</c:Item>
				<c:Item name = "IncludeMeasurements">
					<c:Datum value = "true" xsi:type="ts:TS_boolean" flags = "0x0000"/>
				</c:Item>
				<c:Item name = "IncludeArrayMeasurement">
					<c:Datum value = "2" xsi:type="ts:TS_double" flags = "0x0000"/>
				</c:Item>
				<c:Item name = "ArrayMeasurementFilter">
					<c:Datum value = "3" xsi:type="ts:TS_double" flags = "0x0000"/>
				</c:Item>
				<c:Item name = "ArrayMeasurementMax">
					<c:Datum value = "100" xsi:type="ts:TS_double" flags = "0x0000"/>
				</c:Item>
				<c:Item name = "IncludeTimes">
					<c:Datum value = "true" xsi:type="ts:TS_boolean" flags = "0x0000"/>
				</c:Item>
				<c:Item name = "Format">
					<c:Datum xsi:type="ts:TS_string" flags = "0x0000">
						<c:Value>xml</c:Value>
					</c:Datum>
				</c:Item>
				<c:Item name = "NumericFormat">
					<c:Datum xsi:type="ts:TS_string" flags = "0x0000">
						<c:Value>%$.13g</c:Value>
					</c:Datum>
				</c:Item>
				<c:Item name = "ResultFilterExpression">
					<c:Datum xsi:type="ts:TS_string" flags = "0x0000">
						<c:Value>True</c:Value>
					</c:Datum>
				</c:Item>
				<c:Item name = "GeneratePath">
					<c:Datum value = "true" xsi:type="ts:TS_boolean" flags = "0x0000"/>
				</c:Item>
				<c:Item name = "UseTemporaryFile">
					<c:Datum value = "false" xsi:type="ts:TS_boolean" flags = "0x0000"/>
				</c:Item>
				<c:Item name = "UseSequenceFileNameAsPrefix">
					<c:Datum value = "true" xsi:type="ts:TS_boolean" flags = "0x0000"/>
				</c:Item>
				<c:Item name = "AddTimeAndDateToFileName">
					<c:Datum value = "true" xsi:type="ts:TS_boolean" flags = "0x0000"/>
				</c:Item>
				<c:Item name = "NewFileNameForEachUUT">
					<c:Datum value = "true" xsi:type="ts:TS_boolean" flags = "0x0000"/>
				</c:Item>
				<c:Item name = "ForceFileNameToBeUnique">
					<c:Datum value = "true" xsi:type="ts:TS_boolean" flags = "0x0000"/>
				</c:Item>
				<c:Item name = "AppendToFileIfItExists">
					<c:Datum value = "false" xsi:type="ts:TS_boolean" flags = "0x0000"/>
				</c:Item>
				<c:Item name = "DirectoryType">
					<c:Datum xsi:type="ts:TS_string" flags = "0x0000">
						<c:Value>SpecifyByExpression</c:Value>
					</c:Datum>
				</c:Item>
				<c:Item name = "Directory">
					<c:Datum xsi:type="ts:TS_string" flags = "0x0000">
						<c:Value></c:Value>
					</c:Datum>
				</c:Item>
				<c:Item name = "BaseName">
					<c:Datum xsi:type="ts:TS_string" flags = "0x0000">
						<c:Value>Report</c:Value>
					</c:Datum>
				</c:Item>
				<c:Item name = "UseFormatForExtension">
					<c:Datum value = "true" xsi:type="ts:TS_boolean" flags = "0x0000"/>
				</c:Item>
				<c:Item name = "Extension">
					<c:Datum xsi:type="ts:TS_string" flags = "0x0000">
						<c:Value></c:Value>
					</c:Datum>
				</c:Item>
				<c:Item name = "ReportFilePath">
					<c:Datum xsi:type="ts:TS_string" flags = "0x0000">
						<c:Value></c:Value>
					</c:Datum>
				</c:Item>
				<c:Item name = "DisableReportGeneration">
					<c:Datum value = "false" xsi:type="ts:TS_boolean" flags = "0x0000"/>
				</c:Item>
				<c:Item name = "IncludeStepResults">
					<c:Datum value = "true" xsi:type="ts:TS_boolean" flags = "0x0000"/>
				</c:Item>
				<c:Item name = "BodyGenerator">
					<c:Datum xsi:type="ts:TS_string" flags = "0x0000">
						<c:Value>DLL</c:Value>
					</c:Datum>
				</c:Item>
				<c:Item name = "Colors">
					<c:Collection xsi:type="ts:TS_Collection" flags = "0x0000">
						<c:Item name = "LabelBg">
							<c:Datum xsi:type="ts:TS_string" flags = "0x0000">
								<c:Value>#FFFFFF</c:Value>
							</c:Datum>
						</c:Item>
						<c:Item name = "ValueBg">
							<c:Datum xsi:type="ts:TS_string" flags = "0x0000">
								<c:Value>#32FFFF</c:Value>
							</c:Datum>
						</c:Item>
						<c:Item name = "UUTSeparator">
							<c:Datum xsi:type="ts:TS_string" flags = "0x0000">
								<c:Value>#0000E0</c:Value>
							</c:Datum>
						</c:Item>
						<c:Item name = "HeaderSeparator">
							<c:Datum xsi:type="ts:TS_string" flags = "0x0000">
								<c:Value>#8000CC</c:Value>
							</c:Datum>
						</c:Item>
						<c:Item name = "TableBorder">
							<c:Datum xsi:type="ts:TS_string" flags = "0x0000">
								<c:Value>#000000</c:Value>
							</c:Datum>
						</c:Item>
						<c:Item name = "MainBg">
							<c:Datum xsi:type="ts:TS_string" flags = "0x0000">
								<c:Value>#00C4C4</c:Value>
							</c:Datum>
						</c:Item>
						<c:Item name = "SetupBg">
							<c:Datum xsi:type="ts:TS_string" flags = "0x0000">
								<c:Value>#FF8000</c:Value>
							</c:Datum>
						</c:Item>
						<c:Item name = "CleanupBg">
							<c:Datum xsi:type="ts:TS_string" flags = "0x0000">
								<c:Value>#ADD8E6</c:Value>
							</c:Datum>
						</c:Item>
						<c:Item name = "ReportTextBg">
							<c:Datum xsi:type="ts:TS_string" flags = "0x0000">
								<c:Value>#FF32CC</c:Value>
							</c:Datum>
						</c:Item>
						<c:Item name = "Terminated">
							<c:Datum xsi:type="ts:TS_string" flags = "0x0000">
								<c:Value>#000080</c:Value>
							</c:Datum>
						</c:Item>
						<c:Item name = "Failed">
							<c:Datum xsi:type="ts:TS_string" flags = "0x0000">
								<c:Value>#FF0000</c:Value>
							</c:Datum>
						</c:Item>
						<c:Item name = "Error">
							<c:Datum xsi:type="ts:TS_string" flags = "0x0000">
								<c:Value>#FF0000</c:Value>
							</c:Datum>
						</c:Item>
						<c:Item name = "Passed">
							<c:Datum xsi:type="ts:TS_string" flags = "0x0000">
								<c:Value>#008000</c:Value>
							</c:Datum>
						</c:Item>
						<c:Item name = "Skipped">
							<c:Datum xsi:type="ts:TS_string" flags = "0x0000">
								<c:Value>#B98028</c:Value>
							</c:Datum>
						</c:Item>
						<c:Item name = "Done">
							<c:Datum xsi:type="ts:TS_string" flags = "0x0000">
								<c:Value>#008000</c:Value>
							</c:Datum>
						</c:Item>
						<c:Item name = "Running">
							<c:Datum xsi:type="ts:TS_string" flags = "0x0000">
								<c:Value>#FFCC33</c:Value>
							</c:Datum>
						</c:Item>
						<c:Item name = "TerminatedBg">
							<c:Datum xsi:type="ts:TS_string" flags = "0x0000">
								<c:Value>#0000FF</c:Value>
							</c:Datum>
						</c:Item>
						<c:Item name = "FailedBg">
							<c:Datum xsi:type="ts:TS_string" flags = "0x0000">
								<c:Value>#FF0000</c:Value>
							</c:Datum>
						</c:Item>
						<c:Item name = "ErrorBg">
							<c:Datum xsi:type="ts:TS_string" flags = "0x0000">
								<c:Value>#FF0000</c:Value>
							</c:Datum>
						</c:Item>
						<c:Item name = "PassedBg">
							<c:Datum xsi:type="ts:TS_string" flags = "0x0000">
								<c:Value>#00FF00</c:Value>
							</c:Datum>
						</c:Item>
						<c:Item name = "SkippedBg">
							<c:Datum xsi:type="ts:TS_string" flags = "0x0000">
								<c:Value>#FFFF00</c:Value>
							</c:Datum>
						</c:Item>
						<c:Item name = "DoneBg">
							<c:Datum xsi:type="ts:TS_string" flags = "0x0000">
								<c:Value>#00FFCC</c:Value>
							</c:Datum>
						</c:Item>
						<c:Item name = "RunningBg">
							<c:Datum xsi:type="ts:TS_string" flags = "0x0000">
								<c:Value>#FFCC33</c:Value>
							</c:Datum>
						</c:Item>
						<c:Item name = "FailureStackLabelBg">
							<c:Datum xsi:type="ts:TS_string" flags = "0x0000">
								<c:Value>#FF2020</c:Value>
							</c:Datum>
						</c:Item>
						<c:Item name = "FailureStackValueBg">
							<c:Datum xsi:type="ts:TS_string" flags = "0x0000">
								<c:Value>#D0D0D0</c:Value>
							</c:Datum>
						</c:Item>
						<c:Item name = "BatchHeadingBg">
							<c:Datum xsi:type="ts:TS_string" flags = "0x0000">
								<c:Value>#00C4C4</c:Value>
							</c:Datum>
						</c:Item>
					</c:Collection>
				</c:Item>
				<c:Item name = "DateAndTimeFormat">
					<c:Datum xsi:type="ts:TS_string" flags = "0x0000">
						<c:Value>TimeFirst</c:Value>
					</c:Datum>
				</c:Item>
				<c:Item name = "NewFileNameForEachBatch">
					<c:Datum value = "false" xsi:type="ts:TS_boolean" flags = "0x0000"/>
				</c:Item>
				<c:Item name = "NewBatchFileNameForEachBatch">
					<c:Datum value = "false" xsi:type="ts:TS_boolean" flags = "0x0000"/>
				</c:Item>
				<c:Item name = "NewFileNameForEachTestSocket">
					<c:Datum value = "false" xsi:type="ts:TS_boolean" flags = "0x0000"/>
				</c:Item>
				<c:Item name = "StoreUUTReportWithBatchReport">
					<c:Datum value = "true" xsi:type="ts:TS_boolean" flags = "0x0000"/>
				</c:Item>
				<c:Item name = "BatchBaseName">
					<c:Datum xsi:type="ts:TS_string" flags = "0x0000">
						<c:Value>BatchReport</c:Value>
					</c:Datum>
				</c:Item>
				<c:Item name = "LabelSize">
					<c:Datum value = "26" xsi:type="ts:TS_double" flags = "0x0000"/>
				</c:Item>
				<c:Item name = "RelStylesheetPath">
					<c:Datum xsi:type="ts:TS_string" flags = "0x0000">
						<c:Value>tr5_horizontal.xsl</c:Value>
					</c:Datum>
				</c:Item>
				<c:Item name = "StylesheetPath">
					<c:Datum xsi:type="ts:TS_string" flags = "0x0000">
						<c:Value>C:\Program Files\National Instruments\TestStand 2012\Components\Models\TestStandModels\ATML\StyleSheets\tr5_horizontal.xsl</c:Value>
					</c:Datum>
				</c:Item>
				<c:Item name = "StylesheetMRU">
					<c:IndexedArray dimensions="[5]" lowerBounds="[0]" upperBounds="[4]" xsi:type="ts:TS_stringArray" flags = "0x0000">
						<ts:Element position ="[0]">
							<c:Value>horizontal.xsl</c:Value>
						</ts:Element>
						<ts:Element position ="[1]">
							<c:Value>report.xsl</c:Value>
						</ts:Element>
						<ts:Element position ="[2]">
							<c:Value>expand.xsl</c:Value>
						</ts:Element>
						<ts:Element position ="[3]">
							<c:Value></c:Value>
						</ts:Element>
						<ts:Element position ="[4]">
							<c:Value></c:Value>
						</ts:Element>
					</c:IndexedArray>
				</c:Item>
				<c:Item name = "ATMLStylesheetMRU">
					<c:IndexedArray dimensions="[3]" lowerBounds="[0]" upperBounds="[2]" xsi:type="ts:TS_stringArray" flags = "0x0000">
						<ts:Element position ="[0]">
							<c:Value>TR_horizontal.xsl</c:Value>
						</ts:Element>
						<ts:Element position ="[1]">
							<c:Value>trml.xsl</c:Value>
						</ts:Element>
						<ts:Element position ="[2]">
							<c:Value></c:Value>
						</ts:Element>
					</c:IndexedArray>
				</c:Item>
				<c:Item name = "StoreStylesheetAbsolutePath">
					<c:Datum value = "true" xsi:type="ts:TS_boolean" flags = "0x0000"/>
				</c:Item>
				<c:Item name = "ProcessOnTheFly">
					<c:Datum value = "false" xsi:type="ts:TS_boolean" flags = "0x0000"/>
				</c:Item>
				<c:Item name = "PurgeOnTheFlyResults">
					<c:Datum value = "false" xsi:type="ts:TS_boolean" flags = "0x0000"/>
				</c:Item>
				<c:Item name = "IncludeStepResultComments">
					<c:Datum value = "true" xsi:type="ts:TS_boolean" flags = "0x0000"/>
				</c:Item>
				<c:Item name = "UseLocalizedDecimalPoint">
					<c:Datum value = "false" xsi:type="ts:TS_boolean" flags = "0x0000"/>
				</c:Item>
				<c:Item name = "ReportStyle">
					<c:Datum xsi:type="ts:TS_string" flags = "0x0000">
						<c:Value>ATML5</c:Value>
					</c:Datum>
				</c:Item>
				<c:Item name = "ReportFileSequentialModelExpression">
					<c:Datum xsi:type="ts:TS_string" flags = "0x0000">
						<c:Value><![CDATA["<ClientFileDir>\\TestReport_<ClientFileName>\\<ClientFileName>_Report[<UUT>][<FileTime>][<FileDate>][<UUTStatus>]<Unique>.<FileExtension>"]]></c:Value>
					</c:Datum>
				</c:Item>
				<c:Item name = "ReportFileParallelModelExpression">
					<c:Datum xsi:type="ts:TS_string" flags = "0x0000">
						<c:Value><![CDATA["<ClientFileDir>\\<ClientFileName>_Report[<FileTime>][<FileDate>]<Unique>.<FileExtension>"]]></c:Value>
					</c:Datum>
				</c:Item>
				<c:Item name = "ReportFileBatchModelExpression">
					<c:Datum xsi:type="ts:TS_string" flags = "0x0000">
						<c:Value><![CDATA["<ClientFileDir>\\<ClientFileName>_BatchReport[<FileTime>][<FileDate>]<Unique>.<FileExtension>"]]></c:Value>
					</c:Datum>
				</c:Item>
				<c:Item name = "BatchFileBatchModelExpression">
					<c:Datum xsi:type="ts:TS_string" flags = "0x0000">
						<c:Value><![CDATA["<ClientFileDir>\\<ClientFileName>_BatchReport[<FileTime>][<FileDate>]<Unique>.<FileExtension>"]]></c:Value>
					</c:Datum>
				</c:Item>
				<c:Item name = "NewFileNameForEachUUTStatus">
					<c:Datum value = "true" xsi:type="ts:TS_boolean" flags = "0x0000"/>
				</c:Item>
				<c:Item name = "ReportPathMacroListString">
					<c:Datum xsi:type="ts:TS_string" flags = "0x0000">
						<c:Value><![CDATA[<CLIENTFILEDIR><CLIENTFILENAME><CLIENTFILENAME><UUT><FILETIME><FILEDATE><UUTSTATUS><UNIQUE><FILEEXTENSION>]]></c:Value>
					</c:Datum>
				</c:Item>
				<c:Item name = "BatchReportPathMacroListString">
					<c:Datum xsi:type="ts:TS_string" flags = "0x0000">
						<c:Value></c:Value>
					</c:Datum>
				</c:Item>
				<c:Item name = "CheckIfMacroListIsUnchanged">
					<c:Datum value = "true" xsi:type="ts:TS_boolean" flags = "0x0000"/>
				</c:Item>
				<c:Item name = "ATML5StylesheetMRU">
					<c:IndexedArray dimensions="[3]" lowerBounds="[0]" upperBounds="[2]" xsi:type="ts:TS_stringArray" flags = "0x0000">
						<ts:Element position ="[0]">
							<c:Value>tr5_horizontal.xsl</c:Value>
						</ts:Element>
						<ts:Element position ="[1]">
							<c:Value>tr5_report.xsl</c:Value>
						</ts:Element>
						<ts:Element position ="[2]">
							<c:Value>tr5_expand.xsl</c:Value>
						</ts:Element>
					</c:IndexedArray>
				</c:Item>
				<c:Item name = "Atml_Rpt_Options">
					<c:Collection xsi:type="ts:TS_Collection" flags = "0x0000">
						<c:Item name = "AddReportText">
							<c:Datum value = "true" xsi:type="ts:TS_boolean" flags = "0x0000"/>
						</c:Item>
						<c:Item name = "ExtensionDLLAbsolutePath">
							<c:Datum xsi:type="ts:TS_string" flags = "0x0000">
								<c:Value></c:Value>
							</c:Datum>
						</c:Item>
						<c:Item name = "TestResultsSchemaPath">
							<c:Datum xsi:type="ts:TS_string" flags = "0x0000">
								<c:Value></c:Value>
							</c:Datum>
						</c:Item>
					</c:Collection>
				</c:Item>
			</c:Collection>
		</tr:Configuration>
	</tr:TestProgram>
	<tr:TestStation>
		<c:SerialNumber>CFTP1</c:SerialNumber>
	</tr:TestStation>
	<tr:UUT>
		<c:SerialNumber>10041194D-RD22120401</c:SerialNumber>
	</tr:UUT>
	<tr:Extension>
		<ts:TSResultSetProperties>
			<ts:NumOfResults value = '77'/>
		</ts:TSResultSetProperties>
	</tr:Extension>
</trc:TestResults>
</trc:TestResultsCollection>
