<?xml version="1.0" encoding="gb2312" ?><?xml-stylesheet type="text/xsl" href="C:\Program Files\National Instruments\TestStand 2012\Components\Models\TestStandModels\ATML\StyleSheets\tr5_horizontal.xsl"?>

<trc:TestResultsCollection xmlns:trc="urn:IEEE-1636.1:2011:01:TestResultsCollection" xmlns:tr="urn:IEEE-1636.1:2011:01:TestResults" xmlns:c="urn:IEEE-1671:2010:Common" xmlns:xsi="http://www.w3.org/2001/XMLSchema-instance" xmlns:ts="www.ni.com/TestStand/ATMLTestResults/2.0">
<trc:TestResults uuid="586cf1e9-20d6-476b-8226-18998c65d331" xmlns:trc="urn:IEEE-1636.1:2011:01:TestResultsCollection" xmlns:tr="urn:IEEE-1636.1:2011:01:TestResults" xmlns:c="urn:IEEE-1671:2010:Common" xmlns:xsi="http://www.w3.org/2001/XMLSchema-instance" xmlns:ts="www.ni.com/TestStand/ATMLTestResults/2.0">
	<tr:Personnel>
		<tr:SystemOperator ID = "administrator" name = "administrator"/>
	</tr:Personnel>
	<tr:ResultSet ID="109" name = "C:\Bio Rad TestStand_10041194\Main\Bio Rad Teststand.seq#MainSequence" startDateTime = "2020-09-03T16:03:31.172" endDateTime = "2020-09-03T16:04:09.140">
		<tr:Extension>
			<ts:TSStepProperties>
				<ts:StepType>SequenceCall</ts:StepType>
				<ts:StepGroup>Main</ts:StepGroup>
				<ts:BlockLevel value='1'/>
				<ts:Index value='9'/>
				<ts:TotalTime value='37.9684'/>
				<ts:ModuleTime value='37.9684'/>
			</ts:TSStepProperties>
		</tr:Extension>
		<tr:Outcome value="Aborted" qualifier="Terminated" />
		<tr:SessionAction ID = "110" name = "Load Bio Rad DLL" startDateTime = "2020-09-03T16:03:31.224"  endDateTime = "2020-09-03T16:03:31.225"  testReferenceID="ID#:vjT50USnYkW0sYJ60awv0D">
			<tr:Extension>
				<ts:TSStepProperties>
					<ts:StepType>Action</ts:StepType>
					<ts:StepGroup>Setup</ts:StepGroup>
					<ts:BlockLevel value='0'/>
					<ts:Index value='0'/>
					<ts:TotalTime value='0.0011999'/>
					<ts:ModuleTime value='0.0011999'/>
				</ts:TSStepProperties>
			</tr:Extension>
			<tr:ActionOutcome value = "Done" />
		</tr:SessionAction>
		<tr:Test ID = "111" name = "Put UUT" startDateTime = "2020-09-03T16:03:31.261"  endDateTime = "2020-09-03T16:03:35.706"  testReferenceID="ID#:pCsUDaEDBUWb+mCAymOY1A">
			<tr:Extension>
				<ts:TSStepProperties>
					<ts:StepType>PassFailTest</ts:StepType>
					<ts:StepGroup>Main</ts:StepGroup>
					<ts:BlockLevel value='0'/>
					<ts:Index value='0'/>
					<ts:TotalTime value='4.44516'/>
					<ts:ModuleTime value='4.44516'/>
				</ts:TSStepProperties>
			</tr:Extension>
			<tr:Outcome value = "Passed" />
		</tr:Test>
		<tr:SessionAction ID = "112" name = "DC Power On" startDateTime = "2020-09-03T16:03:35.708"  endDateTime = "2020-09-03T16:03:36.029"  testReferenceID="ID#:f7l0w4KeGUuAgAdvy4llyA">
			<tr:Extension>
				<ts:TSStepProperties>
					<ts:StepType>Action</ts:StepType>
					<ts:StepGroup>Main</ts:StepGroup>
					<ts:BlockLevel value='0'/>
					<ts:Index value='1'/>
					<ts:TotalTime value='0.321133'/>
					<ts:ModuleTime value='0.321133'/>
				</ts:TSStepProperties>
			</tr:Extension>
			<tr:ActionOutcome value = "Done" />
		</tr:SessionAction>
		<tr:SessionAction ID = "113" name = "AC Power On" startDateTime = "2020-09-03T16:03:36.031"  endDateTime = "2020-09-03T16:03:37.852"  testReferenceID="ID#:GzbbZRerW0KsOfSjLH45uD">
			<tr:Extension>
				<ts:TSStepProperties>
					<ts:StepType>Action</ts:StepType>
					<ts:StepGroup>Main</ts:StepGroup>
					<ts:BlockLevel value='0'/>
					<ts:Index value='2'/>
					<ts:TotalTime value='1.82091'/>
					<ts:ModuleTime value='1.82091'/>
				</ts:TSStepProperties>
			</tr:Extension>
			<tr:ActionOutcome value = "Done" />
		</tr:SessionAction>
		<tr:Test ID = "114" name = "Find Attached Devices" startDateTime = "2020-09-03T16:03:37.855"  endDateTime = "2020-09-03T16:03:52.863"  testReferenceID="ID#:3/5kcZbtdEezckeONT1yKB">
			<tr:Extension>
				<ts:TSStepProperties>
					<ts:StepType>StringValueTest</ts:StepType>
					<ts:StepGroup>Main</ts:StepGroup>
					<ts:BlockLevel value='0'/>
					<ts:Index value='4'/>
					<ts:TotalTime value='15.0074'/>
					<ts:ModuleTime value='15.0074'/>
				</ts:TSStepProperties>
			</tr:Extension>
			<tr:Outcome value = "Passed" />
			<tr:TestResult ID = "tr80D0903T0239Z900" name = "String">
				<tr:TestData>
					<c:Datum xsi:type="ts:TS_string" flags = "0x2400">
						<c:Value>Success</c:Value>
					</c:Datum>
				</tr:TestData>
				<tr:TestLimits>
					<tr:Limits>
						<c:Expected comparator = "EQ">
							<c:Datum xsi:type="ts:TS_string" flags = "0x0000">
								<c:Value>Success</c:Value>
							</c:Datum>
						</c:Expected>
					</tr:Limits>
				</tr:TestLimits>
			</tr:TestResult>
		</tr:Test>
		<tr:Test ID = "115" name = "12.8V No Load Test" startDateTime = "2020-09-03T16:03:52.867"  endDateTime = "2020-09-03T16:03:54.099"  testReferenceID="ID#:s2EHM1jn9kGPV9WF3jYYlD">
			<tr:Extension>
				<ts:TSStepProperties>
					<ts:StepType>NumericLimitTest</ts:StepType>
					<ts:StepGroup>Main</ts:StepGroup>
					<ts:BlockLevel value='0'/>
					<ts:Index value='6'/>
					<ts:TotalTime value='1.23265'/>
					<ts:ModuleTime value='1.23265'/>
				</ts:TSStepProperties>
			</tr:Extension>
			<tr:Outcome value = "Passed" />
			<tr:TestResult ID = "tr81D0903T0239Z900" name = "Numeric">
				<tr:TestData>
					<c:Datum value = "12.8458802" xsi:type="ts:TS_double" nonStandardUnit="volt" flags = "0x2400"/>
				</tr:TestData>
				<tr:TestLimits>
					<tr:Limits>
						<c:LimitPair operator = "AND">
							<c:Limit comparator = "GE">
								<c:Datum nonStandardUnit = "volt" value = "12.16" xsi:type="ts:TS_double" flags = "0x0000"/>
							</c:Limit>
							<c:Limit comparator = "LE">
								<c:Datum nonStandardUnit = "volt" value = "13.44" xsi:type="ts:TS_double" flags = "0x0000"/>
							</c:Limit>
						</c:LimitPair>
					</tr:Limits>
				</tr:TestLimits>
			</tr:TestResult>
		</tr:Test>
		<tr:Test ID = "116" name = "12.8V Load 30W" startDateTime = "2020-09-03T16:03:54.101"  endDateTime = "2020-09-03T16:03:55.288"  testReferenceID="ID#:/PEXBGfFnUy0sBWfu6GovA">
			<tr:Extension>
				<ts:TSStepProperties>
					<ts:StepType>NumericLimitTest</ts:StepType>
					<ts:StepGroup>Main</ts:StepGroup>
					<ts:BlockLevel value='0'/>
					<ts:Index value='7'/>
					<ts:TotalTime value='1.18701'/>
					<ts:ModuleTime value='1.18701'/>
				</ts:TSStepProperties>
			</tr:Extension>
			<tr:Outcome value = "Passed" />
			<tr:TestResult ID = "tr82D0903T0239Z900" name = "Numeric">
				<tr:TestData>
					<c:Datum value = "12.5725338" xsi:type="ts:TS_double" nonStandardUnit="volt" flags = "0x2400"/>
				</tr:TestData>
				<tr:TestLimits>
					<tr:Limits>
						<c:LimitPair operator = "AND">
							<c:Limit comparator = "GE">
								<c:Datum nonStandardUnit = "volt" value = "12.16" xsi:type="ts:TS_double" flags = "0x0000"/>
							</c:Limit>
							<c:Limit comparator = "LE">
								<c:Datum nonStandardUnit = "volt" value = "13.44" xsi:type="ts:TS_double" flags = "0x0000"/>
							</c:Limit>
						</c:LimitPair>
					</tr:Limits>
				</tr:TestLimits>
			</tr:TestResult>
		</tr:Test>
		<tr:Test ID = "117" name = "5V No Load Test" startDateTime = "2020-09-03T16:03:55.292"  endDateTime = "2020-09-03T16:03:56.009"  testReferenceID="ID#:uT9QBRM1n0S0ZJX7F9++eA">
			<tr:Extension>
				<ts:TSStepProperties>
					<ts:StepType>NumericLimitTest</ts:StepType>
					<ts:StepGroup>Main</ts:StepGroup>
					<ts:BlockLevel value='0'/>
					<ts:Index value='9'/>
					<ts:TotalTime value='0.717571'/>
					<ts:ModuleTime value='0.717571'/>
				</ts:TSStepProperties>
			</tr:Extension>
			<tr:Outcome value = "Passed" />
			<tr:TestResult ID = "tr83D0903T0239Z900" name = "Numeric">
				<tr:TestData>
					<c:Datum value = "5.05303384" xsi:type="ts:TS_double" nonStandardUnit="volt" flags = "0x2400"/>
				</tr:TestData>
				<tr:TestLimits>
					<tr:Limits>
						<c:LimitPair operator = "AND">
							<c:Limit comparator = "GE">
								<c:Datum nonStandardUnit = "volt" value = "4.75" xsi:type="ts:TS_double" flags = "0x0000"/>
							</c:Limit>
							<c:Limit comparator = "LE">
								<c:Datum nonStandardUnit = "volt" value = "5.25" xsi:type="ts:TS_double" flags = "0x0000"/>
							</c:Limit>
						</c:LimitPair>
					</tr:Limits>
				</tr:TestLimits>
			</tr:TestResult>
		</tr:Test>
		<tr:Test ID = "118" name = "5V 600mA Load" startDateTime = "2020-09-03T16:03:56.011"  endDateTime = "2020-09-03T16:03:57.288"  testReferenceID="ID#:hK5y13WF/UOw/cQ9FI1UED">
			<tr:Extension>
				<ts:TSStepProperties>
					<ts:StepType>NumericLimitTest</ts:StepType>
					<ts:StepGroup>Main</ts:StepGroup>
					<ts:BlockLevel value='0'/>
					<ts:Index value='10'/>
					<ts:TotalTime value='1.27698'/>
					<ts:ModuleTime value='1.27698'/>
				</ts:TSStepProperties>
			</tr:Extension>
			<tr:Outcome value = "Passed" />
			<tr:TestResult ID = "tr84D0903T0239Z900" name = "Numeric">
				<tr:TestData>
					<c:Datum value = "4.99163419" xsi:type="ts:TS_double" nonStandardUnit="volt" flags = "0x2400"/>
				</tr:TestData>
				<tr:TestLimits>
					<tr:Limits>
						<c:LimitPair operator = "AND">
							<c:Limit comparator = "GE">
								<c:Datum nonStandardUnit = "volt" value = "4.75" xsi:type="ts:TS_double" flags = "0x0000"/>
							</c:Limit>
							<c:Limit comparator = "LE">
								<c:Datum nonStandardUnit = "volt" value = "5.25" xsi:type="ts:TS_double" flags = "0x0000"/>
							</c:Limit>
						</c:LimitPair>
					</tr:Limits>
				</tr:TestLimits>
			</tr:TestResult>
		</tr:Test>
		<tr:Test ID = "119" name = "3.3V Voltage Check" startDateTime = "2020-09-03T16:03:57.292"  endDateTime = "2020-09-03T16:03:58.010"  testReferenceID="ID#:dBBvwB2wHES0ifCY7PD/0B">
			<tr:Extension>
				<ts:TSStepProperties>
					<ts:StepType>NumericLimitTest</ts:StepType>
					<ts:StepGroup>Main</ts:StepGroup>
					<ts:BlockLevel value='0'/>
					<ts:Index value='12'/>
					<ts:TotalTime value='0.718452'/>
					<ts:ModuleTime value='0.718452'/>
				</ts:TSStepProperties>
			</tr:Extension>
			<tr:Outcome value = "Passed" />
			<tr:TestResult ID = "tr85D0903T0239Z900" name = "Numeric">
				<tr:TestData>
					<c:Datum value = "3.31084038" xsi:type="ts:TS_double" nonStandardUnit="volt" flags = "0x2400"/>
				</tr:TestData>
				<tr:TestLimits>
					<tr:Limits>
						<c:LimitPair operator = "AND">
							<c:Limit comparator = "GE">
								<c:Datum nonStandardUnit = "volt" value = "2.85" xsi:type="ts:TS_double" flags = "0x0000"/>
							</c:Limit>
							<c:Limit comparator = "LE">
								<c:Datum nonStandardUnit = "volt" value = "3.45" xsi:type="ts:TS_double" flags = "0x0000"/>
							</c:Limit>
						</c:LimitPair>
					</tr:Limits>
				</tr:TestLimits>
			</tr:TestResult>
		</tr:Test>
		<tr:Test ID = "120" name = "Battery Voltage Check" startDateTime = "2020-09-03T16:03:58.014"  endDateTime = "2020-09-03T16:03:58.738"  testReferenceID="ID#:9ZyDVNqHmE+lSY/ulKlYSC">
			<tr:Extension>
				<ts:TSStepProperties>
					<ts:StepType>NumericLimitTest</ts:StepType>
					<ts:StepGroup>Main</ts:StepGroup>
					<ts:BlockLevel value='0'/>
					<ts:Index value='14'/>
					<ts:TotalTime value='0.723711'/>
					<ts:ModuleTime value='0.723711'/>
				</ts:TSStepProperties>
			</tr:Extension>
			<tr:Outcome value = "Passed" />
			<tr:TestResult ID = "tr86D0903T0239Z900" name = "Numeric">
				<tr:TestData>
					<c:Datum value = "3.1547756" xsi:type="ts:TS_double" nonStandardUnit="volt" flags = "0x2400"/>
				</tr:TestData>
				<tr:TestLimits>
					<tr:Limits>
						<c:LimitPair operator = "AND">
							<c:Limit comparator = "GE">
								<c:Datum nonStandardUnit = "volt" value = "2.85" xsi:type="ts:TS_double" flags = "0x0000"/>
							</c:Limit>
							<c:Limit comparator = "LE">
								<c:Datum nonStandardUnit = "volt" value = "3.45" xsi:type="ts:TS_double" flags = "0x0000"/>
							</c:Limit>
						</c:LimitPair>
					</tr:Limits>
				</tr:TestLimits>
			</tr:TestResult>
		</tr:Test>
		<tr:Test ID = "121" name = "Wait 10" startDateTime = "2020-09-03T16:03:58.739"  endDateTime = "2020-09-03T16:04:06.559"  testReferenceID="ID#:731Py5h0n0O4z4TxEZWZlC">
			<tr:Extension>
				<ts:TSStepProperties>
					<ts:StepType>NI_Wait</ts:StepType>
					<ts:StepGroup>Main</ts:StepGroup>
					<ts:BlockLevel value='0'/>
					<ts:Index value='15'/>
					<ts:TotalTime value='7.82'/>
				</ts:TSStepProperties>
			</tr:Extension>
			<tr:Outcome value = "Aborted" qualifier= "Terminated" />
		</tr:Test>
		<tr:SessionAction ID = "122" name = "Power Off" startDateTime = "2020-09-03T16:04:06.559"  endDateTime = "2020-09-03T16:04:08.357"  testReferenceID="ID#:+HcHQC/MrEW6zKqBfNUvNB">
			<tr:Extension>
				<ts:TSStepProperties>
					<ts:StepType>Action</ts:StepType>
					<ts:StepGroup>Cleanup</ts:StepGroup>
					<ts:BlockLevel value='0'/>
					<ts:Index value='0'/>
					<ts:TotalTime value='1.79808'/>
					<ts:ModuleTime value='1.79808'/>
				</ts:TSStepProperties>
			</tr:Extension>
			<tr:ActionOutcome value = "Done" />
		</tr:SessionAction>
		<tr:SessionAction ID = "123" name = "DC Power Off" startDateTime = "2020-09-03T16:04:08.357"  endDateTime = "2020-09-03T16:04:08.679"  testReferenceID="ID#:uHxAHNpOc02A2ZVKR0dFLB">
			<tr:Extension>
				<ts:TSStepProperties>
					<ts:StepType>Action</ts:StepType>
					<ts:StepGroup>Cleanup</ts:StepGroup>
					<ts:BlockLevel value='0'/>
					<ts:Index value='1'/>
					<ts:TotalTime value='0.321467'/>
					<ts:ModuleTime value='0.321467'/>
				</ts:TSStepProperties>
			</tr:Extension>
			<tr:ActionOutcome value = "Done" />
		</tr:SessionAction>
		<tr:Test ID = "124" name = "Wait 10" startDateTime = "2020-09-03T16:04:08.679"  endDateTime = "2020-09-03T16:04:09.130"  testReferenceID="ID#:vYX24mrHDEm0g32FqlewxC">
			<tr:Extension>
				<ts:TSStepProperties>
					<ts:StepType>NI_Wait</ts:StepType>
					<ts:StepGroup>Cleanup</ts:StepGroup>
					<ts:BlockLevel value='0'/>
					<ts:Index value='2'/>
					<ts:TotalTime value='0.451433'/>
				</ts:TSStepProperties>
			</tr:Extension>
			<tr:Outcome value = "Aborted" qualifier= "Terminated" />
		</tr:Test>
	</tr:ResultSet>
	<tr:TestProgram>
		<c:SerialNumber>
			CFTP7
		</c:SerialNumber>
		<tr:Configuration>
			<c:Collection xsi:type="ts:TS_Collection" flags = "0x0000">
				<c:Item name = "IncludeTSExtensionElements">
					<c:Datum value = "true" xsi:type="ts:TS_boolean" flags = "0x0000"/>
				</c:Item>
				<c:Item name = "IncludeAttributes">
					<c:Datum value = "false" xsi:type="ts:TS_boolean" flags = "0x0000"/>
				</c:Item>
				<c:Item name = "IncludeLimits">
					<c:Datum value = "true" xsi:type="ts:TS_boolean" flags = "0x0000"/>
				</c:Item>
				<c:Item name = "IncludeMeasurements">
					<c:Datum value = "true" xsi:type="ts:TS_boolean" flags = "0x0000"/>
				</c:Item>
				<c:Item name = "IncludeArrayMeasurement">
					<c:Datum value = "2" xsi:type="ts:TS_double" flags = "0x0000"/>
				</c:Item>
				<c:Item name = "ArrayMeasurementFilter">
					<c:Datum value = "3" xsi:type="ts:TS_double" flags = "0x0000"/>
				</c:Item>
				<c:Item name = "ArrayMeasurementMax">
					<c:Datum value = "100" xsi:type="ts:TS_double" flags = "0x0000"/>
				</c:Item>
				<c:Item name = "IncludeTimes">
					<c:Datum value = "true" xsi:type="ts:TS_boolean" flags = "0x0000"/>
				</c:Item>
				<c:Item name = "Format">
					<c:Datum xsi:type="ts:TS_string" flags = "0x0000">
						<c:Value>xml</c:Value>
					</c:Datum>
				</c:Item>
				<c:Item name = "NumericFormat">
					<c:Datum xsi:type="ts:TS_string" flags = "0x0000">
						<c:Value>%$.13g</c:Value>
					</c:Datum>
				</c:Item>
				<c:Item name = "ResultFilterExpression">
					<c:Datum xsi:type="ts:TS_string" flags = "0x0000">
						<c:Value>True</c:Value>
					</c:Datum>
				</c:Item>
				<c:Item name = "GeneratePath">
					<c:Datum value = "true" xsi:type="ts:TS_boolean" flags = "0x0000"/>
				</c:Item>
				<c:Item name = "UseTemporaryFile">
					<c:Datum value = "false" xsi:type="ts:TS_boolean" flags = "0x0000"/>
				</c:Item>
				<c:Item name = "UseSequenceFileNameAsPrefix">
					<c:Datum value = "true" xsi:type="ts:TS_boolean" flags = "0x0000"/>
				</c:Item>
				<c:Item name = "AddTimeAndDateToFileName">
					<c:Datum value = "true" xsi:type="ts:TS_boolean" flags = "0x0000"/>
				</c:Item>
				<c:Item name = "NewFileNameForEachUUT">
					<c:Datum value = "true" xsi:type="ts:TS_boolean" flags = "0x0000"/>
				</c:Item>
				<c:Item name = "ForceFileNameToBeUnique">
					<c:Datum value = "true" xsi:type="ts:TS_boolean" flags = "0x0000"/>
				</c:Item>
				<c:Item name = "AppendToFileIfItExists">
					<c:Datum value = "false" xsi:type="ts:TS_boolean" flags = "0x0000"/>
				</c:Item>
				<c:Item name = "DirectoryType">
					<c:Datum xsi:type="ts:TS_string" flags = "0x0000">
						<c:Value>SpecifyByExpression</c:Value>
					</c:Datum>
				</c:Item>
				<c:Item name = "Directory">
					<c:Datum xsi:type="ts:TS_string" flags = "0x0000">
						<c:Value></c:Value>
					</c:Datum>
				</c:Item>
				<c:Item name = "BaseName">
					<c:Datum xsi:type="ts:TS_string" flags = "0x0000">
						<c:Value>Report</c:Value>
					</c:Datum>
				</c:Item>
				<c:Item name = "UseFormatForExtension">
					<c:Datum value = "true" xsi:type="ts:TS_boolean" flags = "0x0000"/>
				</c:Item>
				<c:Item name = "Extension">
					<c:Datum xsi:type="ts:TS_string" flags = "0x0000">
						<c:Value></c:Value>
					</c:Datum>
				</c:Item>
				<c:Item name = "ReportFilePath">
					<c:Datum xsi:type="ts:TS_string" flags = "0x0000">
						<c:Value></c:Value>
					</c:Datum>
				</c:Item>
				<c:Item name = "DisableReportGeneration">
					<c:Datum value = "false" xsi:type="ts:TS_boolean" flags = "0x0000"/>
				</c:Item>
				<c:Item name = "IncludeStepResults">
					<c:Datum value = "true" xsi:type="ts:TS_boolean" flags = "0x0000"/>
				</c:Item>
				<c:Item name = "BodyGenerator">
					<c:Datum xsi:type="ts:TS_string" flags = "0x0000">
						<c:Value>DLL</c:Value>
					</c:Datum>
				</c:Item>
				<c:Item name = "Colors">
					<c:Collection xsi:type="ts:TS_Collection" flags = "0x0000">
						<c:Item name = "LabelBg">
							<c:Datum xsi:type="ts:TS_string" flags = "0x0000">
								<c:Value>#FFFFFF</c:Value>
							</c:Datum>
						</c:Item>
						<c:Item name = "ValueBg">
							<c:Datum xsi:type="ts:TS_string" flags = "0x0000">
								<c:Value>#32FFFF</c:Value>
							</c:Datum>
						</c:Item>
						<c:Item name = "UUTSeparator">
							<c:Datum xsi:type="ts:TS_string" flags = "0x0000">
								<c:Value>#0000E0</c:Value>
							</c:Datum>
						</c:Item>
						<c:Item name = "HeaderSeparator">
							<c:Datum xsi:type="ts:TS_string" flags = "0x0000">
								<c:Value>#8000CC</c:Value>
							</c:Datum>
						</c:Item>
						<c:Item name = "TableBorder">
							<c:Datum xsi:type="ts:TS_string" flags = "0x0000">
								<c:Value>#000000</c:Value>
							</c:Datum>
						</c:Item>
						<c:Item name = "MainBg">
							<c:Datum xsi:type="ts:TS_string" flags = "0x0000">
								<c:Value>#00C4C4</c:Value>
							</c:Datum>
						</c:Item>
						<c:Item name = "SetupBg">
							<c:Datum xsi:type="ts:TS_string" flags = "0x0000">
								<c:Value>#FF8000</c:Value>
							</c:Datum>
						</c:Item>
						<c:Item name = "CleanupBg">
							<c:Datum xsi:type="ts:TS_string" flags = "0x0000">
								<c:Value>#ADD8E6</c:Value>
							</c:Datum>
						</c:Item>
						<c:Item name = "ReportTextBg">
							<c:Datum xsi:type="ts:TS_string" flags = "0x0000">
								<c:Value>#FF32CC</c:Value>
							</c:Datum>
						</c:Item>
						<c:Item name = "Terminated">
							<c:Datum xsi:type="ts:TS_string" flags = "0x0000">
								<c:Value>#000080</c:Value>
							</c:Datum>
						</c:Item>
						<c:Item name = "Failed">
							<c:Datum xsi:type="ts:TS_string" flags = "0x0000">
								<c:Value>#FF0000</c:Value>
							</c:Datum>
						</c:Item>
						<c:Item name = "Error">
							<c:Datum xsi:type="ts:TS_string" flags = "0x0000">
								<c:Value>#FF0000</c:Value>
							</c:Datum>
						</c:Item>
						<c:Item name = "Passed">
							<c:Datum xsi:type="ts:TS_string" flags = "0x0000">
								<c:Value>#008000</c:Value>
							</c:Datum>
						</c:Item>
						<c:Item name = "Skipped">
							<c:Datum xsi:type="ts:TS_string" flags = "0x0000">
								<c:Value>#B98028</c:Value>
							</c:Datum>
						</c:Item>
						<c:Item name = "Done">
							<c:Datum xsi:type="ts:TS_string" flags = "0x0000">
								<c:Value>#008000</c:Value>
							</c:Datum>
						</c:Item>
						<c:Item name = "Running">
							<c:Datum xsi:type="ts:TS_string" flags = "0x0000">
								<c:Value>#FFCC33</c:Value>
							</c:Datum>
						</c:Item>
						<c:Item name = "TerminatedBg">
							<c:Datum xsi:type="ts:TS_string" flags = "0x0000">
								<c:Value>#0000FF</c:Value>
							</c:Datum>
						</c:Item>
						<c:Item name = "FailedBg">
							<c:Datum xsi:type="ts:TS_string" flags = "0x0000">
								<c:Value>#FF0000</c:Value>
							</c:Datum>
						</c:Item>
						<c:Item name = "ErrorBg">
							<c:Datum xsi:type="ts:TS_string" flags = "0x0000">
								<c:Value>#FF0000</c:Value>
							</c:Datum>
						</c:Item>
						<c:Item name = "PassedBg">
							<c:Datum xsi:type="ts:TS_string" flags = "0x0000">
								<c:Value>#00FF00</c:Value>
							</c:Datum>
						</c:Item>
						<c:Item name = "SkippedBg">
							<c:Datum xsi:type="ts:TS_string" flags = "0x0000">
								<c:Value>#FFFF00</c:Value>
							</c:Datum>
						</c:Item>
						<c:Item name = "DoneBg">
							<c:Datum xsi:type="ts:TS_string" flags = "0x0000">
								<c:Value>#00FFCC</c:Value>
							</c:Datum>
						</c:Item>
						<c:Item name = "RunningBg">
							<c:Datum xsi:type="ts:TS_string" flags = "0x0000">
								<c:Value>#FFCC33</c:Value>
							</c:Datum>
						</c:Item>
						<c:Item name = "FailureStackLabelBg">
							<c:Datum xsi:type="ts:TS_string" flags = "0x0000">
								<c:Value>#FF2020</c:Value>
							</c:Datum>
						</c:Item>
						<c:Item name = "FailureStackValueBg">
							<c:Datum xsi:type="ts:TS_string" flags = "0x0000">
								<c:Value>#D0D0D0</c:Value>
							</c:Datum>
						</c:Item>
						<c:Item name = "BatchHeadingBg">
							<c:Datum xsi:type="ts:TS_string" flags = "0x0000">
								<c:Value>#00C4C4</c:Value>
							</c:Datum>
						</c:Item>
					</c:Collection>
				</c:Item>
				<c:Item name = "DateAndTimeFormat">
					<c:Datum xsi:type="ts:TS_string" flags = "0x0000">
						<c:Value>TimeFirst</c:Value>
					</c:Datum>
				</c:Item>
				<c:Item name = "NewFileNameForEachBatch">
					<c:Datum value = "false" xsi:type="ts:TS_boolean" flags = "0x0000"/>
				</c:Item>
				<c:Item name = "NewBatchFileNameForEachBatch">
					<c:Datum value = "false" xsi:type="ts:TS_boolean" flags = "0x0000"/>
				</c:Item>
				<c:Item name = "NewFileNameForEachTestSocket">
					<c:Datum value = "false" xsi:type="ts:TS_boolean" flags = "0x0000"/>
				</c:Item>
				<c:Item name = "StoreUUTReportWithBatchReport">
					<c:Datum value = "true" xsi:type="ts:TS_boolean" flags = "0x0000"/>
				</c:Item>
				<c:Item name = "BatchBaseName">
					<c:Datum xsi:type="ts:TS_string" flags = "0x0000">
						<c:Value>BatchReport</c:Value>
					</c:Datum>
				</c:Item>
				<c:Item name = "LabelSize">
					<c:Datum value = "26" xsi:type="ts:TS_double" flags = "0x0000"/>
				</c:Item>
				<c:Item name = "RelStylesheetPath">
					<c:Datum xsi:type="ts:TS_string" flags = "0x0000">
						<c:Value>tr5_horizontal.xsl</c:Value>
					</c:Datum>
				</c:Item>
				<c:Item name = "StylesheetPath">
					<c:Datum xsi:type="ts:TS_string" flags = "0x0000">
						<c:Value>C:\Program Files\National Instruments\TestStand 2012\Components\Models\TestStandModels\ATML\StyleSheets\tr5_horizontal.xsl</c:Value>
					</c:Datum>
				</c:Item>
				<c:Item name = "StylesheetMRU">
					<c:IndexedArray dimensions="[5]" lowerBounds="[0]" upperBounds="[4]" xsi:type="ts:TS_stringArray" flags = "0x0000">
						<ts:Element position ="[0]">
							<c:Value>horizontal.xsl</c:Value>
						</ts:Element>
						<ts:Element position ="[1]">
							<c:Value>report.xsl</c:Value>
						</ts:Element>
						<ts:Element position ="[2]">
							<c:Value>expand.xsl</c:Value>
						</ts:Element>
						<ts:Element position ="[3]">
							<c:Value></c:Value>
						</ts:Element>
						<ts:Element position ="[4]">
							<c:Value></c:Value>
						</ts:Element>
					</c:IndexedArray>
				</c:Item>
				<c:Item name = "ATMLStylesheetMRU">
					<c:IndexedArray dimensions="[3]" lowerBounds="[0]" upperBounds="[2]" xsi:type="ts:TS_stringArray" flags = "0x0000">
						<ts:Element position ="[0]">
							<c:Value>TR_horizontal.xsl</c:Value>
						</ts:Element>
						<ts:Element position ="[1]">
							<c:Value>trml.xsl</c:Value>
						</ts:Element>
						<ts:Element position ="[2]">
							<c:Value></c:Value>
						</ts:Element>
					</c:IndexedArray>
				</c:Item>
				<c:Item name = "StoreStylesheetAbsolutePath">
					<c:Datum value = "true" xsi:type="ts:TS_boolean" flags = "0x0000"/>
				</c:Item>
				<c:Item name = "ProcessOnTheFly">
					<c:Datum value = "false" xsi:type="ts:TS_boolean" flags = "0x0000"/>
				</c:Item>
				<c:Item name = "PurgeOnTheFlyResults">
					<c:Datum value = "false" xsi:type="ts:TS_boolean" flags = "0x0000"/>
				</c:Item>
				<c:Item name = "IncludeStepResultComments">
					<c:Datum value = "true" xsi:type="ts:TS_boolean" flags = "0x0000"/>
				</c:Item>
				<c:Item name = "UseLocalizedDecimalPoint">
					<c:Datum value = "false" xsi:type="ts:TS_boolean" flags = "0x0000"/>
				</c:Item>
				<c:Item name = "ReportStyle">
					<c:Datum xsi:type="ts:TS_string" flags = "0x0000">
						<c:Value>ATML5</c:Value>
					</c:Datum>
				</c:Item>
				<c:Item name = "ReportFileSequentialModelExpression">
					<c:Datum xsi:type="ts:TS_string" flags = "0x0000">
						<c:Value><![CDATA["<ClientFileDir>\\TestReport_<ClientFileName>\\<ClientFileName>_Report[<UUT>][<FileTime>][<FileDate>][<UUTStatus>]<Unique>.<FileExtension>"]]></c:Value>
					</c:Datum>
				</c:Item>
				<c:Item name = "ReportFileParallelModelExpression">
					<c:Datum xsi:type="ts:TS_string" flags = "0x0000">
						<c:Value><![CDATA["<ClientFileDir>\\<ClientFileName>_Report[<FileTime>][<FileDate>]<Unique>.<FileExtension>"]]></c:Value>
					</c:Datum>
				</c:Item>
				<c:Item name = "ReportFileBatchModelExpression">
					<c:Datum xsi:type="ts:TS_string" flags = "0x0000">
						<c:Value><![CDATA["<ClientFileDir>\\<ClientFileName>_BatchReport[<FileTime>][<FileDate>]<Unique>.<FileExtension>"]]></c:Value>
					</c:Datum>
				</c:Item>
				<c:Item name = "BatchFileBatchModelExpression">
					<c:Datum xsi:type="ts:TS_string" flags = "0x0000">
						<c:Value><![CDATA["<ClientFileDir>\\<ClientFileName>_BatchReport[<FileTime>][<FileDate>]<Unique>.<FileExtension>"]]></c:Value>
					</c:Datum>
				</c:Item>
				<c:Item name = "NewFileNameForEachUUTStatus">
					<c:Datum value = "true" xsi:type="ts:TS_boolean" flags = "0x0000"/>
				</c:Item>
				<c:Item name = "ReportPathMacroListString">
					<c:Datum xsi:type="ts:TS_string" flags = "0x0000">
						<c:Value><![CDATA[<CLIENTFILEDIR><CLIENTFILENAME><CLIENTFILENAME><UUT><FILETIME><FILEDATE><UUTSTATUS><UNIQUE><FILEEXTENSION>]]></c:Value>
					</c:Datum>
				</c:Item>
				<c:Item name = "BatchReportPathMacroListString">
					<c:Datum xsi:type="ts:TS_string" flags = "0x0000">
						<c:Value></c:Value>
					</c:Datum>
				</c:Item>
				<c:Item name = "CheckIfMacroListIsUnchanged">
					<c:Datum value = "true" xsi:type="ts:TS_boolean" flags = "0x0000"/>
				</c:Item>
				<c:Item name = "ATML5StylesheetMRU">
					<c:IndexedArray dimensions="[3]" lowerBounds="[0]" upperBounds="[2]" xsi:type="ts:TS_stringArray" flags = "0x0000">
						<ts:Element position ="[0]">
							<c:Value>tr5_horizontal.xsl</c:Value>
						</ts:Element>
						<ts:Element position ="[1]">
							<c:Value>tr5_report.xsl</c:Value>
						</ts:Element>
						<ts:Element position ="[2]">
							<c:Value>tr5_expand.xsl</c:Value>
						</ts:Element>
					</c:IndexedArray>
				</c:Item>
				<c:Item name = "Atml_Rpt_Options">
					<c:Collection xsi:type="ts:TS_Collection" flags = "0x0000">
						<c:Item name = "AddReportText">
							<c:Datum value = "true" xsi:type="ts:TS_boolean" flags = "0x0000"/>
						</c:Item>
						<c:Item name = "ExtensionDLLAbsolutePath">
							<c:Datum xsi:type="ts:TS_string" flags = "0x0000">
								<c:Value></c:Value>
							</c:Datum>
						</c:Item>
						<c:Item name = "TestResultsSchemaPath">
							<c:Datum xsi:type="ts:TS_string" flags = "0x0000">
								<c:Value></c:Value>
							</c:Datum>
						</c:Item>
					</c:Collection>
				</c:Item>
			</c:Collection>
		</tr:Configuration>
	</tr:TestProgram>
	<tr:TestStation>
		<c:SerialNumber>CFTP7</c:SerialNumber>
	</tr:TestStation>
	<tr:UUT>
		<c:SerialNumber>10041194-RA20346333</c:SerialNumber>
	</tr:UUT>
	<tr:Extension>
		<ts:TSResultSetProperties>
			<ts:NumOfResults value = '15'/>
		</ts:TSResultSetProperties>
	</tr:Extension>
</trc:TestResults>
</trc:TestResultsCollection>
